Workbook
Name Laadmeters: #REF!
Name Postcode: #REF!
Name Tarieven: #REF!

Sheet Voorblad
A3: Offerte
A5: Team Freight Forwarding Logistics | E5: XPO Logistics Netherlands B.V.
A6: Marconiweg 14 | E6: Lagelandseweg 70
A7: 8501 XM Joure | E7: 6545 CG Nijmegen (NL)
A8: operations@tfflogistics.com | E8: Tel: +31 (0)24-372 4680
E9: sales.nl@xpo.com
A13: Laadadres (tenzij anders vermeld) | E13: Losadres (tenzij anders vermeld)
A14: NL (ex Waddeneilanden) | E14: te bevestigen op order
A17: Tarieven zijn geldig t/m 30-06-2026
A18: Tarieven zijn enkel geldig na schriftelijk akkoord binnen 14 dagen na dagtekening van toesturen van offertes.
A19: Voor onze algemene voorwaarden en toeslagen en condities verwijzen wij u naar de overige tabbladen.
A21: Akkoord voor tarieven en Algemene voorwaarden en condities:
A23: Handtekening | C23: =A5 -> Team Freight Forwarding Logistics

Sheet AT
A3: =Voorblad!A5 -> Team Freight Forwarding Logistics
A4: Export Oostenrijk
A6: kg | B6: ldm | C6: euplt | D6: blkplt | E6: 10 | F6: 11 | G6: 12 | H6: 13 | I6: 20 | J6: 21 | K6: 22 | L6: 23 | M6: 24 | N6: 25 | O6: 26 | P6: 27 | Q6: 28 | R6: 30 | S6: 31 | T6: 32 | U6: 33 | V6: 34 | W6: 35 | X6: 36 | Y6: 37 | Z6: 38 | AA6: 39 | AB6: 40 | AC6: 41 | AD6: 42 | AE6: 43 | AF6: 44 | AG6: 45 | AH6: 46 | AI6: 47 | AJ6: 48 | AK6: 49 | AL6: 50 | AM6: 51 | AN6: 52 | AO6: 53 | AP6: 54 | AQ6: 55 | AR6: 56 | AS6: 57 | AT6: 60 | AU6: 61 | AV6: 62 | AW6: 63 | AX6: 64 | AY6: 65 | AZ6: 66 | BA6: 67 | BB6: 68 | BC6: 69 | BD6: 70 | BE6: 71 | BF6: 72 | BG6: 73 | BH6: 74 | BI6: 75 | BJ6: 80 | BK6: 81 | BL6: 82 | BM6: 83 | BN6: 84 | BO6: 85 | BP6: 86 | BQ6: 87 | BR6: 88 | BS6: 89 | BT6: 90 | BU6: 91 | BV6: 92 | BW6: 93 | BX6: 94 | BY6: 95 | BZ6: 96 | CA6: 97 | CB6: 98 | CC6: 99
A7: 300 | B7: 0.2 | C7: 0.5 | E7: 235 | F7: 235 | G7: 235 | H7: 235 | I7: 235 | J7: 235 | K7: 235 | L7: 235 | M7: 235 | N7: 235 | O7: 235 | P7: 235 | Q7: 235 | R7: 235 | S7: 235 | T7: 235 | U7: 235 | V7: 235 | W7: 235 | X7: 235 | Y7: 235 | Z7: 235 | AA7: 235 | AB7: 230 | AC7: 230 | AD7: 230 | AE7: 230 | AF7: 230 | AG7: 230 | AH7: 230 | AI7: 230 | AJ7: 230 | AK7: 230 | AL7: 230 | AM7: 230 | AN7: 230 | AO7: 230 | AP7: 230 | AQ7: 230 | AR7: 230 | AS7: 230 | AT7: 230 | AU7: 230 | AV7: 230 | AW7: 230 | AX7: 230 | AY7: 230 | AZ7: 230 | BA7: 230 | BB7: 230 | BC7: 230 | BD7: 255 | BE7: 255 | BF7: 255 | BG7: 255 | BH7: 255 | BI7: 255 | BJ7: 255 | BK7: 255 | BL7: 255 | BM7: 255 | BN7: 255 | BO7: 255 | BP7: 255 | BQ7: 255 | BR7: 255 | BS7: 255 | BT7: 275 | BU7: 275 | BV7: 275 | BW7: 275 | BX7: 275 | BY7: 275 | BZ7: 275 | CA7: 275 | CB7: 275 | CC7: 275
A8: 700 | B8: 0.4 | C8: 1 | E8: 235 | F8: 235 | G8: 235 | H8: 235 | I8: 235 | J8: 235 | K8: 235 | L8: 235 | M8: 235 | N8: 235 | O8: 235 | P8: 235 | Q8: 235 | R8: 235 | S8: 235 | T8: 235 | U8: 235 | V8: 235 | W8: 235 | X8: 235 | Y8: 235 | Z8: 235 | AA8: 235 | AB8: 230 | AC8: 230 | AD8: 230 | AE8: 230 | AF8: 230 | AG8: 230 | AH8: 230 | AI8: 230 | AJ8: 230 | AK8: 230 | AL8: 230 | AM8: 230 | AN8: 230 | AO8: 230 | AP8: 230 | AQ8: 230 | AR8: 230 | AS8: 230 | AT8: 230 | AU8: 230 | AV8: 230 | AW8: 230 | AX8: 230 | AY8: 230 | AZ8: 230 | BA8: 230 | BB8: 230 | BC8: 230 | BD8: 255 | BE8: 255 | BF8: 255 | BG8: 255 | BH8: 255 | BI8: 255 | BJ8: 255 | BK8: 255 | BL8: 255 | BM8: 255 | BN8: 255 | BO8: 255 | BP8: 255 | BQ8: 255 | BR8: 255 | BS8: 255 | BT8: 275 | BU8: 275 | BV8: 275 | BW8: 275 | BX8: 275 | BY8: 275 | BZ8: 275 | CA8: 275 | CB8: 275 | CC8: 275
A9: 875 | B9: 0.5 | D9: 1 | E9: 257 | F9: 257 | G9: 257 | H9: 257 | I9: 257 | J9: 257 | K9: 257 | L9: 257 | M9: 257 | N9: 257 | O9: 257 | P9: 257 | Q9: 257 | R9: 257 | S9: 257 | T9: 257 | U9: 257 | V9: 257 | W9: 257 | X9: 257 | Y9: 257 | Z9: 257 | AA9: 257 | AB9: 247 | AC9: 247 | AD9: 247 | AE9: 247 | AF9: 247 | AG9: 247 | AH9: 247 | AI9: 247 | AJ9: 247 | AK9: 247 | AL9: 247 | AM9: 247 | AN9: 247 | AO9: 247 | AP9: 247 | AQ9: 247 | AR9: 247 | AS9: 247 | AT9: 247 | AU9: 247 | AV9: 247 | AW9: 247 | AX9: 247 | AY9: 247 | AZ9: 247 | BA9: 247 | BB9: 247 | BC9: 247 | BD9: 277 | BE9: 277 | BF9: 277 | BG9: 277 | BH9: 277 | BI9: 277 | BJ9: 277 | BK9: 277 | BL9: 277 | BM9: 277 | BN9: 277 | BO9: 277 | BP9: 277 | BQ9: 277 | BR9: 277 | BS9: 277 | BT9: 303 | BU9: 303 | BV9: 303 | BW9: 303 | BX9: 303 | BY9: 303 | BZ9: 303 | CA9: 303 | CB9: 303 | CC9: 303
A10: 1050 | B10: 0.6 | E10: 304 | F10: 304 | G10: 304 | H10: 304 | I10: 304 | J10: 304 | K10: 304 | L10: 304 | M10: 304 | N10: 304 | O10: 304 | P10: 304 | Q10: 304 | R10: 304 | S10: 304 | T10: 304 | U10: 304 | V10: 304 | W10: 304 | X10: 304 | Y10: 304 | Z10: 304 | AA10: 304 | AB10: 265 | AC10: 265 | AD10: 265 | AE10: 265 | AF10: 265 | AG10: 265 | AH10: 265 | AI10: 265 | AJ10: 265 | AK10: 265 | AL10: 265 | AM10: 265 | AN10: 265 | AO10: 265 | AP10: 265 | AQ10: 265 | AR10: 265 | AS10: 265 | AT10: 284 | AU10: 284 | AV10: 284 | AW10: 284 | AX10: 284 | AY10: 284 | AZ10: 284 | BA10: 284 | BB10: 284 | BC10: 284 | BD10: 304 | BE10: 304 | BF10: 304 | BG10: 304 | BH10: 304 | BI10: 304 | BJ10: 319 | BK10: 319 | BL10: 319 | BM10: 319 | BN10: 319 | BO10: 319 | BP10: 319 | BQ10: 319 | BR10: 319 | BS10: 319 | BT10: 340 | BU10: 340 | BV10: 340 | BW10: 340 | BX10: 340 | BY10: 340 | BZ10: 340 | CA10: 340 | CB10: 340 | CC10: 340
A11: 1400 | B11: 0.8 | C11: 2 | E11: 371 | F11: 371 | G11: 371 | H11: 371 | I11: 371 | J11: 371 | K11: 371 | L11: 371 | M11: 371 | N11: 371 | O11: 371 | P11: 371 | Q11: 371 | R11: 371 | S11: 371 | T11: 371 | U11: 371 | V11: 371 | W11: 371 | X11: 371 | Y11: 371 | Z11: 371 | AA11: 371 | AB11: 290 | AC11: 290 | AD11: 290 | AE11: 290 | AF11: 290 | AG11: 290 | AH11: 290 | AI11: 290 | AJ11: 290 | AK11: 290 | AL11: 290 | AM11: 290 | AN11: 290 | AO11: 290 | AP11: 290 | AQ11: 290 | AR11: 290 | AS11: 290 | AT11: 345 | AU11: 345 | AV11: 345 | AW11: 345 | AX11: 345 | AY11: 345 | AZ11: 345 | BA11: 345 | BB11: 345 | BC11: 345 | BD11: 371 | BE11: 371 | BF11: 371 | BG11: 371 | BH11: 371 | BI11: 371 | BJ11: 391 | BK11: 391 | BL11: 391 | BM11: 391 | BN11: 391 | BO11: 391 | BP11: 391 | BQ11: 391 | BR11: 391 | BS11: 391 | BT11: 412 | BU11: 412 | BV11: 412 | BW11: 412 | BX11: 412 | BY11: 412 | BZ11: 412 | CA11: 412 | CB11: 412 | CC11: 412
A12: 1750 | B12: 1 | D12: 2 | E12: 448 | F12: 448 | G12: 448 | H12: 448 | I12: 448 | J12: 448 | K12: 448 | L12: 448 | M12: 448 | N12: 448 | O12: 448 | P12: 448 | Q12: 448 | R12: 448 | S12: 448 | T12: 448 | U12: 448 | V12: 448 | W12: 448 | X12: 448 | Y12: 448 | Z12: 448 | AA12: 448 | AB12: 359 | AC12: 359 | AD12: 359 | AE12: 359 | AF12: 359 | AG12: 359 | AH12: 359 | AI12: 359 | AJ12: 359 | AK12: 359 | AL12: 359 | AM12: 359 | AN12: 359 | AO12: 359 | AP12: 359 | AQ12: 359 | AR12: 359 | AS12: 359 | AT12: 415 | AU12: 415 | AV12: 415 | AW12: 415 | AX12: 415 | AY12: 415 | AZ12: 415 | BA12: 415 | BB12: 415 | BC12: 415 | BD12: 448 | BE12: 448 | BF12: 448 | BG12: 448 | BH12: 448 | BI12: 448 | BJ12: 463 | BK12: 463 | BL12: 463 | BM12: 463 | BN12: 463 | BO12: 463 | BP12: 463 | BQ12: 463 | BR12: 463 | BS12: 463 | BT12: 487 | BU12: 487 | BV12: 487 | BW12: 487 | BX12: 487 | BY12: 487 | BZ12: 487 | CA12: 487 | CB12: 487 | CC12: 487
A13: 2100 | B13: 1.2 | C13: 3 | E13: 472 | F13: 472 | G13: 472 | H13: 472 | I13: 472 | J13: 472 | K13: 472 | L13: 472 | M13: 472 | N13: 472 | O13: 472 | P13: 472 | Q13: 472 | R13: 472 | S13: 472 | T13: 472 | U13: 472 | V13: 472 | W13: 472 | X13: 472 | Y13: 472 | Z13: 472 | AA13: 472 | AB13: 384 | AC13: 384 | AD13: 384 | AE13: 384 | AF13: 384 | AG13: 384 | AH13: 384 | AI13: 384 | AJ13: 384 | AK13: 384 | AL13: 384 | AM13: 384 | AN13: 384 | AO13: 384 | AP13: 384 | AQ13: 384 | AR13: 384 | AS13: 384 | AT13: 456 | AU13: 456 | AV13: 456 | AW13: 456 | AX13: 456 | AY13: 456 | AZ13: 456 | BA13: 456 | BB13: 456 | BC13: 456 | BD13: 472 | BE13: 472 | BF13: 472 | BG13: 472 | BH13: 472 | BI13: 472 | BJ13: 489 | BK13: 489 | BL13: 489 | BM13: 489 | BN13: 489 | BO13: 489 | BP13: 489 | BQ13: 489 | BR13: 489 | BS13: 489 | BT13: 512 | BU13: 512 | BV13: 512 | BW13: 512 | BX13: 512 | BY13: 512 | BZ13: 512 | CA13: 512 | CB13: 512 | CC13: 512
A14: 2625 | B14: 1.5 | D14: 3 | E14: 550 | F14: 550 | G14: 550 | H14: 550 | I14: 550 | J14: 550 | K14: 550 | L14: 550 | M14: 550 | N14: 550 | O14: 550 | P14: 550 | Q14: 550 | R14: 550 | S14: 550 | T14: 550 | U14: 550 | V14: 550 | W14: 550 | X14: 550 | Y14: 550 | Z14: 550 | AA14: 550 | AB14: 463 | AC14: 463 | AD14: 463 | AE14: 463 | AF14: 463 | AG14: 463 | AH14: 463 | AI14: 463 | AJ14: 463 | AK14: 463 | AL14: 463 | AM14: 463 | AN14: 463 | AO14: 463 | AP14: 463 | AQ14: 463 | AR14: 463 | AS14: 463 | AT14: 527 | AU14: 527 | AV14: 527 | AW14: 527 | AX14: 527 | AY14: 527 | AZ14: 527 | BA14: 527 | BB14: 527 | BC14: 527 | BD14: 550 | BE14: 550 | BF14: 550 | BG14: 550 | BH14: 550 | BI14: 550 | BJ14: 574 | BK14: 574 | BL14: 574 | BM14: 574 | BN14: 574 | BO14: 574 | BP14: 574 | BQ14: 574 | BR14: 574 | BS14: 574 | BT14: 591 | BU14: 591 | BV14: 591 | BW14: 591 | BX14: 591 | BY14: 591 | BZ14: 591 | CA14: 591 | CB14: 591 | CC14: 591
A15: 2800 | B15: 1.6 | C15: 4 | E15: 561 | F15: 561 | G15: 561 | H15: 561 | I15: 561 | J15: 561 | K15: 561 | L15: 561 | M15: 561 | N15: 561 | O15: 561 | P15: 561 | Q15: 561 | R15: 561 | S15: 561 | T15: 561 | U15: 561 | V15: 561 | W15: 561 | X15: 561 | Y15: 561 | Z15: 561 | AA15: 561 | AB15: 466 | AC15: 466 | AD15: 466 | AE15: 466 | AF15: 466 | AG15: 466 | AH15: 466 | AI15: 466 | AJ15: 466 | AK15: 466 | AL15: 466 | AM15: 466 | AN15: 466 | AO15: 466 | AP15: 466 | AQ15: 466 | AR15: 466 | AS15: 466 | AT15: 536 | AU15: 536 | AV15: 536 | AW15: 536 | AX15: 536 | AY15: 536 | AZ15: 536 | BA15: 536 | BB15: 536 | BC15: 536 | BD15: 561 | BE15: 561 | BF15: 561 | BG15: 561 | BH15: 561 | BI15: 561 | BJ15: 615 | BK15: 615 | BL15: 615 | BM15: 615 | BN15: 615 | BO15: 615 | BP15: 615 | BQ15: 615 | BR15: 615 | BS15: 615 | BT15: 631 | BU15: 631 | BV15: 631 | BW15: 631 | BX15: 631 | BY15: 631 | BZ15: 631 | CA15: 631 | CB15: 631 | CC15: 631
A16: 3500 | B16: 2 | C16: 5 | D16: 4 | E16: 654 | F16: 654 | G16: 654 | H16: 654 | I16: 654 | J16: 654 | K16: 654 | L16: 654 | M16: 654 | N16: 654 | O16: 654 | P16: 654 | Q16: 654 | R16: 654 | S16: 654 | T16: 654 | U16: 654 | V16: 654 | W16: 654 | X16: 654 | Y16: 654 | Z16: 654 | AA16: 654 | AB16: 561 | AC16: 561 | AD16: 561 | AE16: 561 | AF16: 561 | AG16: 561 | AH16: 561 | AI16: 561 | AJ16: 561 | AK16: 561 | AL16: 561 | AM16: 561 | AN16: 561 | AO16: 561 | AP16: 561 | AQ16: 561 | AR16: 561 | AS16: 561 | AT16: 623 | AU16: 623 | AV16: 623 | AW16: 623 | AX16: 623 | AY16: 623 | AZ16: 623 | BA16: 623 | BB16: 623 | BC16: 623 | BD16: 654 | BE16: 654 | BF16: 654 | BG16: 654 | BH16: 654 | BI16: 654 | BJ16: 686 | BK16: 686 | BL16: 686 | BM16: 686 | BN16: 686 | BO16: 686 | BP16: 686 | BQ16: 686 | BR16: 686 | BS16: 686 | BT16: 702 | BU16: 702 | BV16: 702 | BW16: 702 | BX16: 702 | BY16: 702 | BZ16: 702 | CA16: 702 | CB16: 702 | CC16: 702
A17: 4200 | B17: 2.4 | C17: 6 | E17: 743 | F17: 743 | G17: 743 | H17: 743 | I17: 743 | J17: 743 | K17: 743 | L17: 743 | M17: 743 | N17: 743 | O17: 743 | P17: 743 | Q17: 743 | R17: 743 | S17: 743 | T17: 743 | U17: 743 | V17: 743 | W17: 743 | X17: 743 | Y17: 743 | Z17: 743 | AA17: 743 | AB17: 614 | AC17: 614 | AD17: 614 | AE17: 614 | AF17: 614 | AG17: 614 | AH17: 614 | AI17: 614 | AJ17: 614 | AK17: 614 | AL17: 614 | AM17: 614 | AN17: 614 | AO17: 614 | AP17: 614 | AQ17: 614 | AR17: 614 | AS17: 614 | AT17: 687 | AU17: 687 | AV17: 687 | AW17: 687 | AX17: 687 | AY17: 687 | AZ17: 687 | BA17: 687 | BB17: 687 | BC17: 687 | BD17: 743 | BE17: 743 | BF17: 743 | BG17: 743 | BH17: 743 | BI17: 743 | BJ17: 762 | BK17: 762 | BL17: 762 | BM17: 762 | BN17: 762 | BO17: 762 | BP17: 762 | BQ17: 762 | BR17: 762 | BS17: 762 | BT17: 774 | BU17: 774 | BV17: 774 | BW17: 774 | BX17: 774 | BY17: 774 | BZ17: 774 | CA17: 774 | CB17: 774 | CC17: 774
A18: 4375 | B18: 2.5 | D18: 5 | E18: 760 | F18: 760 | G18: 760 | H18: 760 | I18: 760 | J18: 760 | K18: 760 | L18: 760 | M18: 760 | N18: 760 | O18: 760 | P18: 760 | Q18: 760 | R18: 760 | S18: 760 | T18: 760 | U18: 760 | V18: 760 | W18: 760 | X18: 760 | Y18: 760 | Z18: 760 | AA18: 760 | AB18: 617 | AC18: 617 | AD18: 617 | AE18: 617 | AF18: 617 | AG18: 617 | AH18: 617 | AI18: 617 | AJ18: 617 | AK18: 617 | AL18: 617 | AM18: 617 | AN18: 617 | AO18: 617 | AP18: 617 | AQ18: 617 | AR18: 617 | AS18: 617 | AT18: 699 | AU18: 699 | AV18: 699 | AW18: 699 | AX18: 699 | AY18: 699 | AZ18: 699 | BA18: 699 | BB18: 699 | BC18: 699 | BD18: 760 | BE18: 760 | BF18: 760 | BG18: 760 | BH18: 760 | BI18: 760 | BJ18: 774 | BK18: 774 | BL18: 774 | BM18: 774 | BN18: 774 | BO18: 774 | BP18: 774 | BQ18: 774 | BR18: 774 | BS18: 774 | BT18: 791 | BU18: 791 | BV18: 791 | BW18: 791 | BX18: 791 | BY18: 791 | BZ18: 791 | CA18: 791 | CB18: 791 | CC18: 791
A19: 4900 | B19: 2.8 | C19: 7 | E19: 774 | F19: 774 | G19: 774 | H19: 774 | I19: 774 | J19: 774 | K19: 774 | L19: 774 | M19: 774 | N19: 774 | O19: 774 | P19: 774 | Q19: 774 | R19: 774 | S19: 774 | T19: 774 | U19: 774 | V19: 774 | W19: 774 | X19: 774 | Y19: 774 | Z19: 774 | AA19: 774 | AB19: 638 | AC19: 638 | AD19: 638 | AE19: 638 | AF19: 638 | AG19: 638 | AH19: 638 | AI19: 638 | AJ19: 638 | AK19: 638 | AL19: 638 | AM19: 638 | AN19: 638 | AO19: 638 | AP19: 638 | AQ19: 638 | AR19: 638 | AS19: 638 | AT19: 707 | AU19: 707 | AV19: 707 | AW19: 707 | AX19: 707 | AY19: 707 | AZ19: 707 | BA19: 707 | BB19: 707 | BC19: 707 | BD19: 774 | BE19: 774 | BF19: 774 | BG19: 774 | BH19: 774 | BI19: 774 | BJ19: 799 | BK19: 799 | BL19: 799 | BM19: 799 | BN19: 799 | BO19: 799 | BP19: 799 | BQ19: 799 | BR19: 799 | BS19: 799 | BT19: 821 | BU19: 821 | BV19: 821 | BW19: 821 | BX19: 821 | BY19: 821 | BZ19: 821 | CA19: 821 | CB19: 821 | CC19: 821
A20: 5250 | B20: 3 | D20: 6 | E20: 809 | F20: 809 | G20: 809 | H20: 809 | I20: 809 | J20: 809 | K20: 809 | L20: 809 | M20: 809 | N20: 809 | O20: 809 | P20: 809 | Q20: 809 | R20: 809 | S20: 809 | T20: 809 | U20: 809 | V20: 809 | W20: 809 | X20: 809 | Y20: 809 | Z20: 809 | AA20: 809 | AB20: 644 | AC20: 644 | AD20: 644 | AE20: 644 | AF20: 644 | AG20: 644 | AH20: 644 | AI20: 644 | AJ20: 644 | AK20: 644 | AL20: 644 | AM20: 644 | AN20: 644 | AO20: 644 | AP20: 644 | AQ20: 644 | AR20: 644 | AS20: 644 | AT20: 716 | AU20: 716 | AV20: 716 | AW20: 716 | AX20: 716 | AY20: 716 | AZ20: 716 | BA20: 716 | BB20: 716 | BC20: 716 | BD20: 809 | BE20: 809 | BF20: 809 | BG20: 809 | BH20: 809 | BI20: 809 | BJ20: 836 | BK20: 836 | BL20: 836 | BM20: 836 | BN20: 836 | BO20: 836 | BP20: 836 | BQ20: 836 | BR20: 836 | BS20: 836 | BT20: 854 | BU20: 854 | BV20: 854 | BW20: 854 | BX20: 854 | BY20: 854 | BZ20: 854 | CA20: 854 | CB20: 854 | CC20: 854
A21: 5600 | B21: 3.2 | C21: 8 | E21: 839 | F21: 839 | G21: 839 | H21: 839 | I21: 839 | J21: 839 | K21: 839 | L21: 839 | M21: 839 | N21: 839 | O21: 839 | P21: 839 | Q21: 839 | R21: 839 | S21: 839 | T21: 839 | U21: 839 | V21: 839 | W21: 839 | X21: 839 | Y21: 839 | Z21: 839 | AA21: 839 | AB21: 690 | AC21: 690 | AD21: 690 | AE21: 690 | AF21: 690 | AG21: 690 | AH21: 690 | AI21: 690 | AJ21: 690 | AK21: 690 | AL21: 690 | AM21: 690 | AN21: 690 | AO21: 690 | AP21: 690 | AQ21: 690 | AR21: 690 | AS21: 690 | AT21: 740 | AU21: 740 | AV21: 740 | AW21: 740 | AX21: 740 | AY21: 740 | AZ21: 740 | BA21: 740 | BB21: 740 | BC21: 740 | BD21: 839 | BE21: 839 | BF21: 839 | BG21: 839 | BH21: 839 | BI21: 839 | BJ21: 870 | BK21: 870 | BL21: 870 | BM21: 870 | BN21: 870 | BO21: 870 | BP21: 870 | BQ21: 870 | BR21: 870 | BS21: 870 | BT21: 885 | BU21: 885 | BV21: 885 | BW21: 885 | BX21: 885 | BY21: 885 | BZ21: 885 | CA21: 885 | CB21: 885 | CC21: 885
A22: 6125 | B22: 3.5 | D22: 7 | E22: 863 | F22: 863 | G22: 863 | H22: 863 | I22: 863 | J22: 863 | K22: 863 | L22: 863 | M22: 863 | N22: 863 | O22: 863 | P22: 863 | Q22: 863 | R22: 863 | S22: 863 | T22: 863 | U22: 863 | V22: 863 | W22: 863 | X22: 863 | Y22: 863 | Z22: 863 | AA22: 863 | AB22: 732 | AC22: 732 | AD22: 732 | AE22: 732 | AF22: 732 | AG22: 732 | AH22: 732 | AI22: 732 | AJ22: 732 | AK22: 732 | AL22: 732 | AM22: 732 | AN22: 732 | AO22: 732 | AP22: 732 | AQ22: 732 | AR22: 732 | AS22: 732 | AT22: 770 | AU22: 770 | AV22: 770 | AW22: 770 | AX22: 770 | AY22: 770 | AZ22: 770 | BA22: 770 | BB22: 770 | BC22: 770 | BD22: 863 | BE22: 863 | BF22: 863 | BG22: 863 | BH22: 863 | BI22: 863 | BJ22: 893 | BK22: 893 | BL22: 893 | BM22: 893 | BN22: 893 | BO22: 893 | BP22: 893 | BQ22: 893 | BR22: 893 | BS22: 893 | BT22: 894 | BU22: 894 | BV22: 894 | BW22: 894 | BX22: 894 | BY22: 894 | BZ22: 894 | CA22: 894 | CB22: 894 | CC22: 894
A23: 6300 | B23: 3.6 | C23: 9 | E23: 893 | F23: 893 | G23: 893 | H23: 893 | I23: 893 | J23: 893 | K23: 893 | L23: 893 | M23: 893 | N23: 893 | O23: 893 | P23: 893 | Q23: 893 | R23: 893 | S23: 893 | T23: 893 | U23: 893 | V23: 893 | W23: 893 | X23: 893 | Y23: 893 | Z23: 893 | AA23: 893 | AB23: 748 | AC23: 748 | AD23: 748 | AE23: 748 | AF23: 748 | AG23: 748 | AH23: 748 | AI23: 748 | AJ23: 748 | AK23: 748 | AL23: 748 | AM23: 748 | AN23: 748 | AO23: 748 | AP23: 748 | AQ23: 748 | AR23: 748 | AS23: 748 | AT23: 804 | AU23: 804 | AV23: 804 | AW23: 804 | AX23: 804 | AY23: 804 | AZ23: 804 | BA23: 804 | BB23: 804 | BC23: 804 | BD23: 893 | BE23: 893 | BF23: 893 | BG23: 893 | BH23: 893 | BI23: 893 | BJ23: 915 | BK23: 915 | BL23: 915 | BM23: 915 | BN23: 915 | BO23: 915 | BP23: 915 | BQ23: 915 | BR23: 915 | BS23: 915 | BT23: 910 | BU23: 910 | BV23: 910 | BW23: 910 | BX23: 910 | BY23: 910 | BZ23: 910 | CA23: 910 | CB23: 910 | CC23: 910
A24: 7000 | B24: 4 | C24: 10 | D24: 8 | E24: 940 | F24: 940 | G24: 940 | H24: 940 | I24: 940 | J24: 940 | K24: 940 | L24: 940 | M24: 940 | N24: 940 | O24: 940 | P24: 940 | Q24: 940 | R24: 940 | S24: 940 | T24: 940 | U24: 940 | V24: 940 | W24: 940 | X24: 940 | Y24: 940 | Z24: 940 | AA24: 940 | AB24: 793 | AC24: 793 | AD24: 793 | AE24: 793 | AF24: 793 | AG24: 793 | AH24: 793 | AI24: 793 | AJ24: 793 | AK24: 793 | AL24: 793 | AM24: 793 | AN24: 793 | AO24: 793 | AP24: 793 | AQ24: 793 | AR24: 793 | AS24: 793 | AT24: 840 | AU24: 840 | AV24: 840 | AW24: 840 | AX24: 840 | AY24: 840 | AZ24: 840 | BA24: 840 | BB24: 840 | BC24: 840 | BD24: 940 | BE24: 940 | BF24: 940 | BG24: 940 | BH24: 940 | BI24: 940 | BJ24: 969 | BK24: 969 | BL24: 969 | BM24: 969 | BN24: 969 | BO24: 969 | BP24: 969 | BQ24: 969 | BR24: 969 | BS24: 969 | BT24: 985 | BU24: 985 | BV24: 985 | BW24: 985 | BX24: 985 | BY24: 985 | BZ24: 985 | CA24: 985 | CB24: 985 | CC24: 985
A26: Transittijden:
A28: Dag van lading is dag 0 | C28: Vertrek | G28: Transittijd in werkdagen | T28: Transittijd in werkdagen | AG28: Transittijd in werkdagen | AT28: Transittijd in werkdagen | BG28: Transittijd in werkdagen | BT28: Transittijd in werkdagen
A29: Groupage 1-5 pallets | C29: ma,di,wo,do,vrij | E29: 2/3 | F29: 2/3 | G29: 2/3 | H29: 2/3 | I29: 2/3 | J29: 2/3 | K29: 2/3 | L29: 2/3 | M29: 2/3 | N29: 2/3 | O29: 2/3 | P29: 2/3 | Q29: 2/3 | R29: 2/3 | S29: 2/3 | T29: 2/3 | U29: 2/3 | V29: 2/3 | W29: 2/3 | X29: 2/3 | Y29: 2/3 | Z29: 2/3 | AA29: 2/3 | AB29: 2/3 | AC29: 2/3 | AD29: 2/3 | AE29: 2/3 | AF29: 2/3 | AG29: 2/3 | AH29: 2/3 | AI29: 2/3 | AJ29: 2/3 | AK29: 2/3 | AL29: 2/3 | AM29: 2/3 | AN29: 2/3 | AO29: 2/3 | AP29: 2/3 | AQ29: 2/3 | AR29: 2/3 | AS29: 2/3 | AT29: 3/4 | AU29: 3/4 | AV29: 3/4 | AW29: 3/4 | AX29: 3/4 | AY29: 3/4 | AZ29: 3/4 | BA29: 3/4 | BB29: 3/4 | BC29: 3/4 | BD29: 2/3 | BE29: 2/3 | BF29: 2/3 | BG29: 2/3 | BH29: 2/3 | BI29: 2/3 | BJ29: 2/3 | BK29: 2/3 | BL29: 2/3 | BM29: 2/3 | BN29: 2/3 | BO29: 2/3 | BP29: 2/3 | BQ29: 2/3 | BR29: 2/3 | BS29: 2/3 | BT29: 3/4 | BU29: 3/4 | BV29: 3/4 | BW29: 3/4 | BX29: 3/4 | BY29: 3/4 | BZ29: 3/4 | CA29: 3/4 | CB29: 3/4 | CC29: 3/4
A30: Deelpartijen > 5 pallets | C30: ma,di,wo,do,vrij | E30: 2 | F30: 2 | G30: 2 | H30: 2 | I30: 2 | J30: 2 | K30: 2 | L30: 2 | M30: 2 | N30: 2 | O30: 2 | P30: 2 | Q30: 2 | R30: 2 | S30: 2 | T30: 2 | U30: 2 | V30: 2 | W30: 2 | X30: 2 | Y30: 2 | Z30: 2 | AA30: 2 | AB30: 2 | AC30: 2 | AD30: 2 | AE30: 2 | AF30: 2 | AG30: 2 | AH30: 2 | AI30: 2 | AJ30: 2 | AK30: 2 | AL30: 2 | AM30: 2 | AN30: 2 | AO30: 2 | AP30: 2 | AQ30: 2 | AR30: 2 | AS30: 2 | AT30: 3 | AU30: 3 | AV30: 3 | AW30: 3 | AX30: 3 | AY30: 3 | AZ30: 3 | BA30: 3 | BB30: 3 | BC30: 3 | BD30: 2 | BE30: 2 | BF30: 2 | BG30: 2 | BH30: 2 | BI30: 2 | BJ30: 2 | BK30: 2 | BL30: 2 | BM30: 2 | BN30: 2 | BO30: 2 | BP30: 2 | BQ30: 2 | BR30: 2 | BS30: 2 | BT30: 3 | BU30: 3 | BV30: 3 | BW30: 3 | BX30: 3 | BY30: 3 | BZ30: 3 | CA30: 3 | CB30: 3 | CC30: 3
A31: Compleet ladingen | C31: ma,di,wo,do,vrij | E31: 1/2 | F31: 1/2 | G31: 1/2 | H31: 1/2 | I31: 1/2 | J31: 1/2 | K31: 1/2 | L31: 1/2 | M31: 1/2 | N31: 1/2 | O31: 1/2 | P31: 1/2 | Q31: 1/2 | R31: 1/2 | S31: 1/2 | T31: 1/2 | U31: 1/2 | V31: 1/2 | W31: 1/2 | X31: 1/2 | Y31: 1/2 | Z31: 1/2 | AA31: 1/2 | AB31: 1/2 | AC31: 1/2 | AD31: 1/2 | AE31: 1/2 | AF31: 1/2 | AG31: 1/2 | AH31: 1/2 | AI31: 1/2 | AJ31: 1/2 | AK31: 1/2 | AL31: 1/2 | AM31: 1/2 | AN31: 1/2 | AO31: 1/2 | AP31: 1/2 | AQ31: 1/2 | AR31: 1/2 | AS31: 1/2 | AT31: 2/3 | AU31: 2/3 | AV31: 2/3 | AW31: 2/3 | AX31: 2/3 | AY31: 2/3 | AZ31: 2/3 | BA31: 2/3 | BB31: 2/3 | BC31: 2/3 | BD31: 1/2 | BE31: 1/2 | BF31: 1/2 | BG31: 1/2 | BH31: 1/2 | BI31: 1/2 | BJ31: 1/2 | BK31: 1/2 | BL31: 1/2 | BM31: 1/2 | BN31: 1/2 | BO31: 1/2 | BP31: 1/2 | BQ31: 1/2 | BR31: 1/2 | BS31: 1/2 | BT31: 2/3 | BU31: 2/3 | BV31: 2/3 | BW31: 2/3 | BX31: 2/3 | BY31: 2/3 | BZ31: 2/3 | CA31: 2/3 | CB31: 2/3 | CC31: 2/3

Sheet BE
A3: =Voorblad!A5 -> Team Freight Forwarding Logistics
A4: Export België
A6: kg | B6: ldm | C6: euplt | D6: blkplt | E6: BE
A7: 300 | B7: 0.2 | C7: 0.5 | E7: 104
A8: 700 | B8: 0.4 | C8: 1 | E8: 110
A9: 875 | B9: 0.5 | D9: 1 | E9: 118
A10: 1050 | B10: 0.6 | E10: 136
A11: 1400 | B11: 0.8 | C11: 2 | E11: 155
A12: 1750 | B12: 1 | D12: 2 | E12: 181
A13: 2100 | B13: 1.2 | C13: 3 | E13: 206
A14: 2625 | B14: 1.5 | D14: 3 | E14: 216
A15: 2800 | B15: 1.6 | C15: 4 | E15: 223
A16: 3500 | B16: 2 | C16: 5 | D16: 4 | E16: 257
A17: 4200 | B17: 2.4 | C17: 6 | E17: 377
A18: 4375 | B18: 2.5 | D18: 5 | E18: 383
A19: 4900 | B19: 2.8 | C19: 7 | E19: 400
A20: 5250 | B20: 3 | D20: 6 | E20: 416
A21: 5600 | B21: 3.2 | C21: 8 | E21: 452
A22: 6125 | B22: 3.5 | D22: 7 | E22: 460
A23: 6300 | B23: 3.6 | C23: 9 | E23: 472
A24: 7000 | B24: 4 | C24: 10 | D24: 8 | E24: 487
A26: Transittijden:
A28: Dag van lading is dag 0 | C28: Vertrek | E28: Transittijd in werkdagen
A29: Groupage 1-5 pallets | C29: ma,di,wo,do,vrij | E29: 1/2
A30: Deelpartijen > 5 pallets | C30: ma,di,wo,do,vrij | E30: 1/2
A31: Compleet ladingen | C31: ma,di,wo,do,vrij | E31: 1

Sheet BG
A3: =Voorblad!A5 -> Team Freight Forwarding Logistics
A4: Export Bulgarije
A6: kg | B6: ldm | C6: euplt | D6: blkplt | E6: 10 | F6: 11 | G6: 12 | H6: 13 | I6: 14 | J6: 15 | K6: 16 | L6: 17 | M6: 18 | N6: 20 | O6: 21 | P6: 22 | Q6: 23 | R6: 24 | S6: 25 | T6: 26 | U6: 27 | V6: 28 | W6: 29 | X6: 30 | Y6: 31 | Z6: 32 | AA6: 33 | AB6: 34 | AC6: 35 | AD6: 36 | AE6: 37 | AF6: 38 | AG6: 39 | AH6: 40 | AI6: 41 | AJ6: 42 | AK6: 43 | AL6: 44 | AM6: 45 | AN6: 46 | AO6: 47 | AP6: 48 | AQ6: 49 | AR6: 50 | AS6: 51 | AT6: 52 | AU6: 53 | AV6: 54 | AW6: 55 | AX6: 56 | AY6: 57 | AZ6: 58 | BA6: 59 | BB6: 60 | BC6: 61 | BD6: 62 | BE6: 63 | BF6: 64 | BG6: 65 | BH6: 66 | BI6: 67 | BJ6: 68 | BK6: 69 | BL6: 70 | BM6: 71 | BN6: 72 | BO6: 73 | BP6: 74 | BQ6: 75 | BR6: 76 | BS6: 77 | BT6: 78 | BU6: 79 | BV6: 80 | BW6: 81 | BX6: 82 | BY6: 83 | BZ6: 84 | CA6: 85 | CB6: 86 | CC6: 87 | CD6: 88 | CE6: 89 | CF6: 90 | CG6: 91 | CH6: 92 | CI6: 93 | CJ6: 94 | CK6: 95 | CL6: 96 | CM6: 97 | CN6: 98 | CO6: 99
A7: 300 | B7: 0.2 | C7: 0.5 | E7: 199 | F7: 199 | G7: 199 | H7: 199 | I7: 199 | J7: 199 | K7: 199 | L7: 199 | M7: 199 | N7: 229 | O7: 229 | P7: 229 | Q7: 229 | R7: 229 | S7: 229 | T7: 229 | U7: 229 | V7: 229 | W7: 229 | X7: 229 | Y7: 229 | Z7: 229 | AA7: 229 | AB7: 229 | AC7: 229 | AD7: 229 | AE7: 229 | AF7: 229 | AG7: 229 | AH7: 229 | AI7: 229 | AJ7: 229 | AK7: 229 | AL7: 229 | AM7: 229 | AN7: 229 | AO7: 229 | AP7: 229 | AQ7: 229 | AR7: 229 | AS7: 229 | AT7: 229 | AU7: 229 | AV7: 229 | AW7: 229 | AX7: 229 | AY7: 229 | AZ7: 229 | BA7: 229 | BB7: 229 | BC7: 229 | BD7: 229 | BE7: 229 | BF7: 229 | BG7: 229 | BH7: 229 | BI7: 229 | BJ7: 229 | BK7: 229 | BL7: 229 | BM7: 229 | BN7: 229 | BO7: 229 | BP7: 229 | BQ7: 229 | BR7: 229 | BS7: 229 | BT7: 229 | BU7: 229 | BV7: 229 | BW7: 229 | BX7: 229 | BY7: 229 | BZ7: 229 | CA7: 229 | CB7: 229 | CC7: 229 | CD7: 229 | CE7: 229 | CF7: 229 | CG7: 229 | CH7: 229 | CI7: 229 | CJ7: 229 | CK7: 229 | CL7: 229 | CM7: 229 | CN7: 229 | CO7: 229
A8: 700 | B8: 0.4 | C8: 1 | E8: 229 | F8: 229 | G8: 229 | H8: 229 | I8: 229 | J8: 229 | K8: 229 | L8: 229 | M8: 229 | N8: 263 | O8: 263 | P8: 263 | Q8: 263 | R8: 263 | S8: 263 | T8: 263 | U8: 263 | V8: 263 | W8: 263 | X8: 263 | Y8: 263 | Z8: 263 | AA8: 263 | AB8: 263 | AC8: 263 | AD8: 263 | AE8: 263 | AF8: 263 | AG8: 263 | AH8: 263 | AI8: 263 | AJ8: 263 | AK8: 263 | AL8: 263 | AM8: 263 | AN8: 263 | AO8: 263 | AP8: 263 | AQ8: 263 | AR8: 263 | AS8: 263 | AT8: 263 | AU8: 263 | AV8: 263 | AW8: 263 | AX8: 263 | AY8: 263 | AZ8: 263 | BA8: 263 | BB8: 263 | BC8: 263 | BD8: 263 | BE8: 263 | BF8: 263 | BG8: 263 | BH8: 263 | BI8: 263 | BJ8: 263 | BK8: 263 | BL8: 263 | BM8: 263 | BN8: 263 | BO8: 263 | BP8: 263 | BQ8: 263 | BR8: 263 | BS8: 263 | BT8: 263 | BU8: 263 | BV8: 263 | BW8: 263 | BX8: 263 | BY8: 263 | BZ8: 263 | CA8: 263 | CB8: 263 | CC8: 263 | CD8: 263 | CE8: 263 | CF8: 263 | CG8: 263 | CH8: 263 | CI8: 263 | CJ8: 263 | CK8: 263 | CL8: 263 | CM8: 263 | CN8: 263 | CO8: 263
A9: 875 | B9: 0.5 | D9: 1 | E9: 263 | F9: 263 | G9: 263 | H9: 263 | I9: 263 | J9: 263 | K9: 263 | L9: 263 | M9: 263 | N9: 296 | O9: 296 | P9: 296 | Q9: 296 | R9: 296 | S9: 296 | T9: 296 | U9: 296 | V9: 296 | W9: 296 | X9: 296 | Y9: 296 | Z9: 296 | AA9: 296 | AB9: 296 | AC9: 296 | AD9: 296 | AE9: 296 | AF9: 296 | AG9: 296 | AH9: 296 | AI9: 296 | AJ9: 296 | AK9: 296 | AL9: 296 | AM9: 296 | AN9: 296 | AO9: 296 | AP9: 296 | AQ9: 296 | AR9: 296 | AS9: 296 | AT9: 296 | AU9: 296 | AV9: 296 | AW9: 296 | AX9: 296 | AY9: 296 | AZ9: 296 | BA9: 296 | BB9: 296 | BC9: 296 | BD9: 296 | BE9: 296 | BF9: 296 | BG9: 296 | BH9: 296 | BI9: 296 | BJ9: 296 | BK9: 296 | BL9: 296 | BM9: 296 | BN9: 296 | BO9: 296 | BP9: 296 | BQ9: 296 | BR9: 296 | BS9: 296 | BT9: 296 | BU9: 296 | BV9: 296 | BW9: 296 | BX9: 296 | BY9: 296 | BZ9: 296 | CA9: 296 | CB9: 296 | CC9: 296 | CD9: 296 | CE9: 296 | CF9: 296 | CG9: 296 | CH9: 296 | CI9: 296 | CJ9: 296 | CK9: 296 | CL9: 296 | CM9: 296 | CN9: 296 | CO9: 296
A10: 1050 | B10: 0.6 | E10: 311 | F10: 311 | G10: 311 | H10: 311 | I10: 311 | J10: 311 | K10: 311 | L10: 311 | M10: 311 | N10: 398 | O10: 398 | P10: 398 | Q10: 398 | R10: 398 | S10: 398 | T10: 398 | U10: 398 | V10: 398 | W10: 398 | X10: 398 | Y10: 398 | Z10: 398 | AA10: 398 | AB10: 398 | AC10: 398 | AD10: 398 | AE10: 398 | AF10: 398 | AG10: 398 | AH10: 398 | AI10: 398 | AJ10: 398 | AK10: 398 | AL10: 398 | AM10: 433 | AN10: 433 | AO10: 433 | AP10: 433 | AQ10: 433 | AR10: 398 | AS10: 398 | AT10: 398 | AU10: 398 | AV10: 398 | AW10: 398 | AX10: 398 | AY10: 398 | AZ10: 398 | BA10: 398 | BB10: 433 | BC10: 433 | BD10: 433 | BE10: 433 | BF10: 433 | BG10: 433 | BH10: 433 | BI10: 433 | BJ10: 433 | BK10: 433 | BL10: 433 | BM10: 433 | BN10: 433 | BO10: 433 | BP10: 433 | BQ10: 433 | BR10: 433 | BS10: 433 | BT10: 433 | BU10: 433 | BV10: 433 | BW10: 433 | BX10: 433 | BY10: 433 | BZ10: 433 | CA10: 433 | CB10: 433 | CC10: 433 | CD10: 433 | CE10: 433 | CF10: 433 | CG10: 433 | CH10: 433 | CI10: 433 | CJ10: 433 | CK10: 433 | CL10: 433 | CM10: 433 | CN10: 433 | CO10: 433
A11: 1400 | B11: 0.8 | C11: 2 | E11: 352 | F11: 352 | G11: 352 | H11: 352 | I11: 352 | J11: 352 | K11: 352 | L11: 352 | M11: 352 | N11: 468 | O11: 468 | P11: 468 | Q11: 468 | R11: 468 | S11: 468 | T11: 468 | U11: 468 | V11: 468 | W11: 468 | X11: 468 | Y11: 468 | Z11: 468 | AA11: 468 | AB11: 468 | AC11: 468 | AD11: 468 | AE11: 468 | AF11: 468 | AG11: 468 | AH11: 468 | AI11: 468 | AJ11: 468 | AK11: 468 | AL11: 468 | AM11: 502 | AN11: 502 | AO11: 502 | AP11: 502 | AQ11: 502 | AR11: 468 | AS11: 468 | AT11: 468 | AU11: 468 | AV11: 468 | AW11: 468 | AX11: 468 | AY11: 468 | AZ11: 468 | BA11: 468 | BB11: 502 | BC11: 502 | BD11: 502 | BE11: 502 | BF11: 502 | BG11: 502 | BH11: 502 | BI11: 502 | BJ11: 502 | BK11: 502 | BL11: 502 | BM11: 502 | BN11: 502 | BO11: 502 | BP11: 502 | BQ11: 502 | BR11: 502 | BS11: 502 | BT11: 502 | BU11: 502 | BV11: 502 | BW11: 502 | BX11: 502 | BY11: 502 | BZ11: 502 | CA11: 502 | CB11: 502 | CC11: 502 | CD11: 502 | CE11: 502 | CF11: 502 | CG11: 502 | CH11: 502 | CI11: 502 | CJ11: 502 | CK11: 502 | CL11: 502 | CM11: 502 | CN11: 502 | CO11: 502
A12: 1750 | B12: 1 | D12: 2 | E12: 410 | F12: 410 | G12: 410 | H12: 410 | I12: 410 | J12: 410 | K12: 410 | L12: 410 | M12: 410 | N12: 526 | O12: 526 | P12: 526 | Q12: 526 | R12: 526 | S12: 526 | T12: 526 | U12: 526 | V12: 526 | W12: 526 | X12: 526 | Y12: 526 | Z12: 526 | AA12: 526 | AB12: 526 | AC12: 526 | AD12: 526 | AE12: 526 | AF12: 526 | AG12: 526 | AH12: 526 | AI12: 526 | AJ12: 526 | AK12: 526 | AL12: 526 | AM12: 562 | AN12: 562 | AO12: 562 | AP12: 562 | AQ12: 562 | AR12: 526 | AS12: 526 | AT12: 526 | AU12: 526 | AV12: 526 | AW12: 526 | AX12: 526 | AY12: 526 | AZ12: 526 | BA12: 526 | BB12: 562 | BC12: 562 | BD12: 562 | BE12: 562 | BF12: 562 | BG12: 562 | BH12: 562 | BI12: 562 | BJ12: 562 | BK12: 562 | BL12: 562 | BM12: 562 | BN12: 562 | BO12: 562 | BP12: 562 | BQ12: 562 | BR12: 562 | BS12: 562 | BT12: 562 | BU12: 562 | BV12: 562 | BW12: 562 | BX12: 562 | BY12: 562 | BZ12: 562 | CA12: 562 | CB12: 562 | CC12: 562 | CD12: 562 | CE12: 562 | CF12: 562 | CG12: 562 | CH12: 562 | CI12: 562 | CJ12: 562 | CK12: 562 | CL12: 562 | CM12: 562 | CN12: 562 | CO12: 562
A13: 2100 | B13: 1.2 | C13: 3 | E13: 468 | F13: 468 | G13: 468 | H13: 468 | I13: 468 | J13: 468 | K13: 468 | L13: 468 | M13: 468 | N13: 586 | O13: 586 | P13: 586 | Q13: 586 | R13: 586 | S13: 586 | T13: 586 | U13: 586 | V13: 586 | W13: 586 | X13: 586 | Y13: 586 | Z13: 586 | AA13: 586 | AB13: 586 | AC13: 586 | AD13: 586 | AE13: 586 | AF13: 586 | AG13: 586 | AH13: 586 | AI13: 586 | AJ13: 586 | AK13: 586 | AL13: 586 | AM13: 620 | AN13: 620 | AO13: 620 | AP13: 620 | AQ13: 620 | AR13: 586 | AS13: 586 | AT13: 586 | AU13: 586 | AV13: 586 | AW13: 586 | AX13: 586 | AY13: 586 | AZ13: 586 | BA13: 586 | BB13: 620 | BC13: 620 | BD13: 620 | BE13: 620 | BF13: 620 | BG13: 620 | BH13: 620 | BI13: 620 | BJ13: 620 | BK13: 620 | BL13: 620 | BM13: 620 | BN13: 620 | BO13: 620 | BP13: 620 | BQ13: 620 | BR13: 620 | BS13: 620 | BT13: 620 | BU13: 620 | BV13: 620 | BW13: 620 | BX13: 620 | BY13: 620 | BZ13: 620 | CA13: 620 | CB13: 620 | CC13: 620 | CD13: 620 | CE13: 620 | CF13: 620 | CG13: 620 | CH13: 620 | CI13: 620 | CJ13: 620 | CK13: 620 | CL13: 620 | CM13: 620 | CN13: 620 | CO13: 620
A14: 2625 | B14: 1.5 | D14: 3 | E14: 526 | F14: 526 | G14: 526 | H14: 526 | I14: 526 | J14: 526 | K14: 526 | L14: 526 | M14: 526 | N14: 643 | O14: 643 | P14: 643 | Q14: 643 | R14: 643 | S14: 643 | T14: 643 | U14: 643 | V14: 643 | W14: 643 | X14: 643 | Y14: 643 | Z14: 643 | AA14: 643 | AB14: 643 | AC14: 643 | AD14: 643 | AE14: 643 | AF14: 643 | AG14: 643 | AH14: 643 | AI14: 643 | AJ14: 643 | AK14: 643 | AL14: 643 | AM14: 678 | AN14: 678 | AO14: 678 | AP14: 678 | AQ14: 678 | AR14: 643 | AS14: 643 | AT14: 643 | AU14: 643 | AV14: 643 | AW14: 643 | AX14: 643 | AY14: 643 | AZ14: 643 | BA14: 643 | BB14: 678 | BC14: 678 | BD14: 678 | BE14: 678 | BF14: 678 | BG14: 678 | BH14: 678 | BI14: 678 | BJ14: 678 | BK14: 678 | BL14: 678 | BM14: 678 | BN14: 678 | BO14: 678 | BP14: 678 | BQ14: 678 | BR14: 678 | BS14: 678 | BT14: 678 | BU14: 678 | BV14: 678 | BW14: 678 | BX14: 678 | BY14: 678 | BZ14: 678 | CA14: 678 | CB14: 678 | CC14: 678 | CD14: 678 | CE14: 678 | CF14: 678 | CG14: 678 | CH14: 678 | CI14: 678 | CJ14: 678 | CK14: 678 | CL14: 678 | CM14: 678 | CN14: 678 | CO14: 678
A15: 2800 | B15: 1.6 | C15: 4 | E15: 586 | F15: 586 | G15: 586 | H15: 586 | I15: 586 | J15: 586 | K15: 586 | L15: 586 | M15: 586 | N15: 702 | O15: 702 | P15: 702 | Q15: 702 | R15: 702 | S15: 702 | T15: 702 | U15: 702 | V15: 702 | W15: 702 | X15: 702 | Y15: 702 | Z15: 702 | AA15: 702 | AB15: 702 | AC15: 702 | AD15: 702 | AE15: 702 | AF15: 702 | AG15: 702 | AH15: 702 | AI15: 702 | AJ15: 702 | AK15: 702 | AL15: 702 | AM15: 759 | AN15: 759 | AO15: 759 | AP15: 759 | AQ15: 759 | AR15: 702 | AS15: 702 | AT15: 702 | AU15: 702 | AV15: 702 | AW15: 702 | AX15: 702 | AY15: 702 | AZ15: 702 | BA15: 702 | BB15: 759 | BC15: 759 | BD15: 759 | BE15: 759 | BF15: 759 | BG15: 759 | BH15: 759 | BI15: 759 | BJ15: 759 | BK15: 759 | BL15: 759 | BM15: 759 | BN15: 759 | BO15: 759 | BP15: 759 | BQ15: 759 | BR15: 759 | BS15: 759 | BT15: 759 | BU15: 759 | BV15: 759 | BW15: 759 | BX15: 759 | BY15: 759 | BZ15: 759 | CA15: 759 | CB15: 759 | CC15: 759 | CD15: 759 | CE15: 759 | CF15: 759 | CG15: 759 | CH15: 759 | CI15: 759 | CJ15: 759 | CK15: 759 | CL15: 759 | CM15: 759 | CN15: 759 | CO15: 759
A16: 3500 | B16: 2 | C16: 5 | D16: 4 | E16: 643 | F16: 643 | G16: 643 | H16: 643 | I16: 643 | J16: 643 | K16: 643 | L16: 643 | M16: 643 | N16: 759 | O16: 759 | P16: 759 | Q16: 759 | R16: 759 | S16: 759 | T16: 759 | U16: 759 | V16: 759 | W16: 759 | X16: 759 | Y16: 759 | Z16: 759 | AA16: 759 | AB16: 759 | AC16: 759 | AD16: 759 | AE16: 759 | AF16: 759 | AG16: 759 | AH16: 759 | AI16: 759 | AJ16: 759 | AK16: 759 | AL16: 759 | AM16: 818 | AN16: 818 | AO16: 818 | AP16: 818 | AQ16: 818 | AR16: 759 | AS16: 759 | AT16: 759 | AU16: 759 | AV16: 759 | AW16: 759 | AX16: 759 | AY16: 759 | AZ16: 759 | BA16: 759 | BB16: 818 | BC16: 818 | BD16: 818 | BE16: 818 | BF16: 818 | BG16: 818 | BH16: 818 | BI16: 818 | BJ16: 818 | BK16: 818 | BL16: 818 | BM16: 818 | BN16: 818 | BO16: 818 | BP16: 818 | BQ16: 818 | BR16: 818 | BS16: 818 | BT16: 818 | BU16: 818 | BV16: 818 | BW16: 818 | BX16: 818 | BY16: 818 | BZ16: 818 | CA16: 818 | CB16: 818 | CC16: 818 | CD16: 818 | CE16: 818 | CF16: 818 | CG16: 818 | CH16: 818 | CI16: 818 | CJ16: 818 | CK16: 818 | CL16: 818 | CM16: 818 | CN16: 818 | CO16: 818
A17: 4200 | B17: 2.4 | C17: 6 | E17: 660 | F17: 660 | G17: 660 | H17: 660 | I17: 660 | J17: 660 | K17: 660 | L17: 660 | M17: 660 | N17: 770 | O17: 770 | P17: 770 | Q17: 770 | R17: 770 | S17: 770 | T17: 770 | U17: 770 | V17: 770 | W17: 770 | X17: 770 | Y17: 770 | Z17: 770 | AA17: 770 | AB17: 770 | AC17: 770 | AD17: 770 | AE17: 770 | AF17: 770 | AG17: 770 | AH17: 770 | AI17: 770 | AJ17: 770 | AK17: 770 | AL17: 770 | AM17: 825 | AN17: 825 | AO17: 825 | AP17: 825 | AQ17: 825 | AR17: 770 | AS17: 770 | AT17: 770 | AU17: 770 | AV17: 770 | AW17: 770 | AX17: 770 | AY17: 770 | AZ17: 770 | BA17: 770 | BB17: 825 | BC17: 825 | BD17: 825 | BE17: 825 | BF17: 825 | BG17: 825 | BH17: 825 | BI17: 825 | BJ17: 825 | BK17: 825 | BL17: 825 | BM17: 825 | BN17: 825 | BO17: 825 | BP17: 825 | BQ17: 825 | BR17: 825 | BS17: 825 | BT17: 825 | BU17: 825 | BV17: 825 | BW17: 825 | BX17: 825 | BY17: 825 | BZ17: 825 | CA17: 825 | CB17: 825 | CC17: 825 | CD17: 825 | CE17: 825 | CF17: 825 | CG17: 825 | CH17: 825 | CI17: 825 | CJ17: 825 | CK17: 825 | CL17: 825 | CM17: 825 | CN17: 825 | CO17: 825
A18: 4375 | B18: 2.5 | D18: 5 | E18: 714 | F18: 714 | G18: 714 | H18: 714 | I18: 714 | J18: 714 | K18: 714 | L18: 714 | M18: 714 | N18: 825 | O18: 825 | P18: 825 | Q18: 825 | R18: 825 | S18: 825 | T18: 825 | U18: 825 | V18: 825 | W18: 825 | X18: 825 | Y18: 825 | Z18: 825 | AA18: 825 | AB18: 825 | AC18: 825 | AD18: 825 | AE18: 825 | AF18: 825 | AG18: 825 | AH18: 825 | AI18: 825 | AJ18: 825 | AK18: 825 | AL18: 825 | AM18: 880 | AN18: 880 | AO18: 880 | AP18: 880 | AQ18: 880 | AR18: 825 | AS18: 825 | AT18: 825 | AU18: 825 | AV18: 825 | AW18: 825 | AX18: 825 | AY18: 825 | AZ18: 825 | BA18: 825 | BB18: 880 | BC18: 880 | BD18: 880 | BE18: 880 | BF18: 880 | BG18: 880 | BH18: 880 | BI18: 880 | BJ18: 880 | BK18: 880 | BL18: 880 | BM18: 880 | BN18: 880 | BO18: 880 | BP18: 880 | BQ18: 880 | BR18: 880 | BS18: 880 | BT18: 880 | BU18: 880 | BV18: 880 | BW18: 880 | BX18: 880 | BY18: 880 | BZ18: 880 | CA18: 880 | CB18: 880 | CC18: 880 | CD18: 880 | CE18: 880 | CF18: 880 | CG18: 880 | CH18: 880 | CI18: 880 | CJ18: 880 | CK18: 880 | CL18: 880 | CM18: 880 | CN18: 880 | CO18: 880
A19: 4900 | B19: 2.8 | C19: 7 | E19: 770 | F19: 770 | G19: 770 | H19: 770 | I19: 770 | J19: 770 | K19: 770 | L19: 770 | M19: 770 | N19: 880 | O19: 880 | P19: 880 | Q19: 880 | R19: 880 | S19: 880 | T19: 880 | U19: 880 | V19: 880 | W19: 880 | X19: 880 | Y19: 880 | Z19: 880 | AA19: 880 | AB19: 880 | AC19: 880 | AD19: 880 | AE19: 880 | AF19: 880 | AG19: 880 | AH19: 880 | AI19: 880 | AJ19: 880 | AK19: 880 | AL19: 880 | AM19: 935 | AN19: 935 | AO19: 935 | AP19: 935 | AQ19: 935 | AR19: 880 | AS19: 880 | AT19: 880 | AU19: 880 | AV19: 880 | AW19: 880 | AX19: 880 | AY19: 880 | AZ19: 880 | BA19: 880 | BB19: 935 | BC19: 935 | BD19: 935 | BE19: 935 | BF19: 935 | BG19: 935 | BH19: 935 | BI19: 935 | BJ19: 935 | BK19: 935 | BL19: 935 | BM19: 935 | BN19: 935 | BO19: 935 | BP19: 935 | BQ19: 935 | BR19: 935 | BS19: 935 | BT19: 935 | BU19: 935 | BV19: 935 | BW19: 935 | BX19: 935 | BY19: 935 | BZ19: 935 | CA19: 935 | CB19: 935 | CC19: 935 | CD19: 935 | CE19: 935 | CF19: 935 | CG19: 935 | CH19: 935 | CI19: 935 | CJ19: 935 | CK19: 935 | CL19: 935 | CM19: 935 | CN19: 935 | CO19: 935
A20: 5250 | B20: 3 | D20: 6 | E20: 825 | F20: 825 | G20: 825 | H20: 825 | I20: 825 | J20: 825 | K20: 825 | L20: 825 | M20: 825 | N20: 935 | O20: 935 | P20: 935 | Q20: 935 | R20: 935 | S20: 935 | T20: 935 | U20: 935 | V20: 935 | W20: 935 | X20: 935 | Y20: 935 | Z20: 935 | AA20: 935 | AB20: 935 | AC20: 935 | AD20: 935 | AE20: 935 | AF20: 935 | AG20: 935 | AH20: 935 | AI20: 935 | AJ20: 935 | AK20: 935 | AL20: 935 | AM20: 990 | AN20: 990 | AO20: 990 | AP20: 990 | AQ20: 990 | AR20: 935 | AS20: 935 | AT20: 935 | AU20: 935 | AV20: 935 | AW20: 935 | AX20: 935 | AY20: 935 | AZ20: 935 | BA20: 935 | BB20: 990 | BC20: 990 | BD20: 990 | BE20: 990 | BF20: 990 | BG20: 990 | BH20: 990 | BI20: 990 | BJ20: 990 | BK20: 990 | BL20: 990 | BM20: 990 | BN20: 990 | BO20: 990 | BP20: 990 | BQ20: 990 | BR20: 990 | BS20: 990 | BT20: 990 | BU20: 990 | BV20: 990 | BW20: 990 | BX20: 990 | BY20: 990 | BZ20: 990 | CA20: 990 | CB20: 990 | CC20: 990 | CD20: 990 | CE20: 990 | CF20: 990 | CG20: 990 | CH20: 990 | CI20: 990 | CJ20: 990 | CK20: 990 | CL20: 990 | CM20: 990 | CN20: 990 | CO20: 990
A21: 5600 | B21: 3.2 | C21: 8 | E21: 880 | F21: 880 | G21: 880 | H21: 880 | I21: 880 | J21: 880 | K21: 880 | L21: 880 | M21: 880 | N21: 990 | O21: 990 | P21: 990 | Q21: 990 | R21: 990 | S21: 990 | T21: 990 | U21: 990 | V21: 990 | W21: 990 | X21: 990 | Y21: 990 | Z21: 990 | AA21: 990 | AB21: 990 | AC21: 990 | AD21: 990 | AE21: 990 | AF21: 990 | AG21: 990 | AH21: 990 | AI21: 990 | AJ21: 990 | AK21: 990 | AL21: 990 | AM21: 1044 | AN21: 1044 | AO21: 1044 | AP21: 1044 | AQ21: 1044 | AR21: 990 | AS21: 990 | AT21: 990 | AU21: 990 | AV21: 990 | AW21: 990 | AX21: 990 | AY21: 990 | AZ21: 990 | BA21: 990 | BB21: 1044 | BC21: 1044 | BD21: 1044 | BE21: 1044 | BF21: 1044 | BG21: 1044 | BH21: 1044 | BI21: 1044 | BJ21: 1044 | BK21: 1044 | BL21: 1044 | BM21: 1044 | BN21: 1044 | BO21: 1044 | BP21: 1044 | BQ21: 1044 | BR21: 1044 | BS21: 1044 | BT21: 1044 | BU21: 1044 | BV21: 1044 | BW21: 1044 | BX21: 1044 | BY21: 1044 | BZ21: 1044 | CA21: 1044 | CB21: 1044 | CC21: 1044 | CD21: 1044 | CE21: 1044 | CF21: 1044 | CG21: 1044 | CH21: 1044 | CI21: 1044 | CJ21: 1044 | CK21: 1044 | CL21: 1044 | CM21: 1044 | CN21: 1044 | CO21: 1044
A22: 6125 | B22: 3.5 | D22: 7 | E22: 935 | F22: 935 | G22: 935 | H22: 935 | I22: 935 | J22: 935 | K22: 935 | L22: 935 | M22: 935 | N22: 1044 | O22: 1044 | P22: 1044 | Q22: 1044 | R22: 1044 | S22: 1044 | T22: 1044 | U22: 1044 | V22: 1044 | W22: 1044 | X22: 1044 | Y22: 1044 | Z22: 1044 | AA22: 1044 | AB22: 1044 | AC22: 1044 | AD22: 1044 | AE22: 1044 | AF22: 1044 | AG22: 1044 | AH22: 1044 | AI22: 1044 | AJ22: 1044 | AK22: 1044 | AL22: 1044 | AM22: 1099 | AN22: 1099 | AO22: 1099 | AP22: 1099 | AQ22: 1099 | AR22: 1044 | AS22: 1044 | AT22: 1044 | AU22: 1044 | AV22: 1044 | AW22: 1044 | AX22: 1044 | AY22: 1044 | AZ22: 1044 | BA22: 1044 | BB22: 1099 | BC22: 1099 | BD22: 1099 | BE22: 1099 | BF22: 1099 | BG22: 1099 | BH22: 1099 | BI22: 1099 | BJ22: 1099 | BK22: 1099 | BL22: 1099 | BM22: 1099 | BN22: 1099 | BO22: 1099 | BP22: 1099 | BQ22: 1099 | BR22: 1099 | BS22: 1099 | BT22: 1099 | BU22: 1099 | BV22: 1099 | BW22: 1099 | BX22: 1099 | BY22: 1099 | BZ22: 1099 | CA22: 1099 | CB22: 1099 | CC22: 1099 | CD22: 1099 | CE22: 1099 | CF22: 1099 | CG22: 1099 | CH22: 1099 | CI22: 1099 | CJ22: 1099 | CK22: 1099 | CL22: 1099 | CM22: 1099 | CN22: 1099 | CO22: 1099
A23: 6300 | B23: 3.6 | C23: 9 | E23: 990 | F23: 990 | G23: 990 | H23: 990 | I23: 990 | J23: 990 | K23: 990 | L23: 990 | M23: 990 | N23: 1099 | O23: 1099 | P23: 1099 | Q23: 1099 | R23: 1099 | S23: 1099 | T23: 1099 | U23: 1099 | V23: 1099 | W23: 1099 | X23: 1099 | Y23: 1099 | Z23: 1099 | AA23: 1099 | AB23: 1099 | AC23: 1099 | AD23: 1099 | AE23: 1099 | AF23: 1099 | AG23: 1099 | AH23: 1099 | AI23: 1099 | AJ23: 1099 | AK23: 1099 | AL23: 1099 | AM23: 1187 | AN23: 1187 | AO23: 1187 | AP23: 1187 | AQ23: 1187 | AR23: 1099 | AS23: 1099 | AT23: 1099 | AU23: 1099 | AV23: 1099 | AW23: 1099 | AX23: 1099 | AY23: 1099 | AZ23: 1099 | BA23: 1099 | BB23: 1187 | BC23: 1187 | BD23: 1187 | BE23: 1187 | BF23: 1187 | BG23: 1187 | BH23: 1187 | BI23: 1187 | BJ23: 1187 | BK23: 1187 | BL23: 1187 | BM23: 1187 | BN23: 1187 | BO23: 1187 | BP23: 1187 | BQ23: 1187 | BR23: 1187 | BS23: 1187 | BT23: 1187 | BU23: 1187 | BV23: 1187 | BW23: 1187 | BX23: 1187 | BY23: 1187 | BZ23: 1187 | CA23: 1187 | CB23: 1187 | CC23: 1187 | CD23: 1187 | CE23: 1187 | CF23: 1187 | CG23: 1187 | CH23: 1187 | CI23: 1187 | CJ23: 1187 | CK23: 1187 | CL23: 1187 | CM23: 1187 | CN23: 1187 | CO23: 1187
A24: 7000 | B24: 4 | C24: 10 | D24: 8 | E24: 1044 | F24: 1044 | G24: 1044 | H24: 1044 | I24: 1044 | J24: 1044 | K24: 1044 | L24: 1044 | M24: 1044 | N24: 1154 | O24: 1154 | P24: 1154 | Q24: 1154 | R24: 1154 | S24: 1154 | T24: 1154 | U24: 1154 | V24: 1154 | W24: 1154 | X24: 1154 | Y24: 1154 | Z24: 1154 | AA24: 1154 | AB24: 1154 | AC24: 1154 | AD24: 1154 | AE24: 1154 | AF24: 1154 | AG24: 1154 | AH24: 1154 | AI24: 1154 | AJ24: 1154 | AK24: 1154 | AL24: 1154 | AM24: 1275 | AN24: 1275 | AO24: 1275 | AP24: 1275 | AQ24: 1275 | AR24: 1154 | AS24: 1154 | AT24: 1154 | AU24: 1154 | AV24: 1154 | AW24: 1154 | AX24: 1154 | AY24: 1154 | AZ24: 1154 | BA24: 1154 | BB24: 1275 | BC24: 1275 | BD24: 1275 | BE24: 1275 | BF24: 1275 | BG24: 1275 | BH24: 1275 | BI24: 1275 | BJ24: 1275 | BK24: 1275 | BL24: 1275 | BM24: 1275 | BN24: 1275 | BO24: 1275 | BP24: 1275 | BQ24: 1275 | BR24: 1275 | BS24: 1275 | BT24: 1275 | BU24: 1275 | BV24: 1275 | BW24: 1275 | BX24: 1275 | BY24: 1275 | BZ24: 1275 | CA24: 1275 | CB24: 1275 | CC24: 1275 | CD24: 1275 | CE24: 1275 | CF24: 1275 | CG24: 1275 | CH24: 1275 | CI24: 1275 | CJ24: 1275 | CK24: 1275 | CL24: 1275 | CM24: 1275 | CN24: 1275 | CO24: 1275
A26: Transittijden:
A28: Dag van lading is dag 0 | C28: Vertrek | G28: Transittijd in werkdagen | T28: Transittijd in werkdagen | AG28: Transittijd in werkdagen | AT28: Transittijd in werkdagen | BG28: Transittijd in werkdagen | BT28: Transittijd in werkdagen | CG28: Transittijd in werkdagen
A29: Groupage 1-5 pallets | C29: di,do,vrij | E29: 5 | F29: 5 | G29: 5 | H29: 5 | I29: 5 | J29: 5 | K29: 5 | L29: 5 | M29: 5 | N29: 5 | O29: 5 | P29: 5 | Q29: 5 | R29: 5 | S29: 5 | T29: 5 | U29: 5 | V29: 5 | W29: 5 | X29: 5 | Y29: 5 | Z29: 5 | AA29: 5 | AB29: 5 | AC29: 5 | AD29: 5 | AE29: 5 | AF29: 5 | AG29: 5 | AH29: 5/6 | AI29: 5/6 | AJ29: 5/6 | AK29: 5/6 | AL29: 5 | AM29: 5/6 | AN29: 5 | AO29: 5/6 | AP29: 5/6 | AQ29: 5/6 | AR29: 5/6 | AS29: 5/6 | AT29: 5/6 | AU29: 5/6 | AV29: 5/6 | AW29: 5/6 | AX29: 5/6 | AY29: 5/6 | AZ29: 5/6 | BA29: 5/6 | BB29: 5/6 | BC29: 5/6 | BD29: 5/6 | BE29: 5/6 | BF29: 5/6 | BG29: 5/6 | BH29: 5/6 | BI29: 5/6 | BJ29: 5/6 | BK29: 5/6 | BL29: 5/6 | BM29: 5/6 | BN29: 5/6 | BO29: 5/6 | BP29: 5/6 | BQ29: 5/6 | BR29: 5/6 | BS29: 5/6 | BT29: 5/6 | BU29: 5/6 | BV29: 5/6 | BW29: 5/6 | BX29: 5/6 | BY29: 5/6 | BZ29: 5/6 | CA29: 5/6 | CB29: 5/6 | CC29: 5/6 | CD29: 5/6 | CE29: 5/6 | CF29: 5/6 | CG29: 5/6 | CH29: 5/6 | CI29: 5/6 | CJ29: 5/6 | CK29: 5/6 | CL29: 5/6 | CM29: 5/6 | CN29: 5/6 | CO29: 5/6
A30: Deelpartijen > 5 pallets | C30: di,wo,do,vrij | E30: 4/5 | F30: 4/5 | G30: 4/5 | H30: 4/5 | I30: 4/5 | J30: 4/5 | K30: 4/5 | L30: 4/5 | M30: 4/5 | N30: 4/5 | O30: 4/5 | P30: 4/5 | Q30: 4/5 | R30: 4/5 | S30: 4/5 | T30: 4/5 | U30: 4/5 | V30: 4/5 | W30: 4/5 | X30: 4/5 | Y30: 4/5 | Z30: 4/5 | AA30: 4/5 | AB30: 4/5 | AC30: 4/5 | AD30: 4/5 | AE30: 4/5 | AF30: 4/5 | AG30: 4/5 | AH30: 5 | AI30: 5 | AJ30: 5 | AK30: 5 | AL30: 4/5 | AM30: 5 | AN30: 4/5 | AO30: 5 | AP30: 5 | AQ30: 5 | AR30: 5 | AS30: 5 | AT30: 5 | AU30: 5 | AV30: 5 | AW30: 5 | AX30: 5 | AY30: 5 | AZ30: 5 | BA30: 5 | BB30: 5 | BC30: 5 | BD30: 5 | BE30: 5 | BF30: 5 | BG30: 5 | BH30: 5 | BI30: 5 | BJ30: 5 | BK30: 5 | BL30: 5 | BM30: 5 | BN30: 5 | BO30: 5 | BP30: 5 | BQ30: 5 | BR30: 5 | BS30: 5 | BT30: 5 | BU30: 5 | BV30: 5 | BW30: 5 | BX30: 5 | BY30: 5 | BZ30: 5 | CA30: 5 | CB30: 5 | CC30: 5 | CD30: 5 | CE30: 5 | CF30: 5 | CG30: 5 | CH30: 5 | CI30: 5 | CJ30: 5 | CK30: 5 | CL30: 5 | CM30: 5 | CN30: 5 | CO30: 5
A31: Compleet ladingen | C31: ma,di,wo,do,vrij | E31: 4 | F31: 4 | G31: 4 | H31: 4 | I31: 4 | J31: 4 | K31: 4 | L31: 4 | M31: 4 | N31: 4 | O31: 4 | P31: 4 | Q31: 4 | R31: 4 | S31: 4 | T31: 4 | U31: 4 | V31: 4 | W31: 4 | X31: 4 | Y31: 4 | Z31: 4 | AA31: 4 | AB31: 4 | AC31: 4 | AD31: 4 | AE31: 4 | AF31: 4 | AG31: 4 | AH31: 4 | AI31: 4 | AJ31: 4 | AK31: 4 | AL31: 4 | AM31: 4 | AN31: 4 | AO31: 4 | AP31: 4 | AQ31: 4 | AR31: 4 | AS31: 4 | AT31: 4 | AU31: 4 | AV31: 4 | AW31: 4 | AX31: 4 | AY31: 4 | AZ31: 4 | BA31: 4 | BB31: 4 | BC31: 4 | BD31: 4 | BE31: 4 | BF31: 4 | BG31: 4 | BH31: 4 | BI31: 4 | BJ31: 4 | BK31: 4 | BL31: 4 | BM31: 4 | BN31: 4 | BO31: 4 | BP31: 4 | BQ31: 4 | BR31: 4 | BS31: 4 | BT31: 4 | BU31: 4 | BV31: 4 | BW31: 4 | BX31: 4 | BY31: 4 | BZ31: 4 | CA31: 4 | CB31: 4 | CC31: 4 | CD31: 4 | CE31: 4 | CF31: 4 | CG31: 4 | CH31: 4 | CI31: 4 | CJ31: 4 | CK31: 4 | CL31: 4 | CM31: 4 | CN31: 4 | CO31: 4

Sheet CH
A3: =Voorblad!A5 -> Team Freight Forwarding Logistics
A4: Export Zwitserland
A6: kg | B6: ldm | C6: euplt | D6: blkplt | E6: 10 | F6: 11 | G6: 12 | H6: 13 | I6: 14 | J6: 15 | K6: 16 | L6: 17 | M6: 18 | N6: 19 | O6: 20 | P6: 21 | Q6: 22 | R6: 23 | S6: 24 | T6: 25 | U6: 26 | V6: 27 | W6: 28 | X6: 29 | Y6: 30 | Z6: 31 | AA6: 32 | AB6: 33 | AC6: 34 | AD6: 35 | AE6: 36 | AF6: 37 | AG6: 38 | AH6: 39 | AI6: 40 | AJ6: 41 | AK6: 42 | AL6: 43 | AM6: 44 | AN6: 45 | AO6: 46 | AP6: 47 | AQ6: 48 | AR6: 49 | AS6: 50 | AT6: 51 | AU6: 52 | AV6: 53 | AW6: 54 | AX6: 55 | AY6: 56 | AZ6: 57 | BA6: 60 | BB6: 61 | BC6: 62 | BD6: 63 | BE6: 64 | BF6: 65 | BG6: 66 | BH6: 67 | BI6: 68 | BJ6: 69 | BK6: 70 | BL6: 71 | BM6: 72 | BN6: 73 | BO6: 74 | BP6: 75 | BQ6: 76 | BR6: 77 | BS6: 80 | BT6: 81 | BU6: 82 | BV6: 83 | BW6: 84 | BX6: 85 | BY6: 86 | BZ6: 87 | CA6: 88 | CB6: 89 | CC6: 90 | CD6: 91 | CE6: 92 | CF6: 93 | CG6: 94 | CH6: 95 | CI6: 96
A7: 300 | B7: 0.2 | C7: 0.5 | E7: 231 | F7: 231 | G7: 250 | H7: 231 | I7: 213 | J7: 213 | K7: 213 | L7: 213 | M7: 231 | N7: 250 | O7: 193 | P7: 193 | Q7: 193 | R7: 193 | S7: 193 | T7: 193 | U7: 193 | V7: 193 | W7: 193 | X7: 193 | Y7: 193 | Z7: 193 | AA7: 193 | AB7: 193 | AC7: 193 | AD7: 193 | AE7: 213 | AF7: 213 | AG7: 213 | AH7: 287 | AI7: 157 | AJ7: 157 | AK7: 157 | AL7: 157 | AM7: 157 | AN7: 172 | AO7: 172 | AP7: 172 | AQ7: 172 | AR7: 172 | AS7: 172 | AT7: 172 | AU7: 172 | AV7: 172 | AW7: 172 | AX7: 172 | AY7: 193 | AZ7: 193 | BA7: 193 | BB7: 193 | BC7: 193 | BD7: 193 | BE7: 213 | BF7: 270 | BG7: 270 | BH7: 250 | BI7: 270 | BJ7: 270 | BK7: 231 | BL7: 287 | BM7: 250 | BN7: 250 | BO7: 287 | BP7: 287 | BQ7: 287 | BR7: 287 | BS7: 193 | BT7: 193 | BU7: 193 | BV7: 193 | BW7: 193 | BX7: 213 | BY7: 213 | BZ7: 213 | CA7: 213 | CB7: 193 | CC7: 213 | CD7: 213 | CE7: 213 | CF7: 213 | CG7: 213 | CH7: 213 | CI7: 213
A8: 700 | B8: 0.4 | C8: 1 | E8: 320 | F8: 320 | G8: 348 | H8: 320 | I8: 292 | J8: 292 | K8: 292 | L8: 292 | M8: 320 | N8: 348 | O8: 257 | P8: 257 | Q8: 257 | R8: 257 | S8: 257 | T8: 257 | U8: 257 | V8: 257 | W8: 257 | X8: 257 | Y8: 257 | Z8: 257 | AA8: 257 | AB8: 257 | AC8: 257 | AD8: 257 | AE8: 292 | AF8: 292 | AG8: 292 | AH8: 402 | AI8: 203 | AJ8: 203 | AK8: 203 | AL8: 203 | AM8: 203 | AN8: 221 | AO8: 221 | AP8: 221 | AQ8: 221 | AR8: 221 | AS8: 221 | AT8: 221 | AU8: 221 | AV8: 221 | AW8: 221 | AX8: 221 | AY8: 257 | AZ8: 257 | BA8: 257 | BB8: 257 | BC8: 257 | BD8: 257 | BE8: 292 | BF8: 379 | BG8: 379 | BH8: 348 | BI8: 379 | BJ8: 379 | BK8: 320 | BL8: 402 | BM8: 348 | BN8: 348 | BO8: 402 | BP8: 402 | BQ8: 402 | BR8: 402 | BS8: 257 | BT8: 257 | BU8: 257 | BV8: 257 | BW8: 257 | BX8: 292 | BY8: 292 | BZ8: 292 | CA8: 292 | CB8: 257 | CC8: 292 | CD8: 292 | CE8: 292 | CF8: 292 | CG8: 292 | CH8: 292 | CI8: 292
A9: 875 | B9: 0.5 | D9: 1 | E9: 411 | F9: 411 | G9: 451 | H9: 411 | I9: 374 | J9: 374 | K9: 374 | L9: 374 | M9: 411 | N9: 451 | O9: 315 | P9: 315 | Q9: 315 | R9: 315 | S9: 315 | T9: 315 | U9: 315 | V9: 315 | W9: 315 | X9: 315 | Y9: 315 | Z9: 315 | AA9: 315 | AB9: 315 | AC9: 315 | AD9: 315 | AE9: 374 | AF9: 374 | AG9: 374 | AH9: 520 | AI9: 230 | AJ9: 230 | AK9: 230 | AL9: 230 | AM9: 230 | AN9: 240 | AO9: 240 | AP9: 240 | AQ9: 240 | AR9: 240 | AS9: 240 | AT9: 240 | AU9: 240 | AV9: 240 | AW9: 240 | AX9: 240 | AY9: 315 | AZ9: 315 | BA9: 315 | BB9: 315 | BC9: 315 | BD9: 315 | BE9: 374 | BF9: 490 | BG9: 490 | BH9: 451 | BI9: 490 | BJ9: 490 | BK9: 411 | BL9: 520 | BM9: 451 | BN9: 451 | BO9: 520 | BP9: 520 | BQ9: 520 | BR9: 520 | BS9: 315 | BT9: 315 | BU9: 315 | BV9: 315 | BW9: 315 | BX9: 374 | BY9: 374 | BZ9: 374 | CA9: 374 | CB9: 315 | CC9: 374 | CD9: 374 | CE9: 374 | CF9: 374 | CG9: 374 | CH9: 374 | CI9: 374
A10: 1050 | B10: 0.6 | E10: 471 | F10: 471 | G10: 513 | H10: 471 | I10: 421 | J10: 421 | K10: 421 | L10: 421 | M10: 471 | N10: 513 | O10: 350 | P10: 350 | Q10: 350 | R10: 350 | S10: 350 | T10: 350 | U10: 350 | V10: 350 | W10: 350 | X10: 350 | Y10: 350 | Z10: 350 | AA10: 350 | AB10: 350 | AC10: 350 | AD10: 350 | AE10: 421 | AF10: 421 | AG10: 421 | AH10: 591 | AI10: 265 | AJ10: 265 | AK10: 265 | AL10: 265 | AM10: 265 | AN10: 272 | AO10: 272 | AP10: 272 | AQ10: 272 | AR10: 272 | AS10: 272 | AT10: 272 | AU10: 272 | AV10: 272 | AW10: 272 | AX10: 272 | AY10: 350 | AZ10: 350 | BA10: 350 | BB10: 350 | BC10: 350 | BD10: 350 | BE10: 421 | BF10: 557 | BG10: 557 | BH10: 513 | BI10: 557 | BJ10: 557 | BK10: 471 | BL10: 591 | BM10: 513 | BN10: 513 | BO10: 591 | BP10: 591 | BQ10: 591 | BR10: 591 | BS10: 350 | BT10: 350 | BU10: 350 | BV10: 350 | BW10: 350 | BX10: 421 | BY10: 421 | BZ10: 421 | CA10: 421 | CB10: 350 | CC10: 421 | CD10: 421 | CE10: 421 | CF10: 421 | CG10: 421 | CH10: 421 | CI10: 421
A11: 1400 | B11: 0.8 | C11: 2 | E11: 531 | F11: 531 | G11: 576 | H11: 531 | I11: 468 | J11: 468 | K11: 468 | L11: 468 | M11: 531 | N11: 576 | O11: 380 | P11: 380 | Q11: 380 | R11: 380 | S11: 380 | T11: 380 | U11: 380 | V11: 380 | W11: 380 | X11: 380 | Y11: 380 | Z11: 380 | AA11: 380 | AB11: 380 | AC11: 380 | AD11: 380 | AE11: 468 | AF11: 468 | AG11: 468 | AH11: 665 | AI11: 297 | AJ11: 297 | AK11: 297 | AL11: 297 | AM11: 297 | AN11: 306 | AO11: 306 | AP11: 306 | AQ11: 306 | AR11: 306 | AS11: 306 | AT11: 306 | AU11: 306 | AV11: 306 | AW11: 306 | AX11: 306 | AY11: 380 | AZ11: 380 | BA11: 380 | BB11: 380 | BC11: 380 | BD11: 380 | BE11: 468 | BF11: 626 | BG11: 626 | BH11: 576 | BI11: 626 | BJ11: 626 | BK11: 531 | BL11: 665 | BM11: 576 | BN11: 576 | BO11: 665 | BP11: 665 | BQ11: 665 | BR11: 665 | BS11: 380 | BT11: 380 | BU11: 380 | BV11: 380 | BW11: 380 | BX11: 468 | BY11: 468 | BZ11: 468 | CA11: 468 | CB11: 380 | CC11: 468 | CD11: 468 | CE11: 468 | CF11: 468 | CG11: 468 | CH11: 468 | CI11: 468
A12: 1750 | B12: 1 | D12: 2 | E12: 568 | F12: 568 | G12: 613 | H12: 568 | I12: 504 | J12: 504 | K12: 504 | L12: 504 | M12: 568 | N12: 613 | O12: 416 | P12: 416 | Q12: 416 | R12: 416 | S12: 416 | T12: 416 | U12: 416 | V12: 416 | W12: 416 | X12: 416 | Y12: 416 | Z12: 416 | AA12: 416 | AB12: 416 | AC12: 416 | AD12: 416 | AE12: 504 | AF12: 504 | AG12: 504 | AH12: 701 | AI12: 333 | AJ12: 333 | AK12: 333 | AL12: 333 | AM12: 333 | AN12: 340 | AO12: 340 | AP12: 340 | AQ12: 340 | AR12: 340 | AS12: 340 | AT12: 340 | AU12: 340 | AV12: 340 | AW12: 340 | AX12: 340 | AY12: 416 | AZ12: 416 | BA12: 416 | BB12: 416 | BC12: 416 | BD12: 416 | BE12: 504 | BF12: 663 | BG12: 663 | BH12: 613 | BI12: 663 | BJ12: 663 | BK12: 568 | BL12: 701 | BM12: 613 | BN12: 613 | BO12: 701 | BP12: 701 | BQ12: 701 | BR12: 701 | BS12: 416 | BT12: 416 | BU12: 416 | BV12: 416 | BW12: 416 | BX12: 504 | BY12: 504 | BZ12: 504 | CA12: 504 | CB12: 416 | CC12: 504 | CD12: 504 | CE12: 504 | CF12: 504 | CG12: 504 | CH12: 504 | CI12: 504
A13: 2100 | B13: 1.2 | C13: 3 | E13: 648 | F13: 648 | G13: 643 | H13: 648 | I13: 533 | J13: 533 | K13: 533 | L13: 533 | M13: 648 | N13: 643 | O13: 448 | P13: 448 | Q13: 448 | R13: 448 | S13: 448 | T13: 448 | U13: 448 | V13: 448 | W13: 448 | X13: 448 | Y13: 448 | Z13: 448 | AA13: 448 | AB13: 448 | AC13: 448 | AD13: 448 | AE13: 533 | AF13: 533 | AG13: 533 | AH13: 727 | AI13: 364 | AJ13: 364 | AK13: 364 | AL13: 364 | AM13: 364 | AN13: 370 | AO13: 370 | AP13: 370 | AQ13: 370 | AR13: 370 | AS13: 370 | AT13: 370 | AU13: 370 | AV13: 370 | AW13: 370 | AX13: 370 | AY13: 448 | AZ13: 448 | BA13: 448 | BB13: 448 | BC13: 448 | BD13: 448 | BE13: 533 | BF13: 690 | BG13: 690 | BH13: 643 | BI13: 690 | BJ13: 690 | BK13: 648 | BL13: 727 | BM13: 643 | BN13: 643 | BO13: 727 | BP13: 727 | BQ13: 727 | BR13: 727 | BS13: 448 | BT13: 448 | BU13: 448 | BV13: 448 | BW13: 448 | BX13: 533 | BY13: 533 | BZ13: 533 | CA13: 533 | CB13: 448 | CC13: 533 | CD13: 533 | CE13: 533 | CF13: 533 | CG13: 533 | CH13: 533 | CI13: 533
A14: 2625 | B14: 1.5 | D14: 3 | E14: 696 | F14: 696 | G14: 693 | H14: 696 | I14: 584 | J14: 584 | K14: 584 | L14: 584 | M14: 696 | N14: 693 | O14: 497 | P14: 497 | Q14: 497 | R14: 497 | S14: 497 | T14: 497 | U14: 497 | V14: 497 | W14: 497 | X14: 497 | Y14: 497 | Z14: 497 | AA14: 497 | AB14: 497 | AC14: 497 | AD14: 497 | AE14: 584 | AF14: 584 | AG14: 584 | AH14: 768 | AI14: 414 | AJ14: 414 | AK14: 414 | AL14: 414 | AM14: 414 | AN14: 422 | AO14: 422 | AP14: 422 | AQ14: 422 | AR14: 422 | AS14: 422 | AT14: 422 | AU14: 422 | AV14: 422 | AW14: 422 | AX14: 422 | AY14: 497 | AZ14: 497 | BA14: 497 | BB14: 497 | BC14: 497 | BD14: 497 | BE14: 584 | BF14: 734 | BG14: 734 | BH14: 693 | BI14: 734 | BJ14: 734 | BK14: 696 | BL14: 768 | BM14: 693 | BN14: 693 | BO14: 768 | BP14: 768 | BQ14: 768 | BR14: 768 | BS14: 497 | BT14: 497 | BU14: 497 | BV14: 497 | BW14: 497 | BX14: 584 | BY14: 584 | BZ14: 584 | CA14: 584 | CB14: 497 | CC14: 584 | CD14: 584 | CE14: 584 | CF14: 584 | CG14: 584 | CH14: 584 | CI14: 584
A15: 2800 | B15: 1.6 | C15: 4 | E15: 722 | F15: 722 | G15: 707 | H15: 722 | I15: 608 | J15: 608 | K15: 608 | L15: 608 | M15: 722 | N15: 707 | O15: 524 | P15: 524 | Q15: 524 | R15: 524 | S15: 524 | T15: 524 | U15: 524 | V15: 524 | W15: 524 | X15: 524 | Y15: 524 | Z15: 524 | AA15: 524 | AB15: 524 | AC15: 524 | AD15: 524 | AE15: 608 | AF15: 608 | AG15: 608 | AH15: 781 | AI15: 437 | AJ15: 437 | AK15: 437 | AL15: 437 | AM15: 437 | AN15: 447 | AO15: 447 | AP15: 447 | AQ15: 447 | AR15: 447 | AS15: 447 | AT15: 447 | AU15: 447 | AV15: 447 | AW15: 447 | AX15: 447 | AY15: 524 | AZ15: 524 | BA15: 524 | BB15: 524 | BC15: 524 | BD15: 524 | BE15: 608 | BF15: 748 | BG15: 748 | BH15: 707 | BI15: 748 | BJ15: 748 | BK15: 722 | BL15: 781 | BM15: 707 | BN15: 707 | BO15: 781 | BP15: 781 | BQ15: 781 | BR15: 781 | BS15: 524 | BT15: 524 | BU15: 524 | BV15: 524 | BW15: 524 | BX15: 608 | BY15: 608 | BZ15: 608 | CA15: 608 | CB15: 524 | CC15: 608 | CD15: 608 | CE15: 608 | CF15: 608 | CG15: 608 | CH15: 608 | CI15: 608
A16: 3500 | B16: 2 | C16: 5 | D16: 4 | E16: 761 | F16: 761 | G16: 772 | H16: 761 | I16: 649 | J16: 649 | K16: 649 | L16: 649 | M16: 761 | N16: 772 | O16: 564 | P16: 564 | Q16: 564 | R16: 564 | S16: 564 | T16: 564 | U16: 564 | V16: 564 | W16: 564 | X16: 564 | Y16: 564 | Z16: 564 | AA16: 564 | AB16: 564 | AC16: 564 | AD16: 564 | AE16: 649 | AF16: 649 | AG16: 649 | AH16: 834 | AI16: 479 | AJ16: 479 | AK16: 479 | AL16: 479 | AM16: 479 | AN16: 486 | AO16: 486 | AP16: 486 | AQ16: 486 | AR16: 486 | AS16: 486 | AT16: 486 | AU16: 486 | AV16: 486 | AW16: 486 | AX16: 486 | AY16: 564 | AZ16: 564 | BA16: 564 | BB16: 564 | BC16: 564 | BD16: 564 | BE16: 649 | BF16: 805 | BG16: 805 | BH16: 772 | BI16: 805 | BJ16: 805 | BK16: 761 | BL16: 834 | BM16: 772 | BN16: 772 | BO16: 834 | BP16: 834 | BQ16: 834 | BR16: 834 | BS16: 564 | BT16: 564 | BU16: 564 | BV16: 564 | BW16: 564 | BX16: 649 | BY16: 649 | BZ16: 649 | CA16: 649 | CB16: 564 | CC16: 649 | CD16: 649 | CE16: 649 | CF16: 649 | CG16: 649 | CH16: 649 | CI16: 649
A17: 4200 | B17: 2.4 | C17: 6 | E17: 809 | F17: 809 | G17: 820 | H17: 809 | I17: 706 | J17: 706 | K17: 706 | L17: 706 | M17: 809 | N17: 820 | O17: 626 | P17: 626 | Q17: 626 | R17: 626 | S17: 626 | T17: 626 | U17: 626 | V17: 626 | W17: 626 | X17: 626 | Y17: 626 | Z17: 626 | AA17: 626 | AB17: 626 | AC17: 626 | AD17: 626 | AE17: 706 | AF17: 706 | AG17: 706 | AH17: 869 | AI17: 549 | AJ17: 549 | AK17: 549 | AL17: 549 | AM17: 549 | AN17: 555 | AO17: 555 | AP17: 555 | AQ17: 555 | AR17: 555 | AS17: 555 | AT17: 555 | AU17: 555 | AV17: 555 | AW17: 555 | AX17: 555 | AY17: 626 | AZ17: 626 | BA17: 626 | BB17: 626 | BC17: 626 | BD17: 626 | BE17: 706 | BF17: 844 | BG17: 844 | BH17: 820 | BI17: 844 | BJ17: 844 | BK17: 809 | BL17: 869 | BM17: 820 | BN17: 820 | BO17: 869 | BP17: 869 | BQ17: 869 | BR17: 869 | BS17: 626 | BT17: 626 | BU17: 626 | BV17: 626 | BW17: 626 | BX17: 706 | BY17: 706 | BZ17: 706 | CA17: 706 | CB17: 626 | CC17: 706 | CD17: 706 | CE17: 706 | CF17: 706 | CG17: 706 | CH17: 706 | CI17: 706
A18: 4375 | B18: 2.5 | D18: 5 | E18: 825 | F18: 825 | G18: 834 | H18: 825 | I18: 719 | J18: 719 | K18: 719 | L18: 719 | M18: 825 | N18: 834 | O18: 641 | P18: 641 | Q18: 641 | R18: 641 | S18: 641 | T18: 641 | U18: 641 | V18: 641 | W18: 641 | X18: 641 | Y18: 641 | Z18: 641 | AA18: 641 | AB18: 641 | AC18: 641 | AD18: 641 | AE18: 719 | AF18: 719 | AG18: 719 | AH18: 881 | AI18: 587 | AJ18: 587 | AK18: 587 | AL18: 587 | AM18: 587 | AN18: 596 | AO18: 596 | AP18: 596 | AQ18: 596 | AR18: 596 | AS18: 596 | AT18: 596 | AU18: 596 | AV18: 596 | AW18: 596 | AX18: 596 | AY18: 641 | AZ18: 641 | BA18: 641 | BB18: 641 | BC18: 641 | BD18: 641 | BE18: 719 | BF18: 859 | BG18: 859 | BH18: 834 | BI18: 859 | BJ18: 859 | BK18: 825 | BL18: 881 | BM18: 834 | BN18: 834 | BO18: 881 | BP18: 881 | BQ18: 881 | BR18: 881 | BS18: 641 | BT18: 641 | BU18: 641 | BV18: 641 | BW18: 641 | BX18: 719 | BY18: 719 | BZ18: 719 | CA18: 719 | CB18: 641 | CC18: 719 | CD18: 719 | CE18: 719 | CF18: 719 | CG18: 719 | CH18: 719 | CI18: 719
A19: 4900 | B19: 2.8 | C19: 7 | E19: 861 | F19: 861 | G19: 882 | H19: 861 | I19: 769 | J19: 769 | K19: 769 | L19: 769 | M19: 861 | N19: 882 | O19: 677 | P19: 677 | Q19: 677 | R19: 677 | S19: 677 | T19: 677 | U19: 677 | V19: 677 | W19: 677 | X19: 677 | Y19: 677 | Z19: 677 | AA19: 677 | AB19: 677 | AC19: 677 | AD19: 677 | AE19: 769 | AF19: 769 | AG19: 769 | AH19: 921 | AI19: 623 | AJ19: 623 | AK19: 623 | AL19: 623 | AM19: 623 | AN19: 632 | AO19: 632 | AP19: 632 | AQ19: 632 | AR19: 632 | AS19: 632 | AT19: 632 | AU19: 632 | AV19: 632 | AW19: 632 | AX19: 632 | AY19: 677 | AZ19: 677 | BA19: 677 | BB19: 677 | BC19: 677 | BD19: 677 | BE19: 769 | BF19: 900 | BG19: 900 | BH19: 882 | BI19: 900 | BJ19: 900 | BK19: 861 | BL19: 921 | BM19: 882 | BN19: 882 | BO19: 921 | BP19: 921 | BQ19: 921 | BR19: 921 | BS19: 677 | BT19: 677 | BU19: 677 | BV19: 677 | BW19: 677 | BX19: 769 | BY19: 769 | BZ19: 769 | CA19: 769 | CB19: 677 | CC19: 769 | CD19: 769 | CE19: 769 | CF19: 769 | CG19: 769 | CH19: 769 | CI19: 769
A20: 5250 | B20: 3 | D20: 6 | E20: 884 | F20: 884 | G20: 913 | H20: 884 | I20: 794 | J20: 794 | K20: 794 | L20: 794 | M20: 884 | N20: 913 | O20: 701 | P20: 701 | Q20: 701 | R20: 701 | S20: 701 | T20: 701 | U20: 701 | V20: 701 | W20: 701 | X20: 701 | Y20: 701 | Z20: 701 | AA20: 701 | AB20: 701 | AC20: 701 | AD20: 701 | AE20: 794 | AF20: 794 | AG20: 794 | AH20: 948 | AI20: 648 | AJ20: 648 | AK20: 648 | AL20: 648 | AM20: 648 | AN20: 656 | AO20: 656 | AP20: 656 | AQ20: 656 | AR20: 656 | AS20: 656 | AT20: 656 | AU20: 656 | AV20: 656 | AW20: 656 | AX20: 656 | AY20: 701 | AZ20: 701 | BA20: 701 | BB20: 701 | BC20: 701 | BD20: 701 | BE20: 794 | BF20: 930 | BG20: 930 | BH20: 913 | BI20: 930 | BJ20: 930 | BK20: 884 | BL20: 948 | BM20: 913 | BN20: 913 | BO20: 948 | BP20: 948 | BQ20: 948 | BR20: 948 | BS20: 701 | BT20: 701 | BU20: 701 | BV20: 701 | BW20: 701 | BX20: 794 | BY20: 794 | BZ20: 794 | CA20: 794 | CB20: 701 | CC20: 794 | CD20: 794 | CE20: 794 | CF20: 794 | CG20: 794 | CH20: 794 | CI20: 794
A21: 5600 | B21: 3.2 | C21: 8 | E21: 905 | F21: 905 | G21: 951 | H21: 905 | I21: 812 | J21: 812 | K21: 812 | L21: 812 | M21: 905 | N21: 951 | O21: 723 | P21: 723 | Q21: 723 | R21: 723 | S21: 723 | T21: 723 | U21: 723 | V21: 723 | W21: 723 | X21: 723 | Y21: 723 | Z21: 723 | AA21: 723 | AB21: 723 | AC21: 723 | AD21: 723 | AE21: 812 | AF21: 812 | AG21: 812 | AH21: 988 | AI21: 669 | AJ21: 669 | AK21: 669 | AL21: 669 | AM21: 669 | AN21: 678 | AO21: 678 | AP21: 678 | AQ21: 678 | AR21: 678 | AS21: 678 | AT21: 678 | AU21: 678 | AV21: 678 | AW21: 678 | AX21: 678 | AY21: 723 | AZ21: 723 | BA21: 723 | BB21: 723 | BC21: 723 | BD21: 723 | BE21: 812 | BF21: 969 | BG21: 969 | BH21: 951 | BI21: 969 | BJ21: 969 | BK21: 905 | BL21: 988 | BM21: 951 | BN21: 951 | BO21: 988 | BP21: 988 | BQ21: 988 | BR21: 988 | BS21: 723 | BT21: 723 | BU21: 723 | BV21: 723 | BW21: 723 | BX21: 812 | BY21: 812 | BZ21: 812 | CA21: 812 | CB21: 723 | CC21: 812 | CD21: 812 | CE21: 812 | CF21: 812 | CG21: 812 | CH21: 812 | CI21: 812
A22: 6125 | B22: 3.5 | D22: 7 | E22: 1036 | F22: 1036 | G22: 1011 | H22: 1036 | I22: 918 | J22: 918 | K22: 918 | L22: 918 | M22: 1036 | N22: 1011 | O22: 804 | P22: 804 | Q22: 804 | R22: 804 | S22: 804 | T22: 804 | U22: 804 | V22: 804 | W22: 804 | X22: 804 | Y22: 804 | Z22: 804 | AA22: 804 | AB22: 804 | AC22: 804 | AD22: 804 | AE22: 918 | AF22: 918 | AG22: 918 | AH22: 1048 | AI22: 716 | AJ22: 716 | AK22: 716 | AL22: 716 | AM22: 716 | AN22: 733 | AO22: 733 | AP22: 733 | AQ22: 733 | AR22: 733 | AS22: 733 | AT22: 733 | AU22: 733 | AV22: 733 | AW22: 733 | AX22: 733 | AY22: 804 | AZ22: 804 | BA22: 804 | BB22: 804 | BC22: 804 | BD22: 804 | BE22: 918 | BF22: 1028 | BG22: 1028 | BH22: 1011 | BI22: 1028 | BJ22: 1028 | BK22: 1036 | BL22: 1048 | BM22: 1011 | BN22: 1011 | BO22: 1048 | BP22: 1048 | BQ22: 1048 | BR22: 1048 | BS22: 804 | BT22: 804 | BU22: 804 | BV22: 804 | BW22: 804 | BX22: 918 | BY22: 918 | BZ22: 918 | CA22: 918 | CB22: 804 | CC22: 918 | CD22: 918 | CE22: 918 | CF22: 918 | CG22: 918 | CH22: 918 | CI22: 918
A23: 6300 | B23: 3.6 | C23: 9 | E23: 1050 | F23: 1050 | G23: 1032 | H23: 1050 | I23: 935 | J23: 935 | K23: 935 | L23: 935 | M23: 1050 | N23: 1032 | O23: 819 | P23: 819 | Q23: 819 | R23: 819 | S23: 819 | T23: 819 | U23: 819 | V23: 819 | W23: 819 | X23: 819 | Y23: 819 | Z23: 819 | AA23: 819 | AB23: 819 | AC23: 819 | AD23: 819 | AE23: 935 | AF23: 935 | AG23: 935 | AH23: 1065 | AI23: 733 | AJ23: 733 | AK23: 733 | AL23: 733 | AM23: 733 | AN23: 748 | AO23: 748 | AP23: 748 | AQ23: 748 | AR23: 748 | AS23: 748 | AT23: 748 | AU23: 748 | AV23: 748 | AW23: 748 | AX23: 748 | AY23: 819 | AZ23: 819 | BA23: 819 | BB23: 819 | BC23: 819 | BD23: 819 | BE23: 935 | BF23: 1048 | BG23: 1048 | BH23: 1032 | BI23: 1048 | BJ23: 1048 | BK23: 1050 | BL23: 1065 | BM23: 1032 | BN23: 1032 | BO23: 1065 | BP23: 1065 | BQ23: 1065 | BR23: 1065 | BS23: 819 | BT23: 819 | BU23: 819 | BV23: 819 | BW23: 819 | BX23: 935 | BY23: 935 | BZ23: 935 | CA23: 935 | CB23: 819 | CC23: 935 | CD23: 935 | CE23: 935 | CF23: 935 | CG23: 935 | CH23: 935 | CI23: 935
A24: 7000 | B24: 4 | C24: 10 | D24: 8 | E24: 1096 | F24: 1096 | G24: 1107 | H24: 1096 | I24: 981 | J24: 981 | K24: 981 | L24: 981 | M24: 1096 | N24: 1107 | O24: 865 | P24: 865 | Q24: 865 | R24: 865 | S24: 865 | T24: 865 | U24: 865 | V24: 865 | W24: 865 | X24: 865 | Y24: 865 | Z24: 865 | AA24: 865 | AB24: 865 | AC24: 865 | AD24: 865 | AE24: 981 | AF24: 981 | AG24: 981 | AH24: 1145 | AI24: 778 | AJ24: 778 | AK24: 778 | AL24: 778 | AM24: 778 | AN24: 794 | AO24: 794 | AP24: 794 | AQ24: 794 | AR24: 794 | AS24: 794 | AT24: 794 | AU24: 794 | AV24: 794 | AW24: 794 | AX24: 794 | AY24: 865 | AZ24: 865 | BA24: 865 | BB24: 865 | BC24: 865 | BD24: 865 | BE24: 981 | BF24: 1125 | BG24: 1125 | BH24: 1107 | BI24: 1125 | BJ24: 1125 | BK24: 1096 | BL24: 1145 | BM24: 1107 | BN24: 1107 | BO24: 1145 | BP24: 1145 | BQ24: 1145 | BR24: 1145 | BS24: 865 | BT24: 865 | BU24: 865 | BV24: 865 | BW24: 865 | BX24: 981 | BY24: 981 | BZ24: 981 | CA24: 981 | CB24: 865 | CC24: 981 | CD24: 981 | CE24: 981 | CF24: 981 | CG24: 981 | CH24: 981 | CI24: 981
A26: Transittijden:
A28: Dag van lading is dag 0 | C28: Vertrek | G28: Transittijd in werkdagen | T28: Transittijd in werkdagen | AD28: Transittijd in werkdagen | AQ28: Transittijd in werkdagen | BD28: Transittijd in werkdagen | BQ28: Transittijd in werkdagen
A29: Groupage 1-5 pallets | C29: ma,di,wo,vrij | E29: 2/3 | F29: 2/3 | G29: 2/3 | H29: 2/3 | I29: 2/3 | J29: 2/3 | K29: 2/3 | L29: 2/3 | M29: 2/3 | N29: 2/3 | O29: 2/3 | P29: 2/3 | Q29: 2/3 | R29: 2/3 | S29: 2/3 | T29: 2/3 | U29: 2/3 | V29: 2/3 | W29: 2/3 | X29: 2/3 | Y29: 2/3 | Z29: 2/3 | AA29: 2/3 | AB29: 2/3 | AC29: 2/3 | AD29: 2/3 | AE29: 2/3 | AF29: 2/3 | AG29: 2/3 | AH29: 2/3 | AI29: 2/3 | AJ29: 2/3 | AK29: 2/3 | AL29: 2/3 | AM29: 2/3 | AN29: 2/3 | AO29: 2/3 | AP29: 2/3 | AQ29: 2/3 | AR29: 2/3 | AS29: 2/3 | AT29: 2/3 | AU29: 2/3 | AV29: 2/3 | AW29: 2/3 | AX29: 2/3 | AY29: 2/3 | AZ29: 2/3 | BA29: 2/3 | BB29: 2/3 | BC29: 2/3 | BD29: 2/3 | BE29: 2/3 | BF29: 2/3 | BG29: 2/3 | BH29: 2/3 | BI29: 2/3 | BJ29: 2/3 | BK29: 2/3 | BL29: 2/3 | BM29: 2/3 | BN29: 2/3 | BO29: 2/3 | BP29: 2/3 | BQ29: 2/3 | BR29: 2/3 | BS29: 2/3 | BT29: 2/3 | BU29: 2/3 | BV29: 2/3 | BW29: 2/3 | BX29: 2/3 | BY29: 2/3 | BZ29: 2/3 | CA29: 2/3 | CB29: 2/3 | CC29: 2/3 | CD29: 2/3 | CE29: 2/3 | CF29: 2/3 | CG29: 2/3 | CH29: 2/3 | CI29: 2/3
A30: Deelpartijen > 5 pallets | C30: ma,di,wo,vrij | E30: 2 | F30: 2 | G30: 2 | H30: 2 | I30: 2 | J30: 2 | K30: 2 | L30: 2 | M30: 2 | N30: 2 | O30: 2 | P30: 2 | Q30: 2 | R30: 2 | S30: 2 | T30: 2 | U30: 2 | V30: 2 | W30: 2 | X30: 2 | Y30: 2 | Z30: 2 | AA30: 2 | AB30: 2 | AC30: 2 | AD30: 2 | AE30: 2 | AF30: 3 | AG30: 3 | AH30: 3 | AI30: 2 | AJ30: 2 | AK30: 2 | AL30: 2 | AM30: 2 | AN30: 2 | AO30: 2 | AP30: 2 | AQ30: 2 | AR30: 2 | AS30: 2 | AT30: 2 | AU30: 2 | AV30: 2 | AW30: 2 | AX30: 2 | AY30: 2 | AZ30: 2 | BA30: 2 | BB30: 2 | BC30: 2 | BD30: 2 | BE30: 2 | BF30: 3 | BG30: 3 | BH30: 3 | BI30: 3 | BJ30: 3 | BK30: 3 | BL30: 3 | BM30: 3 | BN30: 3 | BO30: 2 | BP30: 2 | BQ30: 2 | BR30: 2 | BS30: 2 | BT30: 2 | BU30: 2 | BV30: 2 | BW30: 2 | BX30: 2 | BY30: 2 | BZ30: 2 | CA30: 2 | CB30: 2 | CC30: 2 | CD30: 2 | CE30: 2 | CF30: 2 | CG30: 2 | CH30: 2 | CI30: 2
A31: Compleet ladingen | C31: ma,di,wo,do,vrij | E31: 2 | F31: 2 | G31: 2 | H31: 2 | I31: 2 | J31: 2 | K31: 2 | L31: 2 | M31: 2 | N31: 2 | O31: 2 | P31: 2 | Q31: 2 | R31: 2 | S31: 2 | T31: 2 | U31: 2 | V31: 2 | W31: 2 | X31: 2 | Y31: 2 | Z31: 2 | AA31: 2 | AB31: 2 | AC31: 2 | AD31: 2 | AE31: 2 | AF31: 2 | AG31: 2 | AH31: 2 | AI31: 2 | AJ31: 2 | AK31: 2 | AL31: 2 | AM31: 2 | AN31: 2 | AO31: 2 | AP31: 2 | AQ31: 2 | AR31: 2 | AS31: 2 | AT31: 2 | AU31: 2 | AV31: 2 | AW31: 2 | AX31: 2 | AY31: 2 | AZ31: 2 | BA31: 2 | BB31: 2 | BC31: 2 | BD31: 2 | BE31: 2 | BF31: 2 | BG31: 2 | BH31: 2 | BI31: 2 | BJ31: 2 | BK31: 2 | BL31: 2 | BM31: 2 | BN31: 2 | BO31: 2 | BP31: 2 | BQ31: 2 | BR31: 2 | BS31: 2 | BT31: 2 | BU31: 2 | BV31: 2 | BW31: 2 | BX31: 2 | BY31: 2 | BZ31: 2 | CA31: 2 | CB31: 2 | CC31: 2 | CD31: 2 | CE31: 2 | CF31: 2 | CG31: 2 | CH31: 2 | CI31: 2

Sheet CZ
A3: =Voorblad!A5 -> Team Freight Forwarding Logistics
A4: Export Tsjechië
A6: kg | B6: ldm | C6: euplt | D6: blkplt | E6: 10 | F6: 11 | G6: 12 | H6: 13 | I6: 14 | J6: 15 | K6: 16 | L6: 17 | M6: 18 | N6: 19 | O6: 25 | P6: 26 | Q6: 27 | R6: 28 | S6: 29 | T6: 30 | U6: 31 | V6: 32 | W6: 33 | X6: 34 | Y6: 35 | Z6: 36 | AA6: 37 | AB6: 38 | AC6: 39 | AD6: 40 | AE6: 41 | AF6: 43 | AG6: 44 | AH6: 46 | AI6: 47 | AJ6: 50 | AK6: 51 | AL6: 53 | AM6: 54 | AN6: 55 | AO6: 56 | AP6: 57 | AQ6: 58 | AR6: 59 | AS6: 60 | AT6: 61 | AU6: 62 | AV6: 63 | AW6: 64 | AX6: 65 | AY6: 66 | AZ6: 67 | BA6: 68 | BB6: 69 | BC6: 70 | BD6: 71 | BE6: 72 | BF6: 73 | BG6: 74 | BH6: 75 | BI6: 76 | BJ6: 77 | BK6: 78 | BL6: 79
A7: 300 | B7: 0.2 | C7: 0.5 | E7: 67 | F7: 67 | G7: 67 | H7: 67 | I7: 67 | J7: 67 | K7: 67 | L7: 67 | M7: 67 | N7: 67 | O7: 73 | P7: 73 | Q7: 73 | R7: 73 | S7: 73 | T7: 76 | U7: 76 | V7: 76 | W7: 76 | X7: 79 | Y7: 81 | Z7: 76 | AA7: 76 | AB7: 76 | AC7: 76 | AD7: 76 | AE7: 76 | AF7: 76 | AG7: 76 | AH7: 76 | AI7: 76 | AJ7: 76 | AK7: 76 | AL7: 76 | AM7: 76 | AN7: 76 | AO7: 76 | AP7: 76 | AQ7: 76 | AR7: 76 | AS7: 73 | AT7: 73 | AU7: 73 | AV7: 73 | AW7: 73 | AX7: 79 | AY7: 79 | AZ7: 79 | BA7: 79 | BB7: 79 | BC7: 82 | BD7: 76 | BE7: 76 | BF7: 76 | BG7: 76 | BH7: 83 | BI7: 76 | BJ7: 76 | BK7: 76 | BL7: 85
A8: 700 | B8: 0.4 | C8: 1 | E8: 107 | F8: 107 | G8: 107 | H8: 107 | I8: 107 | J8: 107 | K8: 107 | L8: 107 | M8: 107 | N8: 107 | O8: 116 | P8: 116 | Q8: 116 | R8: 116 | S8: 116 | T8: 123 | U8: 123 | V8: 123 | W8: 123 | X8: 131 | Y8: 136 | Z8: 123 | AA8: 123 | AB8: 123 | AC8: 123 | AD8: 123 | AE8: 123 | AF8: 123 | AG8: 123 | AH8: 123 | AI8: 123 | AJ8: 123 | AK8: 123 | AL8: 123 | AM8: 123 | AN8: 123 | AO8: 124 | AP8: 124 | AQ8: 124 | AR8: 124 | AS8: 116 | AT8: 116 | AU8: 116 | AV8: 116 | AW8: 116 | AX8: 132 | AY8: 132 | AZ8: 132 | BA8: 132 | BB8: 132 | BC8: 138 | BD8: 138 | BE8: 138 | BF8: 138 | BG8: 138 | BH8: 141 | BI8: 141 | BJ8: 141 | BK8: 141 | BL8: 144
A9: 875 | B9: 0.5 | D9: 1 | E9: 121 | F9: 121 | G9: 121 | H9: 121 | I9: 121 | J9: 121 | K9: 121 | L9: 121 | M9: 121 | N9: 121 | O9: 133 | P9: 133 | Q9: 133 | R9: 133 | S9: 133 | T9: 142 | U9: 142 | V9: 142 | W9: 142 | X9: 150 | Y9: 156 | Z9: 142 | AA9: 142 | AB9: 142 | AC9: 142 | AD9: 142 | AE9: 142 | AF9: 142 | AG9: 142 | AH9: 142 | AI9: 142 | AJ9: 142 | AK9: 142 | AL9: 142 | AM9: 142 | AN9: 142 | AO9: 142 | AP9: 142 | AQ9: 142 | AR9: 142 | AS9: 133 | AT9: 133 | AU9: 133 | AV9: 133 | AW9: 133 | AX9: 151 | AY9: 151 | AZ9: 151 | BA9: 151 | BB9: 151 | BC9: 159 | BD9: 159 | BE9: 159 | BF9: 159 | BG9: 159 | BH9: 161 | BI9: 161 | BJ9: 161 | BK9: 166 | BL9: 170
A10: 1050 | B10: 0.6 | E10: 159 | F10: 159 | G10: 159 | H10: 159 | I10: 159 | J10: 159 | K10: 159 | L10: 159 | M10: 159 | N10: 159 | O10: 182 | P10: 182 | Q10: 182 | R10: 182 | S10: 182 | T10: 197 | U10: 197 | V10: 197 | W10: 197 | X10: 214 | Y10: 225 | Z10: 197 | AA10: 197 | AB10: 197 | AC10: 197 | AD10: 197 | AE10: 197 | AF10: 197 | AG10: 197 | AH10: 197 | AI10: 197 | AJ10: 197 | AK10: 197 | AL10: 197 | AM10: 197 | AN10: 197 | AO10: 198 | AP10: 198 | AQ10: 198 | AR10: 198 | AS10: 182 | AT10: 182 | AU10: 182 | AV10: 182 | AW10: 182 | AX10: 217 | AY10: 217 | AZ10: 217 | BA10: 217 | BB10: 217 | BC10: 231 | BD10: 231 | BE10: 231 | BF10: 231 | BG10: 231 | BH10: 236 | BI10: 236 | BJ10: 236 | BK10: 241 | BL10: 255
A11: 1400 | B11: 0.8 | C11: 2 | E11: 193 | F11: 193 | G11: 193 | H11: 193 | I11: 193 | J11: 193 | K11: 193 | L11: 193 | M11: 193 | N11: 193 | O11: 211 | P11: 211 | Q11: 211 | R11: 211 | S11: 211 | T11: 223 | U11: 223 | V11: 223 | W11: 223 | X11: 237 | Y11: 245 | Z11: 223 | AA11: 223 | AB11: 223 | AC11: 223 | AD11: 223 | AE11: 223 | AF11: 223 | AG11: 223 | AH11: 223 | AI11: 223 | AJ11: 223 | AK11: 223 | AL11: 223 | AM11: 223 | AN11: 223 | AO11: 224 | AP11: 224 | AQ11: 224 | AR11: 224 | AS11: 211 | AT11: 211 | AU11: 211 | AV11: 211 | AW11: 211 | AX11: 238 | AY11: 238 | AZ11: 238 | BA11: 238 | BB11: 238 | BC11: 254 | BD11: 254 | BE11: 254 | BF11: 254 | BG11: 254 | BH11: 253 | BI11: 253 | BJ11: 253 | BK11: 253 | BL11: 266
A12: 1750 | B12: 1 | D12: 2 | E12: 219 | F12: 219 | G12: 219 | H12: 219 | I12: 219 | J12: 219 | K12: 219 | L12: 219 | M12: 219 | N12: 219 | O12: 241 | P12: 241 | Q12: 241 | R12: 241 | S12: 241 | T12: 255 | U12: 255 | V12: 255 | W12: 255 | X12: 273 | Y12: 285 | Z12: 255 | AA12: 255 | AB12: 255 | AC12: 255 | AD12: 255 | AE12: 255 | AF12: 255 | AG12: 255 | AH12: 255 | AI12: 255 | AJ12: 255 | AK12: 255 | AL12: 255 | AM12: 255 | AN12: 255 | AO12: 257 | AP12: 257 | AQ12: 257 | AR12: 257 | AS12: 241 | AT12: 241 | AU12: 241 | AV12: 241 | AW12: 241 | AX12: 275 | AY12: 275 | AZ12: 275 | BA12: 275 | BB12: 275 | BC12: 291 | BD12: 291 | BE12: 291 | BF12: 291 | BG12: 291 | BH12: 294 | BI12: 294 | BJ12: 294 | BK12: 294 | BL12: 310
A13: 2100 | B13: 1.2 | C13: 3 | E13: 267 | F13: 267 | G13: 267 | H13: 267 | I13: 267 | J13: 267 | K13: 267 | L13: 267 | M13: 267 | N13: 267 | O13: 291 | P13: 291 | Q13: 291 | R13: 291 | S13: 291 | T13: 309 | U13: 309 | V13: 309 | W13: 309 | X13: 327 | Y13: 339 | Z13: 309 | AA13: 309 | AB13: 309 | AC13: 309 | AD13: 309 | AE13: 309 | AF13: 309 | AG13: 309 | AH13: 309 | AI13: 309 | AJ13: 309 | AK13: 309 | AL13: 309 | AM13: 309 | AN13: 309 | AO13: 310 | AP13: 310 | AQ13: 310 | AR13: 310 | AS13: 291 | AT13: 291 | AU13: 291 | AV13: 291 | AW13: 291 | AX13: 330 | AY13: 330 | AZ13: 330 | BA13: 330 | BB13: 330 | BC13: 340 | BD13: 340 | BE13: 340 | BF13: 340 | BG13: 340 | BH13: 352 | BI13: 352 | BJ13: 352 | BK13: 352 | BL13: 362
A14: 2625 | B14: 1.5 | D14: 3 | E14: 305 | F14: 305 | G14: 305 | H14: 305 | I14: 305 | J14: 305 | K14: 305 | L14: 305 | M14: 305 | N14: 305 | O14: 336 | P14: 336 | Q14: 336 | R14: 336 | S14: 336 | T14: 357 | U14: 357 | V14: 357 | W14: 357 | X14: 380 | Y14: 396 | Z14: 357 | AA14: 357 | AB14: 357 | AC14: 357 | AD14: 357 | AE14: 357 | AF14: 357 | AG14: 357 | AH14: 357 | AI14: 357 | AJ14: 357 | AK14: 357 | AL14: 357 | AM14: 357 | AN14: 357 | AO14: 358 | AP14: 358 | AQ14: 358 | AR14: 358 | AS14: 335 | AT14: 335 | AU14: 335 | AV14: 335 | AW14: 335 | AX14: 383 | AY14: 383 | AZ14: 383 | BA14: 383 | BB14: 383 | BC14: 390 | BD14: 390 | BE14: 390 | BF14: 390 | BG14: 390 | BH14: 410 | BI14: 410 | BJ14: 410 | BK14: 410 | BL14: 423
A15: 2800 | B15: 1.6 | C15: 4 | E15: 343 | F15: 343 | G15: 343 | H15: 343 | I15: 343 | J15: 343 | K15: 343 | L15: 343 | M15: 343 | N15: 343 | O15: 377 | P15: 354 | Q15: 354 | R15: 377 | S15: 377 | T15: 399 | U15: 399 | V15: 399 | W15: 399 | X15: 424 | Y15: 440 | Z15: 399 | AA15: 399 | AB15: 399 | AC15: 399 | AD15: 399 | AE15: 399 | AF15: 399 | AG15: 399 | AH15: 399 | AI15: 399 | AJ15: 399 | AK15: 399 | AL15: 399 | AM15: 399 | AN15: 399 | AO15: 400 | AP15: 400 | AQ15: 400 | AR15: 400 | AS15: 377 | AT15: 377 | AU15: 377 | AV15: 377 | AW15: 377 | AX15: 427 | AY15: 427 | AZ15: 427 | BA15: 427 | BB15: 427 | BC15: 435 | BD15: 435 | BE15: 435 | BF15: 435 | BG15: 435 | BH15: 456 | BI15: 456 | BJ15: 456 | BK15: 456 | BL15: 470
A16: 3500 | B16: 2 | C16: 5 | D16: 4 | E16: 369 | F16: 369 | G16: 369 | H16: 369 | I16: 369 | J16: 369 | K16: 369 | L16: 369 | M16: 369 | N16: 369 | O16: 381 | P16: 369 | Q16: 369 | R16: 402 | S16: 415 | T16: 407 | U16: 407 | V16: 409 | W16: 408 | X16: 432 | Y16: 448 | Z16: 409 | AA16: 486 | AB16: 423 | AC16: 418 | AD16: 406 | AE16: 406 | AF16: 406 | AG16: 406 | AH16: 443 | AI16: 408 | AJ16: 477 | AK16: 454 | AL16: 494 | AM16: 497 | AN16: 497 | AO16: 499 | AP16: 499 | AQ16: 450 | AR16: 497 | AS16: 470 | AT16: 470 | AU16: 470 | AV16: 470 | AW16: 470 | AX16: 533 | AY16: 533 | AZ16: 521 | BA16: 533 | BB16: 533 | BC16: 536 | BD16: 536 | BE16: 536 | BF16: 536 | BG16: 536 | BH16: 569 | BI16: 569 | BJ16: 569 | BK16: 569 | BL16: 586
A17: 4200 | B17: 2.4 | C17: 6 | E17: 405 | F17: 405 | G17: 405 | H17: 405 | I17: 405 | J17: 405 | K17: 405 | L17: 405 | M17: 405 | N17: 405 | O17: 416 | P17: 405 | Q17: 405 | R17: 436 | S17: 450 | T17: 415 | U17: 415 | V17: 418 | W17: 417 | X17: 439 | Y17: 455 | Z17: 420 | AA17: 519 | AB17: 447 | AC17: 439 | AD17: 409 | AE17: 409 | AF17: 409 | AG17: 409 | AH17: 486 | AI17: 429 | AJ17: 509 | AK17: 486 | AL17: 525 | AM17: 529 | AN17: 529 | AO17: 530 | AP17: 530 | AQ17: 483 | AR17: 529 | AS17: 502 | AT17: 502 | AU17: 502 | AV17: 502 | AW17: 502 | AX17: 565 | AY17: 565 | AZ17: 551 | BA17: 565 | BB17: 565 | BC17: 567 | BD17: 567 | BE17: 567 | BF17: 567 | BG17: 567 | BH17: 598 | BI17: 598 | BJ17: 598 | BK17: 598 | BL17: 616
A18: 4375 | B18: 2.5 | D18: 5 | E18: 412 | F18: 412 | G18: 412 | H18: 412 | I18: 412 | J18: 412 | K18: 412 | L18: 412 | M18: 412 | N18: 412 | O18: 424 | P18: 412 | Q18: 412 | R18: 445 | S18: 457 | T18: 424 | U18: 424 | V18: 429 | W18: 427 | X18: 447 | Y18: 463 | Z18: 431 | AA18: 527 | AB18: 471 | AC18: 460 | AD18: 412 | AE18: 412 | AF18: 412 | AG18: 412 | AH18: 495 | AI18: 438 | AJ18: 518 | AK18: 495 | AL18: 533 | AM18: 537 | AN18: 537 | AO18: 539 | AP18: 539 | AQ18: 491 | AR18: 538 | AS18: 510 | AT18: 510 | AU18: 510 | AV18: 510 | AW18: 510 | AX18: 572 | AY18: 572 | AZ18: 561 | BA18: 572 | BB18: 572 | BC18: 574 | BD18: 574 | BE18: 574 | BF18: 574 | BG18: 574 | BH18: 608 | BI18: 608 | BJ18: 608 | BK18: 608 | BL18: 624
A19: 4900 | B19: 2.8 | C19: 7 | E19: 423 | F19: 423 | G19: 423 | H19: 423 | I19: 423 | J19: 423 | K19: 423 | L19: 423 | M19: 423 | N19: 423 | O19: 435 | P19: 423 | Q19: 423 | R19: 455 | S19: 468 | T19: 434 | U19: 433 | V19: 439 | W19: 437 | X19: 454 | Y19: 471 | Z19: 441 | AA19: 538 | AB19: 481 | AC19: 470 | AD19: 437 | AE19: 437 | AF19: 437 | AG19: 437 | AH19: 505 | AI19: 448 | AJ19: 528 | AK19: 505 | AL19: 544 | AM19: 562 | AN19: 548 | AO19: 561 | AP19: 564 | AQ19: 501 | AR19: 547 | AS19: 536 | AT19: 536 | AU19: 536 | AV19: 536 | AW19: 536 | AX19: 597 | AY19: 597 | AZ19: 571 | BA19: 597 | BB19: 597 | BC19: 598 | BD19: 598 | BE19: 598 | BF19: 598 | BG19: 598 | BH19: 631 | BI19: 631 | BJ19: 631 | BK19: 631 | BL19: 649
A20: 5250 | B20: 3 | D20: 6 | E20: 434 | F20: 434 | G20: 434 | H20: 434 | I20: 434 | J20: 434 | K20: 434 | L20: 434 | M20: 434 | N20: 434 | O20: 446 | P20: 434 | Q20: 434 | R20: 464 | S20: 479 | T20: 443 | U20: 441 | V20: 450 | W20: 447 | X20: 461 | Y20: 479 | Z20: 452 | AA20: 547 | AB20: 492 | AC20: 481 | AD20: 444 | AE20: 444 | AF20: 444 | AG20: 444 | AH20: 515 | AI20: 458 | AJ20: 539 | AK20: 515 | AL20: 553 | AM20: 586 | AN20: 562 | AO20: 580 | AP20: 588 | AQ20: 512 | AR20: 557 | AS20: 561 | AT20: 561 | AU20: 561 | AV20: 561 | AW20: 561 | AX20: 622 | AY20: 622 | AZ20: 580 | BA20: 622 | BB20: 622 | BC20: 623 | BD20: 623 | BE20: 623 | BF20: 623 | BG20: 623 | BH20: 656 | BI20: 656 | BJ20: 656 | BK20: 656 | BL20: 673
A21: 5600 | B21: 3.2 | C21: 8 | E21: 450 | F21: 450 | G21: 450 | H21: 450 | I21: 450 | J21: 450 | K21: 450 | L21: 450 | M21: 450 | N21: 450 | O21: 461 | P21: 450 | Q21: 450 | R21: 481 | S21: 495 | T21: 451 | U21: 450 | V21: 459 | W21: 456 | X21: 468 | Y21: 486 | Z21: 462 | AA21: 564 | AB21: 507 | AC21: 497 | AD21: 450 | AE21: 450 | AF21: 450 | AG21: 450 | AH21: 531 | AI21: 475 | AJ21: 554 | AK21: 531 | AL21: 571 | AM21: 612 | AN21: 577 | AO21: 596 | AP21: 608 | AQ21: 528 | AR21: 574 | AS21: 598 | AT21: 598 | AU21: 598 | AV21: 598 | AW21: 598 | AX21: 645 | AY21: 649 | AZ21: 596 | BA21: 649 | BB21: 649 | BC21: 646 | BD21: 646 | BE21: 646 | BF21: 646 | BG21: 646 | BH21: 672 | BI21: 672 | BJ21: 672 | BK21: 672 | BL21: 704
A22: 6125 | B22: 3.5 | D22: 7 | E22: 474 | F22: 474 | G22: 474 | H22: 474 | I22: 474 | J22: 474 | K22: 474 | L22: 474 | M22: 474 | N22: 474 | O22: 485 | P22: 474 | Q22: 474 | R22: 505 | S22: 519 | T22: 475 | U22: 474 | V22: 484 | W22: 480 | X22: 476 | Y22: 494 | Z22: 474 | AA22: 588 | AB22: 532 | AC22: 522 | AD22: 474 | AE22: 474 | AF22: 474 | AG22: 474 | AH22: 555 | AI22: 499 | AJ22: 578 | AK22: 555 | AL22: 594 | AM22: 636 | AN22: 600 | AO22: 621 | AP22: 632 | AQ22: 551 | AR22: 598 | AS22: 623 | AT22: 623 | AU22: 623 | AV22: 623 | AW22: 623 | AX22: 669 | AY22: 673 | AZ22: 621 | BA22: 673 | BB22: 673 | BC22: 670 | BD22: 670 | BE22: 670 | BF22: 670 | BG22: 670 | BH22: 696 | BI22: 696 | BJ22: 696 | BK22: 696 | BL22: 727
A23: 6300 | B23: 3.6 | C23: 9 | E23: 482 | F23: 482 | G23: 482 | H23: 482 | I23: 482 | J23: 482 | K23: 482 | L23: 482 | M23: 482 | N23: 482 | O23: 494 | P23: 482 | Q23: 482 | R23: 513 | S23: 527 | T23: 483 | U23: 482 | V23: 492 | W23: 489 | X23: 484 | Y23: 501 | Z23: 482 | AA23: 595 | AB23: 540 | AC23: 529 | AD23: 482 | AE23: 482 | AF23: 482 | AG23: 482 | AH23: 565 | AI23: 506 | AJ23: 587 | AK23: 565 | AL23: 603 | AM23: 643 | AN23: 610 | AO23: 629 | AP23: 643 | AQ23: 561 | AR23: 607 | AS23: 640 | AT23: 640 | AU23: 640 | AV23: 640 | AW23: 640 | AX23: 677 | AY23: 682 | AZ23: 629 | BA23: 690 | BB23: 690 | BC23: 681 | BD23: 681 | BE23: 681 | BF23: 681 | BG23: 681 | BH23: 710 | BI23: 710 | BJ23: 710 | BK23: 710 | BL23: 750
A24: 7000 | B24: 4 | C24: 10 | D24: 8 | E24: 514 | F24: 514 | G24: 514 | H24: 514 | I24: 514 | J24: 514 | K24: 514 | L24: 514 | M24: 514 | N24: 514 | O24: 526 | P24: 514 | Q24: 514 | R24: 545 | S24: 560 | T24: 515 | U24: 514 | V24: 524 | W24: 521 | X24: 517 | Y24: 517 | Z24: 514 | AA24: 627 | AB24: 572 | AC24: 562 | AD24: 514 | AE24: 514 | AF24: 514 | AG24: 514 | AH24: 596 | AI24: 539 | AJ24: 619 | AK24: 596 | AL24: 635 | AM24: 676 | AN24: 641 | AO24: 661 | AP24: 676 | AQ24: 592 | AR24: 638 | AS24: 672 | AT24: 672 | AU24: 672 | AV24: 672 | AW24: 672 | AX24: 709 | AY24: 714 | AZ24: 661 | BA24: 722 | BB24: 722 | BC24: 713 | BD24: 713 | BE24: 713 | BF24: 713 | BG24: 713 | BH24: 742 | BI24: 742 | BJ24: 742 | BK24: 742 | BL24: 782
A26: Transittijden:
A28: Dag van lading is dag 0 | C28: Vertrek | G28: Transittijd in werkdagen | S28: Transittijd in werkdagen | AE28: Transittijd in werkdagen | AQ28: Transittijd in werkdagen | BC28: Transittijd in werkdagen
A29: Groupage 1-5 pallets | C29: di,vrij | E29: 3 | F29: 3 | G29: 3 | H29: 3 | I29: 3 | J29: 3 | K29: 3 | L29: 3 | M29: 3 | N29: 3 | O29: 3 | P29: 3 | Q29: 3 | R29: 3 | S29: 3 | T29: 3 | U29: 3 | V29: 3 | W29: 3 | X29: 3 | Y29: 3 | Z29: 3 | AA29: 3 | AB29: 3 | AC29: 3 | AD29: 3 | AE29: 3 | AF29: 3 | AG29: 3 | AH29: 3 | AI29: 3 | AJ29: 3 | AK29: 3 | AL29: 3 | AM29: 3 | AN29: 3 | AO29: 3 | AP29: 3 | AQ29: 3 | AR29: 3 | AS29: 3 | AT29: 3 | AU29: 3 | AV29: 3 | AW29: 3 | AX29: 3 | AY29: 3 | AZ29: 3 | BA29: 3 | BB29: 3 | BC29: 3 | BD29: 3 | BE29: 3 | BF29: 3 | BG29: 3 | BH29: 3 | BI29: 3 | BJ29: 3 | BK29: 3 | BL29: 3
A30: Deelpartijen > 5 pallets | C30: di,vrij | E30: 3 | F30: 3 | G30: 3 | H30: 3 | I30: 3 | J30: 3 | K30: 3 | L30: 3 | M30: 3 | N30: 3 | O30: 3 | P30: 3 | Q30: 3 | R30: 3 | S30: 3 | T30: 3 | U30: 3 | V30: 3 | W30: 3 | X30: 3 | Y30: 3 | Z30: 3 | AA30: 3 | AB30: 3 | AC30: 3 | AD30: 3 | AE30: 3 | AF30: 3 | AG30: 3 | AH30: 3 | AI30: 3 | AJ30: 3 | AK30: 3 | AL30: 3 | AM30: 3 | AN30: 3 | AO30: 3 | AP30: 3 | AQ30: 3 | AR30: 3 | AS30: 3 | AT30: 3 | AU30: 3 | AV30: 3 | AW30: 3 | AX30: 3 | AY30: 3 | AZ30: 3 | BA30: 3 | BB30: 3 | BC30: 3 | BD30: 3 | BE30: 3 | BF30: 3 | BG30: 3 | BH30: 3 | BI30: 3 | BJ30: 3 | BK30: 3 | BL30: 3
A31: Compleet ladingen | C31: di,wo,do,vrij | E31: 2 | F31: 2 | G31: 2 | H31: 2 | I31: 2 | J31: 2 | K31: 2 | L31: 2 | M31: 2 | N31: 2 | O31: 2 | P31: 2 | Q31: 2 | R31: 2 | S31: 2 | T31: 2 | U31: 2 | V31: 2 | W31: 2 | X31: 2 | Y31: 2 | Z31: 2 | AA31: 2 | AB31: 2 | AC31: 2 | AD31: 2 | AE31: 2 | AF31: 2 | AG31: 2 | AH31: 2 | AI31: 2 | AJ31: 2 | AK31: 2 | AL31: 2 | AM31: 2 | AN31: 2 | AO31: 2 | AP31: 2 | AQ31: 2 | AR31: 2 | AS31: 2 | AT31: 2 | AU31: 2 | AV31: 2 | AW31: 2 | AX31: 2 | AY31: 2 | AZ31: 2 | BA31: 2 | BB31: 2 | BC31: 2 | BD31: 2 | BE31: 2 | BF31: 2 | BG31: 2 | BH31: 2 | BI31: 2 | BJ31: 2 | BK31: 2 | BL31: 2

Sheet DE
A3: =Voorblad!A5 -> Team Freight Forwarding Logistics
A4: Export Duitsland
A6: kg | B6: ldm | C6: euplt | D6: blkplt | E6: 1 | F6: 2 | G6: 3 | H6: 4 | I6: 6 | J6: 7 | K6: 8 | L6: 9 | M6: 10 | N6: 12 | O6: 13 | P6: 14 | Q6: 15 | R6: 16 | S6: 17 | T6: 18 | U6: 19 | V6: 20 | W6: 21 | X6: 22 | Y6: 23 | Z6: 24 | AA6: 25 | AB6: 26 | AC6: 27 | AD6: 28 | AE6: 29 | AF6: 30 | AG6: 31 | AH6: 32 | AI6: 33 | AJ6: 34 | AK6: 35 | AL6: 36 | AM6: 37 | AN6: 38 | AO6: 39 | AP6: 40 | AQ6: 41 | AR6: 42 | AS6: 44 | AT6: 45 | AU6: 46 | AV6: 47 | AW6: 48 | AX6: 49 | AY6: 50 | AZ6: 51 | BA6: 52 | BB6: 53 | BC6: 54 | BD6: 55 | BE6: 56 | BF6: 57 | BG6: 58 | BH6: 59 | BI6: 60 | BJ6: 61 | BK6: 63 | BL6: 64 | BM6: 65 | BN6: 66 | BO6: 67 | BP6: 68 | BQ6: 69 | BR6: 70 | BS6: 71 | BT6: 72 | BU6: 73 | BV6: 74 | BW6: 75 | BX6: 76 | BY6: 77 | BZ6: 78 | CA6: 79 | CB6: 80 | CC6: 81 | CD6: 82 | CE6: 83 | CF6: 84 | CG6: 85 | CH6: 86 | CI6: 87 | CJ6: 88 | CK6: 89 | CL6: 90 | CM6: 91 | CN6: 92 | CO6: 93 | CP6: 94 | CQ6: 95 | CR6: 96 | CS6: 97 | CT6: 98 | CU6: 99
A7: 300 | B7: 0.2 | C7: 0.5 | E7: 163 | F7: 163 | G7: 163 | H7: 154 | I7: 154 | J7: 163 | K7: 163 | L7: 163 | M7: 163 | N7: 163 | O7: 163 | P7: 163 | Q7: 163 | R7: 163 | S7: 163 | T7: 163 | U7: 163 | V7: 149 | W7: 149 | X7: 149 | Y7: 154 | Z7: 154 | AA7: 154 | AB7: 140 | AC7: 140 | AD7: 146 | AE7: 146 | AF7: 146 | AG7: 146 | AH7: 125 | AI7: 125 | AJ7: 146 | AK7: 140 | AL7: 146 | AM7: 146 | AN7: 149 | AO7: 154 | AP7: 121 | AQ7: 121 | AR7: 121 | AS7: 121 | AT7: 121 | AU7: 121 | AV7: 121 | AW7: 121 | AX7: 125 | AY7: 121 | AZ7: 121 | BA7: 121 | BB7: 121 | BC7: 140 | BD7: 140 | BE7: 140 | BF7: 140 | BG7: 125 | BH7: 125 | BI7: 146 | BJ7: 146 | BK7: 146 | BL7: 146 | BM7: 146 | BN7: 149 | BO7: 149 | BP7: 149 | BQ7: 149 | BR7: 154 | BS7: 154 | BT7: 154 | BU7: 154 | BV7: 154 | BW7: 154 | BX7: 154 | BY7: 154 | BZ7: 163 | CA7: 163 | CB7: 163 | CC7: 163 | CD7: 163 | CE7: 163 | CF7: 163 | CG7: 163 | CH7: 163 | CI7: 163 | CJ7: 163 | CK7: 163 | CL7: 154 | CM7: 154 | CN7: 163 | CO7: 163 | CP7: 163 | CQ7: 163 | CR7: 163 | CS7: 149 | CT7: 149 | CU7: 149
A8: 700 | B8: 0.4 | C8: 1 | E8: 176 | F8: 176 | G8: 176 | H8: 167 | I8: 167 | J8: 173 | K8: 173 | L8: 173 | M8: 173 | N8: 173 | O8: 173 | P8: 173 | Q8: 173 | R8: 173 | S8: 176 | T8: 176 | U8: 173 | V8: 161 | W8: 161 | X8: 161 | Y8: 167 | Z8: 167 | AA8: 167 | AB8: 150 | AC8: 150 | AD8: 157 | AE8: 157 | AF8: 157 | AG8: 157 | AH8: 135 | AI8: 135 | AJ8: 157 | AK8: 150 | AL8: 157 | AM8: 157 | AN8: 161 | AO8: 167 | AP8: 130 | AQ8: 130 | AR8: 130 | AS8: 130 | AT8: 130 | AU8: 130 | AV8: 130 | AW8: 130 | AX8: 135 | AY8: 130 | AZ8: 130 | BA8: 130 | BB8: 130 | BC8: 150 | BD8: 150 | BE8: 150 | BF8: 150 | BG8: 135 | BH8: 135 | BI8: 157 | BJ8: 157 | BK8: 157 | BL8: 157 | BM8: 157 | BN8: 161 | BO8: 161 | BP8: 161 | BQ8: 161 | BR8: 167 | BS8: 167 | BT8: 167 | BU8: 167 | BV8: 167 | BW8: 167 | BX8: 167 | BY8: 167 | BZ8: 173 | CA8: 173 | CB8: 176 | CC8: 176 | CD8: 176 | CE8: 176 | CF8: 176 | CG8: 176 | CH8: 173 | CI8: 173 | CJ8: 173 | CK8: 173 | CL8: 167 | CM8: 167 | CN8: 173 | CO8: 173 | CP8: 176 | CQ8: 173 | CR8: 173 | CS8: 161 | CT8: 161 | CU8: 161
A9: 875 | B9: 0.5 | D9: 1 | E9: 213 | F9: 213 | G9: 213 | H9: 199 | I9: 199 | J9: 206 | K9: 206 | L9: 206 | M9: 206 | N9: 206 | O9: 206 | P9: 206 | Q9: 206 | R9: 206 | S9: 213 | T9: 213 | U9: 206 | V9: 193 | W9: 193 | X9: 193 | Y9: 199 | Z9: 199 | AA9: 199 | AB9: 172 | AC9: 172 | AD9: 181 | AE9: 181 | AF9: 181 | AG9: 181 | AH9: 162 | AI9: 162 | AJ9: 181 | AK9: 172 | AL9: 181 | AM9: 181 | AN9: 193 | AO9: 199 | AP9: 155 | AQ9: 155 | AR9: 155 | AS9: 155 | AT9: 155 | AU9: 155 | AV9: 155 | AW9: 155 | AX9: 162 | AY9: 155 | AZ9: 155 | BA9: 155 | BB9: 155 | BC9: 172 | BD9: 172 | BE9: 172 | BF9: 172 | BG9: 162 | BH9: 162 | BI9: 181 | BJ9: 181 | BK9: 181 | BL9: 181 | BM9: 181 | BN9: 193 | BO9: 193 | BP9: 193 | BQ9: 193 | BR9: 199 | BS9: 199 | BT9: 199 | BU9: 199 | BV9: 199 | BW9: 199 | BX9: 199 | BY9: 199 | BZ9: 206 | CA9: 206 | CB9: 213 | CC9: 213 | CD9: 213 | CE9: 213 | CF9: 213 | CG9: 213 | CH9: 206 | CI9: 206 | CJ9: 206 | CK9: 206 | CL9: 199 | CM9: 199 | CN9: 206 | CO9: 206 | CP9: 213 | CQ9: 206 | CR9: 206 | CS9: 193 | CT9: 193 | CU9: 193
A10: 1050 | B10: 0.6 | E10: 282 | F10: 282 | G10: 282 | H10: 257 | I10: 257 | J10: 266 | K10: 266 | L10: 266 | M10: 266 | N10: 266 | O10: 266 | P10: 266 | Q10: 266 | R10: 266 | S10: 282 | T10: 282 | U10: 266 | V10: 248 | W10: 248 | X10: 248 | Y10: 257 | Z10: 257 | AA10: 257 | AB10: 215 | AC10: 215 | AD10: 228 | AE10: 228 | AF10: 228 | AG10: 228 | AH10: 204 | AI10: 204 | AJ10: 228 | AK10: 215 | AL10: 228 | AM10: 228 | AN10: 248 | AO10: 257 | AP10: 193 | AQ10: 193 | AR10: 193 | AS10: 193 | AT10: 193 | AU10: 193 | AV10: 193 | AW10: 193 | AX10: 204 | AY10: 193 | AZ10: 193 | BA10: 193 | BB10: 193 | BC10: 215 | BD10: 215 | BE10: 215 | BF10: 215 | BG10: 204 | BH10: 204 | BI10: 228 | BJ10: 228 | BK10: 228 | BL10: 228 | BM10: 228 | BN10: 248 | BO10: 248 | BP10: 248 | BQ10: 248 | BR10: 257 | BS10: 257 | BT10: 257 | BU10: 257 | BV10: 257 | BW10: 257 | BX10: 257 | BY10: 257 | BZ10: 266 | CA10: 266 | CB10: 282 | CC10: 282 | CD10: 282 | CE10: 282 | CF10: 282 | CG10: 282 | CH10: 266 | CI10: 266 | CJ10: 266 | CK10: 266 | CL10: 257 | CM10: 257 | CN10: 266 | CO10: 266 | CP10: 282 | CQ10: 266 | CR10: 266 | CS10: 248 | CT10: 248 | CU10: 248
A11: 1400 | B11: 0.8 | C11: 2 | E11: 317 | F11: 317 | G11: 317 | H11: 287 | I11: 287 | J11: 295 | K11: 295 | L11: 295 | M11: 295 | N11: 295 | O11: 295 | P11: 295 | Q11: 295 | R11: 295 | S11: 317 | T11: 317 | U11: 295 | V11: 276 | W11: 276 | X11: 276 | Y11: 287 | Z11: 287 | AA11: 287 | AB11: 235 | AC11: 235 | AD11: 250 | AE11: 250 | AF11: 250 | AG11: 250 | AH11: 224 | AI11: 224 | AJ11: 250 | AK11: 235 | AL11: 250 | AM11: 250 | AN11: 276 | AO11: 287 | AP11: 213 | AQ11: 213 | AR11: 213 | AS11: 213 | AT11: 213 | AU11: 213 | AV11: 213 | AW11: 213 | AX11: 224 | AY11: 213 | AZ11: 213 | BA11: 213 | BB11: 213 | BC11: 235 | BD11: 235 | BE11: 235 | BF11: 235 | BG11: 224 | BH11: 224 | BI11: 250 | BJ11: 250 | BK11: 250 | BL11: 250 | BM11: 250 | BN11: 276 | BO11: 276 | BP11: 276 | BQ11: 276 | BR11: 287 | BS11: 287 | BT11: 287 | BU11: 287 | BV11: 287 | BW11: 287 | BX11: 287 | BY11: 287 | BZ11: 295 | CA11: 295 | CB11: 317 | CC11: 317 | CD11: 317 | CE11: 317 | CF11: 317 | CG11: 317 | CH11: 295 | CI11: 295 | CJ11: 295 | CK11: 295 | CL11: 287 | CM11: 287 | CN11: 295 | CO11: 295 | CP11: 317 | CQ11: 295 | CR11: 295 | CS11: 276 | CT11: 276 | CU11: 276
A12: 1750 | B12: 1 | D12: 2 | E12: 341 | F12: 356 | G12: 356 | H12: 326 | I12: 311 | J12: 315 | K12: 315 | L12: 330 | M12: 330 | N12: 330 | O12: 330 | P12: 330 | Q12: 345 | R12: 330 | S12: 356 | T12: 341 | U12: 315 | V12: 306 | W12: 293 | X12: 306 | Y12: 296 | Z12: 311 | AA12: 311 | AB12: 262 | AC12: 262 | AD12: 272 | AE12: 276 | AF12: 276 | AG12: 262 | AH12: 244 | AI12: 244 | AJ12: 276 | AK12: 266 | AL12: 276 | AM12: 276 | AN12: 293 | AO12: 311 | AP12: 223 | AQ12: 220 | AR12: 223 | AS12: 223 | AT12: 220 | AU12: 220 | AV12: 220 | AW12: 222 | AX12: 233 | AY12: 223 | AZ12: 223 | BA12: 223 | BB12: 237 | BC12: 252 | BD12: 266 | BE12: 252 | BF12: 252 | BG12: 230 | BH12: 230 | BI12: 276 | BJ12: 276 | BK12: 276 | BL12: 276 | BM12: 276 | BN12: 294 | BO12: 294 | BP12: 294 | BQ12: 294 | BR12: 311 | BS12: 311 | BT12: 311 | BU12: 311 | BV12: 308 | BW12: 308 | BX12: 308 | BY12: 311 | BZ12: 330 | CA12: 330 | CB12: 341 | CC12: 341 | CD12: 356 | CE12: 356 | CF12: 356 | CG12: 341 | CH12: 330 | CI12: 345 | CJ12: 330 | CK12: 330 | CL12: 311 | CM12: 311 | CN12: 330 | CO12: 330 | CP12: 356 | CQ12: 315 | CR12: 315 | CS12: 291 | CT12: 291 | CU12: 291
A13: 2100 | B13: 1.2 | C13: 3 | E13: 364 | F13: 394 | G13: 394 | H13: 364 | I13: 335 | J13: 335 | K13: 335 | L13: 364 | M13: 364 | N13: 364 | O13: 364 | P13: 364 | Q13: 394 | R13: 364 | S13: 394 | T13: 364 | U13: 335 | V13: =ROUNDUP(V12+(V$14-V$11)/3,0) -> 336 | W13: =ROUNDUP(W12+(W$14-W$11)/3,0) -> 310 | X13: =ROUNDUP(X12+(X$14-X$11)/3,0) -> 336 | Y13: 305 | Z13: 335 | AA13: 335 | AB13: =ROUNDUP(AB12+(AB$14-AB$11)/3,0) -> 289 | AC13: =ROUNDUP(AC12+(AC$14-AC$11)/3,0) -> 289 | AD13: =ROUNDUP(AD12+(AD$14-AD$11)/3,0) -> 294 | AE13: =ROUNDUP(AE12+(AE$14-AE$11)/3,0) -> 302 | AF13: =ROUNDUP(AF12+(AF$14-AF$11)/3,0) -> 302 | AG13: =ROUNDUP(AG12+(AG$14-AG$11)/3,0) -> 274 | AH13: =ROUNDUP(AH12+(AH$14-AH$11)/3,0) -> 264 | AI13: =ROUNDUP(AI12+(AI$14-AI$11)/3,0) -> 264 | ... AN13: =ROUNDUP(AN12+(AN$14-AN$11)/3,0) -> 310 | AO13: 335 | AP13: =ROUNDUP(AP12+(AP$14-AP$11)/3,0) -> 233 | AQ13: =ROUNDUP(AQ12+(AQ$14-AQ$11)/3,0) -> 227 | AR13: =ROUNDUP(AR12+(AR$14-AR$11)/3,0) -> 233 | AS13: =ROUNDUP(AS12+(AS$14-AS$11)/3,0) -> 233 | AT13: =ROUNDUP(AT12+(AT$14-AT$11)/3,0) -> 227 | AU13: =ROUNDUP(AU12+(AU$14-AU$11)/3,0) -> 227 | AV13: =ROUNDUP(AV12+(AV$14-AV$11)/3,0) -> 227 | AW13: =ROUNDUP(AW12+(AW$14-AW$11)/3,0) -> 231 | AX13: 241 | AY13: =ROUNDUP(AY12+(AY$14-AY$11)/3,0) -> 233 | AZ13: =ROUNDUP(AZ12+(AZ$14-AZ$11)/3,0) -> 233 | BA13: =ROUNDUP(BA12+(BA$14-BA$11)/3,0) -> 233 | BB13: =ROUNDUP(BB12+(BB$14-BB$11)/3,0) -> 261 | BC13: =ROUNDUP(BC12+(BC$14-BC$11)/3,0) -> 269 | BD13: =ROUNDUP(BD12+(BD$14-BD$11)/3,0) -> 297 | BE13: =ROUNDUP(BE12+(BE$14-BE$11)/3,0) -> 269 | BF13: =ROUNDUP(BF12+(BF$14-BF$11)/3,0) -> 269 | ... BQ13: =ROUNDUP(BQ12+(BQ$14-BQ$11)/3,0) -> 312 | BR13: 335 | BS13: 335 | BT13: 335 | BU13: 335 | BV13: =ROUNDUP(BV12+(BV$14-BV$11)/3,0) -> 329 | BW13: =ROUNDUP(BW12+(BW$14-BW$11)/3,0) -> 329 | BX13: =ROUNDUP(BX12+(BX$14-BX$11)/3,0) -> 329 | BY13: 335 | BZ13: 364 | CA13: 364 | CB13: 364 | CC13: 364 | CD13: 394 | CE13: 394 | CF13: 394 | CG13: 364 | CH13: 364 | CI13: 394 | CJ13: 364 | CK13: 364 | CL13: 335 | CM13: 335 | CN13: 364 | CO13: 364 | CP13: 394 | CQ13: 335 | CR13: 335 | CS13: 305 | CT13: 305 | CU13: 305
A14: 2625 | B14: 1.5 | D14: 3 | E14: 409 | F14: 409 | G14: 409 | H14: 387 | I14: 378 | J14: 387 | K14: 390 | L14: 390 | M14: 389 | N14: 389 | O14: 389 | P14: 387 | Q14: 409 | R14: 389 | S14: 399 | T14: 399 | U14: 378 | V14: 364 | W14: 326 | X14: 364 | Y14: 378 | Z14: 378 | AA14: 378 | AB14: 316 | AC14: 316 | AD14: 316 | AE14: 326 | AF14: 326 | AG14: 284 | AH14: 284 | AI14: 284 | AJ14: 326 | AK14: 326 | AL14: 326 | AM14: 326 | AN14: 326 | AO14: 349 | AP14: 242 | AQ14: 232 | AR14: 242 | AS14: 242 | AT14: 232 | AU14: 232 | AV14: 232 | AW14: 238 | AX14: 242 | AY14: 242 | AZ14: 242 | BA14: 242 | BB14: 284 | BC14: 286 | BD14: 326 | BE14: 284 | BF14: 284 | BG14: 242 | BH14: 242 | BI14: 326 | BJ14: 326 | BK14: 326 | BL14: 326 | BM14: 326 | BN14: 330 | BO14: 330 | BP14: 330 | BQ14: 330 | BR14: 349 | BS14: 349 | BT14: 378 | BU14: 378 | BV14: 349 | BW14: 349 | BX14: 349 | BY14: 358 | BZ14: 390 | CA14: 390 | CB14: 412 | CC14: 412 | CD14: 412 | CE14: 412 | CF14: 412 | CG14: 409 | CH14: 409 | CI14: 409 | CJ14: 402 | CK14: 387 | CL14: 387 | CM14: 387 | CN14: 399 | CO14: 399 | CP14: 412 | CQ14: 390 | CR14: 387 | CS14: 356 | CT14: 356 | CU14: 356
A15: 2800 | B15: 1.6 | C15: 4 | E15: 428 | F15: 428 | G15: 428 | H15: 405 | I15: 402 | J15: 405 | K15: 413 | L15: 413 | M15: 406 | N15: 406 | O15: 406 | P15: 405 | Q15: 428 | R15: 406 | S15: 417 | T15: 417 | U15: 402 | V15: 395 | W15: 338 | X15: 395 | Y15: 402 | Z15: 402 | AA15: 402 | AB15: 333 | AC15: 333 | AD15: 333 | AE15: 338 | AF15: 338 | AG15: 286 | AH15: 286 | AI15: 286 | AJ15: 338 | AK15: 338 | AL15: 338 | AM15: 338 | AN15: 338 | AO15: 367 | AP15: 249 | AQ15: 241 | AR15: 249 | AS15: 249 | AT15: 241 | AU15: 241 | AV15: 241 | AW15: 246 | AX15: 249 | AY15: 249 | AZ15: 249 | BA15: 249 | BB15: 286 | BC15: 288 | BD15: 338 | BE15: 286 | BF15: 286 | BG15: 249 | BH15: 249 | BI15: 338 | BJ15: 338 | BK15: 338 | BL15: 338 | BM15: 338 | BN15: 340 | BO15: 340 | BP15: 340 | BQ15: 340 | BR15: 367 | BS15: 367 | BT15: 402 | BU15: 402 | BV15: 367 | BW15: 367 | BX15: 367 | BY15: 369 | BZ15: 413 | CA15: 413 | CB15: 429 | CC15: 429 | CD15: 429 | CE15: 429 | CF15: 429 | CG15: 428 | CH15: 428 | CI15: 428 | CJ15: 425 | CK15: 405 | CL15: 405 | CM15: 405 | CN15: 417 | CO15: 417 | CP15: 429 | CQ15: 413 | CR15: 405 | CS15: 368 | CT15: 368 | CU15: 368
A16: 3500 | B16: 2 | C16: 5 | D16: 4 | E16: 444 | F16: 444 | G16: 444 | H16: 420 | I16: 420 | J16: 420 | K16: 429 | L16: 429 | M16: 420 | N16: 420 | O16: 420 | P16: 420 | Q16: 444 | R16: 420 | S16: 429 | T16: 429 | U16: 420 | V16: 420 | W16: 346 | X16: 420 | Y16: 420 | Z16: 420 | AA16: 420 | AB16: 346 | AC16: 346 | AD16: 346 | AE16: 346 | AF16: 346 | AG16: 286 | AH16: 286 | AI16: 286 | AJ16: 346 | AK16: 346 | AL16: 346 | AM16: 346 | AN16: 346 | AO16: 378 | AP16: 254 | AQ16: 246 | AR16: 254 | AS16: 254 | AT16: 246 | AU16: 246 | AV16: 246 | AW16: 251 | AX16: 254 | AY16: 254 | AZ16: 254 | BA16: 254 | BB16: 287 | BC16: 288 | BD16: 346 | BE16: 287 | BF16: 287 | BG16: 254 | BH16: 254 | BI16: 346 | BJ16: 346 | BK16: 346 | BL16: 346 | BM16: 346 | BN16: 346 | BO16: 346 | BP16: 346 | BQ16: 346 | BR16: 378 | BS16: 378 | BT16: 420 | BU16: 420 | BV16: 378 | BW16: 378 | BX16: 378 | BY16: 378 | BZ16: 429 | CA16: 429 | CB16: 444 | CC16: 444 | CD16: 444 | CE16: 444 | CF16: 444 | CG16: 444 | CH16: 444 | CI16: 444 | CJ16: 444 | CK16: 420 | CL16: 420 | CM16: 420 | CN16: 429 | CO16: 429 | CP16: 444 | CQ16: 429 | CR16: 420 | CS16: 378 | CT16: 378 | CU16: 378
A17: 4200 | B17: 2.4 | C17: 6 | E17: 448 | F17: 448 | G17: 448 | H17: 433 | I17: 433 | J17: 433 | K17: 442 | L17: 442 | M17: 433 | N17: 433 | O17: 433 | P17: 433 | Q17: 448 | R17: 433 | S17: 442 | T17: 442 | U17: 433 | V17: 433 | W17: 365 | X17: 433 | Y17: 433 | Z17: 433 | AA17: 433 | AB17: 365 | AC17: 365 | AD17: 365 | AE17: 365 | AF17: 365 | AG17: 288 | AH17: 288 | AI17: 288 | AJ17: 365 | AK17: 365 | AL17: 365 | AM17: 365 | AN17: 365 | AO17: 386 | AP17: 264 | AQ17: 253 | AR17: 264 | AS17: 264 | AT17: 253 | AU17: 253 | AV17: 253 | AW17: 262 | AX17: 264 | AY17: 264 | AZ17: 264 | BA17: 264 | BB17: 290 | BC17: 291 | BD17: 365 | BE17: 290 | BF17: 290 | BG17: 264 | BH17: 264 | BI17: 365 | BJ17: 365 | BK17: 365 | BL17: 365 | BM17: 365 | BN17: 365 | BO17: 365 | BP17: 365 | BQ17: 365 | BR17: 386 | BS17: 386 | BT17: 433 | BU17: 433 | BV17: 386 | BW17: 386 | BX17: 386 | BY17: 386 | BZ17: 442 | CA17: 442 | CB17: 448 | CC17: 448 | CD17: 448 | CE17: 448 | CF17: 448 | CG17: 448 | CH17: 448 | CI17: 448 | CJ17: 448 | CK17: 433 | CL17: 433 | CM17: 433 | CN17: 442 | CO17: 442 | CP17: 448 | CQ17: 442 | CR17: 433 | CS17: 386 | CT17: 386 | CU17: 386
A18: 4375 | B18: 2.5 | D18: 5 | E18: 499 | F18: 499 | G18: 499 | H18: 437 | I18: 437 | J18: 437 | K18: 464 | L18: 464 | M18: 437 | N18: 437 | O18: 437 | P18: 437 | Q18: 499 | R18: 437 | S18: 464 | T18: 464 | U18: 437 | V18: 437 | W18: 368 | X18: 437 | Y18: 437 | Z18: 437 | AA18: 437 | AB18: 368 | AC18: 368 | AD18: 368 | AE18: 368 | AF18: 368 | AG18: 291 | AH18: 291 | AI18: 291 | AJ18: 368 | AK18: 368 | AL18: 368 | AM18: 368 | AN18: 368 | AO18: 390 | AP18: 266 | AQ18: 258 | AR18: 266 | AS18: 266 | AT18: 258 | AU18: 258 | AV18: 258 | AW18: 266 | AX18: 266 | AY18: 266 | AZ18: 266 | BA18: 266 | BB18: 291 | BC18: 291 | BD18: 368 | BE18: 291 | BF18: 291 | BG18: 266 | BH18: 266 | BI18: 368 | BJ18: 368 | BK18: 368 | BL18: 368 | BM18: 368 | BN18: 368 | BO18: 368 | BP18: 368 | BQ18: 368 | BR18: 390 | BS18: 390 | BT18: 437 | BU18: 437 | BV18: 390 | BW18: 390 | BX18: 390 | BY18: 390 | BZ18: 464 | CA18: 464 | CB18: 499 | CC18: 499 | CD18: 499 | CE18: 499 | CF18: 499 | CG18: 499 | CH18: 499 | CI18: 499 | CJ18: 499 | CK18: 437 | CL18: 437 | CM18: 437 | CN18: 464 | CO18: 464 | CP18: 499 | CQ18: 464 | CR18: 437 | CS18: 390 | CT18: 390 | CU18: 390
A19: 4900 | B19: 2.8 | C19: 7 | E19: 550 | F19: 550 | G19: 550 | H19: 446 | I19: 446 | J19: 446 | K19: 497 | L19: 497 | M19: 446 | N19: 446 | O19: 446 | P19: 446 | Q19: 550 | R19: 446 | S19: 497 | T19: 497 | U19: 446 | V19: 446 | W19: 376 | X19: 446 | Y19: 446 | Z19: 446 | AA19: 446 | AB19: 376 | AC19: 376 | AD19: 376 | AE19: 376 | AF19: 376 | AG19: 296 | AH19: 296 | AI19: 296 | AJ19: 376 | AK19: 376 | AL19: 376 | AM19: 376 | AN19: 376 | AO19: 400 | AP19: 285 | AQ19: 272 | AR19: 285 | AS19: 285 | AT19: 272 | AU19: 272 | AV19: 272 | AW19: 285 | AX19: 285 | AY19: 285 | AZ19: 285 | BA19: 285 | BB19: 296 | BC19: 296 | BD19: 376 | BE19: 296 | BF19: 296 | BG19: 285 | BH19: 285 | BI19: 376 | BJ19: 376 | BK19: 376 | BL19: 376 | BM19: 376 | BN19: 376 | BO19: 376 | BP19: 376 | BQ19: 376 | BR19: 400 | BS19: 400 | BT19: 446 | BU19: 446 | BV19: 400 | BW19: 400 | BX19: 400 | BY19: 400 | BZ19: 497 | CA19: 497 | CB19: 550 | CC19: 550 | CD19: 550 | CE19: 550 | CF19: 550 | CG19: 550 | CH19: 550 | CI19: 550 | CJ19: 550 | CK19: 446 | CL19: 446 | CM19: 446 | CN19: 497 | CO19: 497 | CP19: 550 | CQ19: 497 | CR19: 446 | CS19: 400 | CT19: 400 | CU19: 400
A20: 5250 | B20: 3 | D20: 6 | E20: 615 | F20: 615 | G20: 615 | H20: 494 | I20: 494 | J20: 494 | K20: 549 | L20: 549 | M20: 494 | N20: 494 | O20: 494 | P20: 494 | Q20: 615 | R20: 494 | S20: 549 | T20: 549 | U20: 494 | V20: 494 | W20: 382 | X20: 494 | Y20: 494 | Z20: 494 | AA20: 494 | AB20: 382 | AC20: 382 | AD20: 382 | AE20: 382 | AF20: 382 | AG20: 303 | AH20: 303 | AI20: 303 | AJ20: 382 | AK20: 382 | AL20: 382 | AM20: 382 | AN20: 382 | AO20: 427 | AP20: 291 | AQ20: 274 | AR20: 291 | AS20: 291 | AT20: 274 | AU20: 274 | AV20: 274 | AW20: 291 | AX20: 291 | AY20: 291 | AZ20: 291 | BA20: 291 | BB20: 303 | BC20: 303 | BD20: 382 | BE20: 303 | BF20: 303 | BG20: 291 | BH20: 291 | BI20: 382 | BJ20: 382 | BK20: 382 | BL20: 382 | BM20: 382 | BN20: 382 | BO20: 382 | BP20: 382 | BQ20: 382 | BR20: 427 | BS20: 427 | BT20: 494 | BU20: 494 | BV20: 427 | BW20: 427 | BX20: 427 | BY20: 427 | BZ20: 549 | CA20: 549 | CB20: 615 | CC20: 615 | CD20: 615 | CE20: 615 | CF20: 615 | CG20: 615 | CH20: 615 | CI20: 615 | CJ20: 615 | CK20: 494 | CL20: 494 | CM20: 494 | CN20: 549 | CO20: 549 | CP20: 615 | CQ20: 549 | CR20: 494 | CS20: 427 | CT20: 427 | CU20: 427
A21: 5600 | B21: 3.2 | C21: 8 | E21: 676 | F21: 676 | G21: 676 | H21: 542 | I21: 542 | J21: 542 | K21: 605 | L21: 605 | M21: 542 | N21: 542 | O21: 542 | P21: 542 | Q21: 676 | R21: 542 | S21: 605 | T21: 605 | U21: 542 | V21: 542 | W21: 392 | X21: 542 | Y21: 542 | Z21: 542 | AA21: 542 | AB21: 392 | AC21: 392 | AD21: 392 | AE21: 392 | AF21: 392 | AG21: 309 | AH21: 309 | AI21: 309 | AJ21: 392 | AK21: 392 | AL21: 392 | AM21: 392 | AN21: 392 | AO21: 460 | AP21: 298 | AQ21: 280 | AR21: 298 | AS21: 298 | AT21: 280 | AU21: 280 | AV21: 280 | AW21: 298 | AX21: 298 | AY21: 298 | AZ21: 298 | BA21: 298 | BB21: 309 | BC21: 309 | BD21: 392 | BE21: 309 | BF21: 309 | BG21: 298 | BH21: 298 | BI21: 392 | BJ21: 392 | BK21: 392 | BL21: 392 | BM21: 392 | BN21: 392 | BO21: 392 | BP21: 392 | BQ21: 392 | BR21: 460 | BS21: 460 | BT21: 542 | BU21: 542 | BV21: 460 | BW21: 460 | BX21: 460 | BY21: 460 | BZ21: 605 | CA21: 605 | CB21: 676 | CC21: 676 | CD21: 676 | CE21: 676 | CF21: 676 | CG21: 676 | CH21: 676 | CI21: 676 | CJ21: 676 | CK21: 542 | CL21: 542 | CM21: 542 | CN21: 605 | CO21: 605 | CP21: 676 | CQ21: 605 | CR21: 542 | CS21: 460 | CT21: 460 | CU21: 460
A22: 6125 | B22: 3.5 | D22: 7 | E22: 735 | F22: 735 | G22: 735 | H22: 589 | I22: 589 | J22: 589 | K22: 662 | L22: 662 | M22: 589 | N22: 589 | O22: 589 | P22: 589 | Q22: 735 | R22: 589 | S22: 662 | T22: 662 | U22: 589 | V22: 589 | W22: 402 | X22: 589 | Y22: 589 | Z22: 589 | AA22: 589 | AB22: 402 | AC22: 402 | AD22: 402 | AE22: 402 | AF22: 402 | AG22: 317 | AH22: 317 | AI22: 317 | AJ22: 402 | AK22: 402 | AL22: 402 | AM22: 402 | AN22: 402 | AO22: 506 | AP22: 311 | AQ22: 299 | AR22: 311 | AS22: 311 | AT22: 299 | AU22: 299 | AV22: 299 | AW22: 311 | AX22: 311 | AY22: 311 | AZ22: 311 | BA22: 311 | BB22: 317 | BC22: 317 | BD22: 402 | BE22: 317 | BF22: 317 | BG22: 311 | BH22: 311 | BI22: 402 | BJ22: 402 | BK22: 402 | BL22: 402 | BM22: 402 | BN22: 402 | BO22: 402 | BP22: 402 | BQ22: 402 | BR22: 506 | BS22: 506 | BT22: 589 | BU22: 589 | BV22: 506 | BW22: 506 | BX22: 506 | BY22: 506 | BZ22: 662 | CA22: 662 | CB22: 735 | CC22: 735 | CD22: 735 | CE22: 735 | CF22: 735 | CG22: 735 | CH22: 735 | CI22: 735 | CJ22: 735 | CK22: 589 | CL22: 589 | CM22: 589 | CN22: 662 | CO22: 662 | CP22: 735 | CQ22: 662 | CR22: 589 | CS22: 506 | CT22: 506 | CU22: 506
A23: 6300 | B23: 3.6 | C23: 9 | E23: 749 | F23: 749 | G23: 749 | H23: 599 | I23: 599 | J23: 599 | K23: 673 | L23: 673 | M23: 599 | N23: 599 | O23: 599 | P23: 599 | Q23: 749 | R23: 599 | S23: 673 | T23: 673 | U23: 599 | V23: 599 | W23: 414 | X23: 599 | Y23: 599 | Z23: 599 | AA23: 599 | AB23: 414 | AC23: 414 | AD23: 414 | AE23: 414 | AF23: 414 | AG23: 327 | AH23: 327 | AI23: 327 | AJ23: 414 | AK23: 414 | AL23: 414 | AM23: 414 | AN23: 414 | AO23: 514 | AP23: 322 | AQ23: 308 | AR23: 322 | AS23: 322 | AT23: 308 | AU23: 308 | AV23: 308 | AW23: 322 | AX23: 322 | AY23: 322 | AZ23: 322 | BA23: 322 | BB23: 327 | BC23: 327 | BD23: 414 | BE23: 327 | BF23: 327 | BG23: 322 | BH23: 322 | BI23: 414 | BJ23: 414 | BK23: 414 | BL23: 414 | BM23: 414 | BN23: 414 | BO23: 414 | BP23: 414 | BQ23: 414 | BR23: 514 | BS23: 514 | BT23: 599 | BU23: 599 | BV23: 514 | BW23: 514 | BX23: 514 | BY23: 514 | BZ23: 673 | CA23: 673 | CB23: 749 | CC23: 749 | CD23: 749 | CE23: 749 | CF23: 749 | CG23: 749 | CH23: 749 | CI23: 749 | CJ23: 749 | CK23: 599 | CL23: 599 | CM23: 599 | CN23: 673 | CO23: 673 | CP23: 749 | CQ23: 673 | CR23: 599 | CS23: 514 | CT23: 514 | CU23: 514
A24: 7000 | B24: 4 | C24: 10 | D24: 8 | E24: 825 | F24: 825 | G24: 825 | H24: 660 | I24: 660 | J24: 660 | K24: 739 | L24: 739 | M24: 660 | N24: 660 | O24: 660 | P24: 660 | Q24: 825 | R24: 660 | S24: 739 | T24: 739 | U24: 660 | V24: 660 | W24: 453 | X24: 660 | Y24: 660 | Z24: 660 | AA24: 660 | AB24: 453 | AC24: 453 | AD24: 453 | AE24: 453 | AF24: 453 | AG24: 360 | AH24: 360 | AI24: 360 | AJ24: 453 | AK24: 453 | AL24: 453 | AM24: 453 | AN24: 453 | AO24: 564 | AP24: 337 | AQ24: 319 | AR24: 337 | AS24: 337 | AT24: 319 | AU24: 319 | AV24: 319 | AW24: 337 | AX24: 337 | AY24: 337 | AZ24: 337 | BA24: 337 | BB24: 360 | BC24: 360 | BD24: 453 | BE24: 360 | BF24: 360 | BG24: 337 | BH24: 337 | BI24: 453 | BJ24: 453 | BK24: 453 | BL24: 453 | BM24: 453 | BN24: 453 | BO24: 453 | BP24: 453 | BQ24: 453 | BR24: 564 | BS24: 564 | BT24: 660 | BU24: 660 | BV24: 564 | BW24: 564 | BX24: 564 | BY24: 564 | BZ24: 739 | CA24: 739 | CB24: 825 | CC24: 825 | CD24: 825 | CE24: 825 | CF24: 825 | CG24: 825 | CH24: 825 | CI24: 825 | CJ24: 825 | CK24: 660 | CL24: 660 | CM24: 660 | CN24: 739 | CO24: 739 | CP24: 825 | CQ24: 739 | CR24: 660 | CS24: 564 | CT24: 564 | CU24: 564
A26: Transittijden:
A28: Dag van lading is dag 0 | C28: Vertrek | G28: Transittijd in werkdagen | S28: Transittijd in werkdagen | AF28: Transittijd in werkdagen | AS28: Transittijd in werkdagen | BE28: Transittijd in werkdagen | BF28: Transittijd in werkdagen | BS28: Transittijd in werkdagen | CF28: Transittijd in werkdagen
A29: Groupage 1-5 pallets | C29: ma,di,wo,do,vrij | E29: 2/3 | F29: 2/3 | G29: 2/3 | H29: 2/3 | I29: 2/3 | J29: 2/3 | K29: 2/3 | L29: 2/3 | M29: 2/3 | N29: 2/3 | O29: 2/3 | P29: 2/3 | Q29: 2/3 | R29: 2/3 | S29: 2/3 | T29: 2/3 | U29: 2/3 | V29: 2/3 | W29: 2/3 | X29: 2/3 | Y29: 2/3 | Z29: 2/3 | AA29: 2/3 | AB29: 2/3 | AC29: 2/3 | AD29: 2/3 | AE29: 2/3 | AF29: 2/3 | AG29: 2/3 | AH29: 2/3 | AI29: 2/3 | AJ29: 2/3 | AK29: 2/3 | AL29: 2/3 | AM29: 2/3 | AN29: 2/3 | AO29: 2/3 | AP29: 2/3 | AQ29: 2/3 | AR29: 2/3 | AS29: 2/3 | AT29: 2/3 | AU29: 2/3 | AV29: 2/3 | AW29: 2/3 | AX29: 2/3 | AY29: 2/3 | AZ29: 2/3 | BA29: 2/3 | BB29: 2/3 | BC29: 2/3 | BD29: 2/3 | BE29: 2/3 | BF29: 2/3 | BG29: 2/3 | BH29: 2/3 | BI29: 2/3 | BJ29: 2/3 | BK29: 2/3 | BL29: 2/3 | BM29: 2/3 | BN29: 2/3 | BO29: 2/3 | BP29: 2/3 | BQ29: 2/3 | BR29: 2/3 | BS29: 2/3 | BT29: 2/3 | BU29: 2/3 | BV29: 2/3 | BW29: 2/3 | BX29: 2/3 | BY29: 2/3 | BZ29: 2/3 | CA29: 2/3 | CB29: 2/3 | CC29: 2/3 | CD29: 2/3 | CE29: 2/3 | CF29: 2/3 | CG29: 2/3 | CH29: 2/3 | CI29: 2/3 | CJ29: 2/3 | CK29: 2/3 | CL29: 2/3 | CM29: 2/3 | CN29: 2/3 | CO29: 2/3 | CP29: 2/3 | CQ29: 2/3 | CR29: 2/3 | CS29: 2/3 | CT29: 2/3 | CU29: 2/3
A30: Deelpartijen > 5 pallets | C30: ma,di,wo,do,vrij | E30: 1/2 | F30: 1/2 | G30: 1/2 | H30: 1/2 | I30: 1/2 | J30: 1/2 | K30: 1/2 | L30: 1/2 | M30: 1/2 | N30: 1/2 | O30: 1/2 | P30: 1/2 | Q30: 1/2 | R30: 1/2 | S30: 1/2 | T30: 1/2 | U30: 1/2 | V30: 1/2 | W30: 1/2 | X30: 1/2 | Y30: 1/2 | Z30: 1/2 | AA30: 1/2 | AB30: 1/2 | AC30: 1/2 | AD30: 1/2 | AE30: 1/2 | AF30: 1/2 | AG30: 1/2 | AH30: 1/2 | AI30: 1/2 | AJ30: 1/2 | AK30: 1/2 | AL30: 1/2 | AM30: 1/2 | AN30: 1/2 | AO30: 1/2 | AP30: 1/2 | AQ30: 1/2 | AR30: 1/2 | AS30: 1/2 | AT30: 1/2 | AU30: 1/2 | AV30: 1/2 | AW30: 1/2 | AX30: 1/2 | AY30: 1/2 | AZ30: 1/2 | BA30: 1/2 | BB30: 1/2 | BC30: 1/2 | BD30: 1/2 | BE30: 1/2 | BF30: 1/2 | BG30: 1/2 | BH30: 1/2 | BI30: 1/2 | BJ30: 1/2 | BK30: 1/2 | BL30: 1/2 | BM30: 1/2 | BN30: 1/2 | BO30: 1/2 | BP30: 1/2 | BQ30: 1/2 | BR30: 1/2 | BS30: 1/2 | BT30: 1/2 | BU30: 1/2 | BV30: 1/2 | BW30: 1/2 | BX30: 1/2 | BY30: 1/2 | BZ30: 1/2 | CA30: 1/2 | CB30: 1/2 | CC30: 1/2 | CD30: 1/2 | CE30: 1/2 | CF30: 1/2 | CG30: 1/2 | CH30: 1/2 | CI30: 1/2 | CJ30: 1/2 | CK30: 1/2 | CL30: 1/2 | CM30: 1/2 | CN30: 1/2 | CO30: 1/2 | CP30: 1/2 | CQ30: 1/2 | CR30: 1/2 | CS30: 1/2 | CT30: 1/2 | CU30: 1/2
A31: Compleet ladingen | C31: ma,di,wo,do,vrij | E31: 1 | F31: 1 | G31: 1 | H31: 1 | I31: 1 | J31: 1 | K31: 1 | L31: 1 | M31: 1 | N31: 1 | O31: 1 | P31: 1 | Q31: 1 | R31: 1 | S31: 1 | T31: 1 | U31: 1 | V31: 1 | W31: 1 | X31: 1 | Y31: 1 | Z31: 1 | AA31: 1 | AB31: 1 | AC31: 1 | AD31: 1 | AE31: 1 | AF31: 1 | AG31: 1 | AH31: 1 | AI31: 1 | AJ31: 1 | AK31: 1 | AL31: 1 | AM31: 1 | AN31: 1 | AO31: 1 | AP31: 1 | AQ31: 1 | AR31: 1 | AS31: 1 | AT31: 1 | AU31: 1 | AV31: 1 | AW31: 1 | AX31: 1 | AY31: 1 | AZ31: 1 | BA31: 1 | BB31: 1 | BC31: 1 | BD31: 1 | BE31: 1 | BF31: 1 | BG31: 1 | BH31: 1 | BI31: 1 | BJ31: 1 | BK31: 1 | BL31: 1 | BM31: 1 | BN31: 1 | BO31: 1 | BP31: 1 | BQ31: 1 | BR31: 1 | BS31: 1 | BT31: 1 | BU31: 1 | BV31: 1 | BW31: 1 | BX31: 1 | BY31: 1 | BZ31: 1 | CA31: 1 | CB31: 1 | CC31: 1 | CD31: 1 | CE31: 1 | CF31: 1 | CG31: 1 | CH31: 1 | CI31: 1 | CJ31: 1 | CK31: 1 | CL31: 1 | CM31: 1 | CN31: 1 | CO31: 1 | CP31: 1 | CQ31: 1 | CR31: 1 | CS31: 1 | CT31: 1 | CU31: 1
A33: Condities:
A34: * Kleplevering t/m 3 pallets inclusief. Vanaf 4 pallets € 75,- per zending

Sheet DK
A3: =Voorblad!A5 -> Team Freight Forwarding Logistics
A4: Export Denemarken
A6: kg | B6: ldm | C6: euplt | D6: blkplt | E6: 10 | F6: 11 | G6: 12 | H6: 13 | I6: 14 | J6: 15 | K6: 16 | L6: 17 | M6: 18 | N6: 19 | O6: 20 | P6: 21 | Q6: 22 | R6: 23 | S6: 24 | T6: 25 | U6: 26 | V6: 27 | W6: 28 | X6: 29 | Y6: 30 | Z6: 31 | AA6: 32 | AB6: 33 | AC6: 34 | AD6: 35 | AE6: 36 | AF6: 40 | AG6: 41 | AH6: 42 | AI6: 43 | AJ6: 44 | AK6: 45 | AL6: 46 | AM6: 47 | AN6: 48 | AO6: 49 | AP6: 50 | AQ6: 51 | AR6: 52 | AS6: 53 | AT6: 54 | AU6: 55 | AV6: 56 | AW6: 57 | AX6: 58 | AY6: 59 | AZ6: 60 | BA6: 61 | BB6: 62 | BC6: 63 | BD6: 64 | BE6: 65 | BF6: 66 | BG6: 67 | BH6: 68 | BI6: 69 | BJ6: 70 | BK6: 71 | BL6: 72 | BM6: 73 | BN6: 74 | BO6: 75 | BP6: 76 | BQ6: 77 | BR6: 78 | BS6: 79 | BT6: 80 | BU6: 81 | BV6: 82 | BW6: 83 | BX6: 84 | BY6: 85 | BZ6: 86 | CA6: 87 | CB6: 88 | CC6: 89 | CD6: 90 | CE6: 91 | CF6: 92 | CG6: 93 | CH6: 94 | CI6: 95 | CJ6: 96 | CK6: 97 | CL6: 98 | CM6: 99
A7: 300 | B7: 0.2 | C7: 0.5 | E7: 221 | F7: 221 | G7: 221 | H7: 221 | I7: 221 | J7: 221 | K7: 221 | L7: 221 | M7: 221 | N7: 221 | O7: 221 | P7: 221 | Q7: 221 | R7: 221 | S7: 221 | T7: 221 | U7: 221 | V7: 221 | W7: 221 | X7: 221 | Y7: 221 | Z7: 221 | AA7: 221 | AB7: 221 | AC7: 221 | AD7: 221 | AE7: 221 | AF7: 221 | AG7: 221 | AH7: 221 | AI7: 221 | AJ7: 221 | AK7: 221 | AL7: 221 | AM7: 221 | AN7: 221 | AO7: 221 | AP7: 167 | AQ7: 167 | AR7: 167 | AS7: 167 | AT7: 167 | AU7: 167 | AV7: 167 | AW7: 167 | AX7: 167 | AY7: 167 | AZ7: 167 | BA7: 167 | BB7: 167 | BC7: 167 | BD7: 167 | BE7: 167 | BF7: 167 | BG7: 167 | BH7: 167 | BI7: 167 | BJ7: 167 | BK7: 167 | BL7: 167 | BM7: 167 | BN7: 167 | BO7: 167 | BP7: 173 | BQ7: 173 | BR7: 173 | BS7: 173 | BT7: 167 | BU7: 167 | BV7: 167 | BW7: 167 | BX7: 167 | BY7: 167 | BZ7: 167 | CA7: 167 | CB7: 167 | CC7: 167 | CD7: 173 | CE7: 173 | CF7: 173 | CG7: 187 | CH7: 187 | CI7: 173 | CJ7: 173 | CK7: 187 | CL7: 187 | CM7: 187
A8: 700 | B8: 0.4 | C8: 1 | E8: 232 | F8: 232 | G8: 232 | H8: 232 | I8: 232 | J8: 232 | K8: 232 | L8: 232 | M8: 232 | N8: 232 | O8: 232 | P8: 232 | Q8: 232 | R8: 232 | S8: 232 | T8: 232 | U8: 232 | V8: 232 | W8: 232 | X8: 232 | Y8: 232 | Z8: 232 | AA8: 232 | AB8: 232 | AC8: 232 | AD8: 232 | AE8: 232 | AF8: 232 | AG8: 232 | AH8: 232 | AI8: 232 | AJ8: 232 | AK8: 232 | AL8: 232 | AM8: 232 | AN8: 232 | AO8: 232 | AP8: 175 | AQ8: 175 | AR8: 175 | AS8: 175 | AT8: 175 | AU8: 175 | AV8: 175 | AW8: 175 | AX8: 175 | AZ8: 175 | BA8: 175 | BB8: 175 | BC8: 175 | BD8: 175 | BE8: 175 | BF8: 175 | BG8: 175 | BH8: 175 | BI8: 175 | BJ8: 175 | BK8: 175 | BL8: 175 | BM8: 175 | BN8: 175 | BO8: 175 | BP8: 182 | BQ8: 182 | BR8: 182 | BS8: 182 | BT8: 175 | BU8: 175 | BV8: 175 | BW8: 175 | BX8: 175 | BY8: 175 | BZ8: 175 | CA8: 175 | CB8: 175 | CC8: 175 | CD8: 182 | CE8: 182 | CF8: 182 | CG8: 196 | CH8: 196 | CI8: 182 | CJ8: 182 | CK8: 196 | CL8: 196 | CM8: 196
A9: 875 | B9: 0.5 | D9: 1 | E9: 253 | F9: 253 | G9: 253 | H9: 253 | I9: 253 | J9: 253 | K9: 253 | L9: 253 | M9: 253 | N9: 253 | O9: 253 | P9: 253 | Q9: 253 | R9: 253 | S9: 253 | T9: 253 | U9: 253 | V9: 253 | W9: 253 | X9: 253 | Y9: 253 | Z9: 253 | AA9: 253 | AB9: 253 | AC9: 253 | AD9: 253 | AE9: 253 | AF9: 253 | AG9: 253 | AH9: 253 | AI9: 253 | AJ9: 253 | AK9: 253 | AL9: 253 | AM9: 253 | AN9: 253 | AO9: 253 | AP9: 190 | AQ9: 190 | AR9: 190 | AS9: 190 | AT9: 190 | AU9: 190 | AV9: 190 | AW9: 190 | AX9: 190 | AZ9: 182 | BA9: 182 | BB9: 182 | BC9: 182 | BD9: 182 | BE9: 182 | BF9: 182 | BG9: 182 | BH9: 190 | BI9: 190 | BJ9: 190 | BK9: 190 | BL9: 190 | BM9: 190 | BN9: 190 | BO9: 190 | BP9: 197 | BQ9: 197 | BR9: 197 | BS9: 197 | BT9: 190 | BU9: 190 | BV9: 190 | BW9: 190 | BX9: 190 | BY9: 190 | BZ9: 190 | CA9: 190 | CB9: 190 | CC9: 190 | CD9: 197 | CE9: 197 | CF9: 197 | CG9: 206 | CH9: 206 | CI9: 197 | CJ9: 197 | CK9: 206 | CL9: 206 | CM9: 206
A10: 1050 | B10: 0.6 | E10: 265 | F10: 265 | G10: 265 | H10: 265 | I10: 265 | J10: 265 | K10: 265 | L10: 265 | M10: 265 | N10: 265 | O10: 265 | P10: 265 | Q10: 265 | R10: 265 | S10: 265 | T10: 265 | U10: 265 | V10: 265 | W10: 265 | X10: 265 | Y10: 265 | Z10: 265 | AA10: 265 | AB10: 265 | AC10: 265 | AD10: 265 | AE10: 265 | AF10: 265 | AG10: 265 | AH10: 265 | AI10: 265 | AJ10: 265 | AK10: 265 | AL10: 265 | AM10: 265 | AN10: 265 | AO10: 265 | AP10: 203 | AQ10: 203 | AR10: 203 | AS10: 203 | AT10: 203 | AU10: 203 | AV10: 203 | AW10: 203 | AX10: 203 | AZ10: 194 | BA10: 194 | BB10: 194 | BC10: 194 | BD10: 194 | BE10: 194 | BF10: 194 | BG10: 194 | BH10: 203 | BI10: 203 | BJ10: 203 | BK10: 203 | BL10: 203 | BM10: 203 | BN10: 203 | BO10: 203 | BP10: 211 | BQ10: 211 | BR10: 211 | BS10: 211 | BT10: 203 | BU10: 203 | BV10: 203 | BW10: 203 | BX10: 203 | BY10: 203 | BZ10: 203 | CA10: 203 | CB10: 203 | CC10: 203 | CD10: 211 | CE10: 211 | CF10: 211 | CG10: 220 | CH10: 220 | CI10: 211 | CJ10: 211 | CK10: 220 | CL10: 220 | CM10: 220
A11: 1400 | B11: 0.8 | C11: 2 | E11: 287 | F11: 287 | G11: 287 | H11: 287 | I11: 287 | J11: 287 | K11: 287 | L11: 287 | M11: 287 | N11: 287 | O11: 287 | P11: 287 | Q11: 287 | R11: 287 | S11: 287 | T11: 287 | U11: 287 | V11: 287 | W11: 287 | X11: 287 | Y11: 287 | Z11: 287 | AA11: 287 | AB11: 287 | AC11: 287 | AD11: 287 | AE11: 287 | AF11: 287 | AG11: 287 | AH11: 287 | AI11: 287 | AJ11: 287 | AK11: 287 | AL11: 287 | AM11: 287 | AN11: 287 | AO11: 287 | AP11: 229 | AQ11: 229 | AR11: 229 | AS11: 229 | AT11: 229 | AU11: 229 | AV11: 229 | AW11: 229 | AX11: 229 | AZ11: 217 | BA11: 217 | BB11: 217 | BC11: 217 | BD11: 217 | BE11: 217 | BF11: 217 | BG11: 217 | BH11: 229 | BI11: 229 | BJ11: 229 | BK11: 229 | BL11: 229 | BM11: 229 | BN11: 229 | BO11: 229 | BP11: 237 | BQ11: 237 | BR11: 237 | BS11: 237 | BT11: 229 | BU11: 229 | BV11: 229 | BW11: 229 | BX11: 229 | BY11: 229 | BZ11: 229 | CA11: 229 | CB11: 229 | CC11: 229 | CD11: 237 | CE11: 237 | CF11: 237 | CG11: 247 | CH11: 247 | CI11: 237 | CJ11: 237 | CK11: 247 | CL11: 247 | CM11: 247
A12: 1750 | B12: 1 | D12: 2 | E12: 307 | F12: 307 | G12: 307 | H12: 307 | I12: 307 | J12: 307 | K12: 307 | L12: 307 | M12: 307 | N12: 307 | O12: 307 | P12: 307 | Q12: 307 | R12: 307 | S12: 307 | T12: 307 | U12: 307 | V12: 307 | W12: 307 | X12: 307 | Y12: 307 | Z12: 307 | AA12: 307 | AB12: 307 | AC12: 307 | AD12: 307 | AE12: 307 | AF12: 307 | AG12: 307 | AH12: 307 | AI12: 307 | AJ12: 307 | AK12: 307 | AL12: 307 | AM12: 307 | AN12: 307 | AO12: 307 | AP12: 274 | AQ12: 274 | AR12: 274 | AS12: 274 | AT12: 274 | AU12: 274 | AV12: 274 | AW12: 274 | AX12: 274 | AZ12: 259 | BA12: 259 | BB12: 259 | BC12: 259 | BD12: 259 | BE12: 259 | BF12: 259 | BG12: 259 | BH12: 274 | BI12: 274 | BJ12: 274 | BK12: 274 | BL12: 274 | BM12: 274 | BN12: 274 | BO12: 274 | BP12: 284 | BQ12: 284 | BR12: 284 | BS12: 284 | BT12: 274 | BU12: 274 | BV12: 274 | BW12: 274 | BX12: 274 | BY12: 274 | BZ12: 274 | CA12: 274 | CB12: 274 | CC12: 274 | CD12: 284 | CE12: 284 | CF12: 284 | CG12: 296 | CH12: 296 | CI12: 284 | CJ12: 284 | CK12: 296 | CL12: 296 | CM12: 296
A13: 2100 | B13: 1.2 | C13: 3 | E13: 348 | F13: 348 | G13: 348 | H13: 348 | I13: 348 | J13: 348 | K13: 348 | L13: 348 | M13: 348 | N13: 348 | O13: 348 | P13: 348 | Q13: 348 | R13: 348 | S13: 348 | T13: 348 | U13: 348 | V13: 348 | W13: 348 | X13: 348 | Y13: 348 | Z13: 348 | AA13: 348 | AB13: 348 | AC13: 348 | AD13: 348 | AE13: 348 | AF13: 348 | AG13: 348 | AH13: 348 | AI13: 348 | AJ13: 348 | AK13: 348 | AL13: 348 | AM13: 348 | AN13: 348 | AO13: 348 | AP13: 301 | AQ13: 301 | AR13: 301 | AS13: 301 | AT13: 301 | AU13: 301 | AV13: 301 | AW13: 301 | AX13: 301 | AZ13: 285 | BA13: 285 | BB13: 285 | BC13: 285 | BD13: 285 | BE13: 285 | BF13: 285 | BG13: 285 | BH13: 301 | BI13: 301 | BJ13: 301 | BK13: 301 | BL13: 301 | BM13: 301 | BN13: 301 | BO13: 301 | BP13: 312 | BQ13: 312 | BR13: 312 | BS13: 312 | BT13: 301 | BU13: 301 | BV13: 301 | BW13: 301 | BX13: 301 | BY13: 301 | BZ13: 301 | CA13: 301 | CB13: 301 | CC13: 301 | CD13: 312 | CE13: 312 | CF13: 312 | CG13: 325 | CH13: 325 | CI13: 312 | CJ13: 312 | CK13: 325 | CL13: 325 | CM13: 325
A14: 2625 | B14: 1.5 | D14: 3 | E14: 382 | F14: 382 | G14: 382 | H14: 382 | I14: 382 | J14: 382 | K14: 382 | L14: 382 | M14: 382 | N14: 382 | O14: 382 | P14: 382 | Q14: 382 | R14: 382 | S14: 382 | T14: 382 | U14: 382 | V14: 382 | W14: 382 | X14: 382 | Y14: 382 | Z14: 382 | AA14: 382 | AB14: 382 | AC14: 382 | AD14: 382 | AE14: 382 | AF14: 382 | AG14: 382 | AH14: 382 | AI14: 382 | AJ14: 382 | AK14: 382 | AL14: 382 | AM14: 382 | AN14: 382 | AO14: 382 | AP14: 350 | AQ14: 350 | AR14: 350 | AS14: 350 | AT14: 350 | AU14: 350 | AV14: 350 | AW14: 350 | AX14: 350 | AZ14: 332 | BA14: 332 | BB14: 332 | BC14: 332 | BD14: 332 | BE14: 332 | BF14: 332 | BG14: 332 | BH14: 350 | BI14: 350 | BJ14: 350 | BK14: 350 | BL14: 350 | BM14: 350 | BN14: 350 | BO14: 350 | BP14: 362 | BQ14: 362 | BR14: 362 | BS14: 362 | BT14: 350 | BU14: 350 | BV14: 350 | BW14: 350 | BX14: 350 | BY14: 350 | BZ14: 350 | CA14: 350 | CB14: 350 | CC14: 350 | CD14: 362 | CE14: 362 | CF14: 362 | CG14: 378 | CH14: 378 | CI14: 362 | CJ14: 362 | CK14: 378 | CL14: 378 | CM14: 378
A15: 2800 | B15: 1.6 | C15: 4 | E15: 414 | F15: 414 | G15: 414 | H15: 414 | I15: 414 | J15: 414 | K15: 414 | L15: 414 | M15: 414 | N15: 414 | O15: 414 | P15: 414 | Q15: 414 | R15: 414 | S15: 414 | T15: 414 | U15: 414 | V15: 414 | W15: 414 | X15: 414 | Y15: 414 | Z15: 414 | AA15: 414 | AB15: 414 | AC15: 414 | AD15: 414 | AE15: 414 | AF15: 414 | AG15: 414 | AH15: 414 | AI15: 414 | AJ15: 414 | AK15: 414 | AL15: 414 | AM15: 414 | AN15: 414 | AO15: 414 | AP15: 373 | AQ15: 373 | AR15: 373 | AS15: 373 | AT15: 373 | AU15: 373 | AV15: 373 | AW15: 373 | AX15: 373 | AZ15: 354 | BA15: 354 | BB15: 354 | BC15: 354 | BD15: 354 | BE15: 354 | BF15: 354 | BG15: 354 | BH15: 373 | BI15: 373 | BJ15: 373 | BK15: 373 | BL15: 373 | BM15: 373 | BN15: 373 | BO15: 373 | BP15: 386 | BQ15: 386 | BR15: 386 | BS15: 386 | BT15: 373 | BU15: 373 | BV15: 373 | BW15: 373 | BX15: 373 | BY15: 373 | BZ15: 373 | CA15: 373 | CB15: 373 | CC15: 373 | CD15: 386 | CE15: 386 | CF15: 386 | CG15: 402 | CH15: 402 | CI15: 386 | CJ15: 386 | CK15: 402 | CL15: 402 | CM15: 402
A16: 3500 | B16: 2 | C16: 5 | D16: 4 | E16: 473 | F16: 473 | G16: 473 | H16: 473 | I16: 473 | J16: 473 | K16: 473 | L16: 473 | M16: 473 | N16: 473 | O16: 473 | P16: 473 | Q16: 473 | R16: 473 | S16: 473 | T16: 473 | U16: 473 | V16: 473 | W16: 473 | X16: 473 | Y16: 473 | Z16: 473 | AA16: 473 | AB16: 473 | AC16: 473 | AD16: 473 | AE16: 473 | AF16: 473 | AG16: 473 | AH16: 473 | AI16: 473 | AJ16: 473 | AK16: 473 | AL16: 473 | AM16: 473 | AN16: 473 | AO16: 473 | AP16: 431 | AQ16: 431 | AR16: 431 | AS16: 431 | AT16: 431 | AU16: 431 | AV16: 431 | AW16: 431 | AX16: 431 | AZ16: 407 | BA16: 407 | BB16: 407 | BC16: 407 | BD16: 407 | BE16: 407 | BF16: 407 | BG16: 407 | BH16: 431 | BI16: 431 | BJ16: 431 | BK16: 431 | BL16: 431 | BM16: 431 | BN16: 431 | BO16: 431 | BP16: 446 | BQ16: 446 | BR16: 446 | BS16: 446 | BT16: 431 | BU16: 431 | BV16: 431 | BW16: 431 | BX16: 431 | BY16: 431 | BZ16: 431 | CA16: 431 | CB16: 431 | CC16: 431 | CD16: 446 | CE16: 446 | CF16: 446 | CG16: 465 | CH16: 465 | CI16: 446 | CJ16: 446 | CK16: 465 | CL16: 465 | CM16: 465
A17: 4200 | B17: 2.4 | C17: 6 | E17: 523 | F17: 523 | G17: 523 | H17: 523 | I17: 523 | J17: 523 | K17: 523 | L17: 523 | M17: 523 | N17: 523 | O17: 523 | P17: 523 | Q17: 523 | R17: 523 | S17: 523 | T17: 523 | U17: 523 | V17: 523 | W17: 523 | X17: 523 | Y17: 523 | Z17: 523 | AA17: 523 | AB17: 523 | AC17: 523 | AD17: 523 | AE17: 523 | AF17: 523 | AG17: 523 | AH17: 523 | AI17: 523 | AJ17: 523 | AK17: 523 | AL17: 523 | AM17: 523 | AN17: 523 | AO17: 523 | AP17: 481 | AQ17: 481 | AR17: 481 | AS17: 481 | AT17: 481 | AU17: 481 | AV17: 481 | AW17: 481 | AX17: 481 | AZ17: 455 | BA17: 455 | BB17: 455 | BC17: 455 | BD17: 455 | BE17: 455 | BF17: 455 | BG17: 455 | BH17: 481 | BI17: 481 | BJ17: 481 | BK17: 481 | BL17: 481 | BM17: 481 | BN17: 481 | BO17: 481 | BP17: 498 | BQ17: 498 | BR17: 498 | BS17: 498 | BT17: 481 | BU17: 481 | BV17: 481 | BW17: 481 | BX17: 481 | BY17: 481 | BZ17: 481 | CA17: 481 | CB17: 481 | CC17: 481 | CD17: 498 | CE17: 498 | CF17: 498 | CG17: 519 | CH17: 519 | CI17: 498 | CJ17: 498 | CK17: 519 | CL17: 519 | CM17: 519
A18: 4375 | B18: 2.5 | D18: 5 | E18: 535 | F18: 535 | G18: 535 | H18: 535 | I18: 535 | J18: 535 | K18: 535 | L18: 535 | M18: 535 | N18: 535 | O18: 535 | P18: 535 | Q18: 535 | R18: 535 | S18: 535 | T18: 535 | U18: 535 | V18: 535 | W18: 535 | X18: 535 | Y18: 535 | Z18: 535 | AA18: 535 | AB18: 535 | AC18: 535 | AD18: 535 | AE18: 535 | AF18: 535 | AG18: 535 | AH18: 535 | AI18: 535 | AJ18: 535 | AK18: 535 | AL18: 535 | AM18: 535 | AN18: 535 | AO18: 535 | AP18: 484 | AQ18: 484 | AR18: 484 | AS18: 484 | AT18: 484 | AU18: 484 | AV18: 484 | AW18: 484 | AX18: 484 | AZ18: 459 | BA18: 459 | BB18: 459 | BC18: 459 | BD18: 459 | BE18: 459 | BF18: 459 | BG18: 459 | BH18: 484 | BI18: 484 | BJ18: 484 | BK18: 484 | BL18: 484 | BM18: 484 | BN18: 484 | BO18: 484 | BP18: 500 | BQ18: 500 | BR18: 500 | BS18: 500 | BT18: 484 | BU18: 484 | BV18: 484 | BW18: 484 | BX18: 484 | BY18: 484 | BZ18: 484 | CA18: 484 | CB18: 484 | CC18: 484 | CD18: 500 | CE18: 500 | CF18: 500 | CG18: 522 | CH18: 522 | CI18: 500 | CJ18: 500 | CK18: 522 | CL18: 522 | CM18: 522
A19: 4900 | B19: 2.8 | C19: 7 | E19: 586 | F19: 586 | G19: 586 | H19: 586 | I19: 586 | J19: 586 | K19: 586 | L19: 586 | M19: 586 | N19: 586 | O19: 586 | P19: 586 | Q19: 586 | R19: 586 | S19: 586 | T19: 586 | U19: 586 | V19: 586 | W19: 586 | X19: 586 | Y19: 586 | Z19: 586 | AA19: 586 | AB19: 586 | AC19: 586 | AD19: 586 | AE19: 586 | AF19: 586 | AG19: 586 | AH19: 586 | AI19: 586 | AJ19: 586 | AK19: 586 | AL19: 586 | AM19: 586 | AN19: 586 | AO19: 586 | AP19: 541 | AQ19: 541 | AR19: 541 | AS19: 541 | AT19: 541 | AU19: 541 | AV19: 541 | AW19: 541 | AX19: 541 | AZ19: 513 | BA19: 513 | BB19: 513 | BC19: 513 | BD19: 513 | BE19: 513 | BF19: 513 | BG19: 513 | BH19: 541 | BI19: 541 | BJ19: 541 | BK19: 541 | BL19: 541 | BM19: 541 | BN19: 541 | BO19: 541 | BP19: 560 | BQ19: 560 | BR19: 560 | BS19: 560 | BT19: 541 | BU19: 541 | BV19: 541 | BW19: 541 | BX19: 541 | BY19: 541 | BZ19: 541 | CA19: 541 | CB19: 541 | CC19: 541 | CD19: 560 | CE19: 560 | CF19: 560 | CG19: 584 | CH19: 584 | CI19: 560 | CJ19: 560 | CK19: 584 | CL19: 584 | CM19: 584
A20: 5250 | B20: 3 | D20: 6 | E20: 612 | F20: 612 | G20: 612 | H20: 612 | I20: 612 | J20: 612 | K20: 612 | L20: 612 | M20: 612 | N20: 612 | O20: 612 | P20: 612 | Q20: 612 | R20: 612 | S20: 612 | T20: 612 | U20: 612 | V20: 612 | W20: 612 | X20: 612 | Y20: 612 | Z20: 612 | AA20: 612 | AB20: 612 | AC20: 612 | AD20: 612 | AE20: 612 | AF20: 612 | AG20: 612 | AH20: 612 | AI20: 612 | AJ20: 612 | AK20: 612 | AL20: 612 | AM20: 612 | AN20: 612 | AO20: 612 | AP20: 549 | AQ20: 549 | AR20: 549 | AS20: 549 | AT20: 549 | AU20: 549 | AV20: 549 | AW20: 549 | AX20: 549 | AZ20: 520 | BA20: 520 | BB20: 520 | BC20: 520 | BD20: 520 | BE20: 520 | BF20: 520 | BG20: 520 | BH20: 549 | BI20: 549 | BJ20: 549 | BK20: 549 | BL20: 549 | BM20: 549 | BN20: 549 | BO20: 549 | BP20: 569 | BQ20: 569 | BR20: 569 | BS20: 569 | BT20: 549 | BU20: 549 | BV20: 549 | BW20: 549 | BX20: 549 | BY20: 549 | BZ20: 549 | CA20: 549 | CB20: 549 | CC20: 549 | CD20: 569 | CE20: 569 | CF20: 569 | CG20: 593 | CH20: 593 | CI20: 569 | CJ20: 569 | CK20: 593 | CL20: 593 | CM20: 593
A21: 5600 | B21: 3.2 | C21: 8 | E21: 647 | F21: 647 | G21: 647 | H21: 647 | I21: 647 | J21: 647 | K21: 647 | L21: 647 | M21: 647 | N21: 647 | O21: 647 | P21: 647 | Q21: 647 | R21: 647 | S21: 647 | T21: 647 | U21: 647 | V21: 647 | W21: 647 | X21: 647 | Y21: 647 | Z21: 647 | AA21: 647 | AB21: 647 | AC21: 647 | AD21: 647 | AE21: 647 | AF21: 647 | AG21: 647 | AH21: 647 | AI21: 647 | AJ21: 647 | AK21: 647 | AL21: 647 | AM21: 647 | AN21: 647 | AO21: 647 | AP21: 600 | AQ21: 600 | AR21: 600 | AS21: 600 | AT21: 600 | AU21: 600 | AV21: 600 | AW21: 600 | AX21: 600 | AZ21: 569 | BA21: 569 | BB21: 569 | BC21: 569 | BD21: 569 | BE21: 569 | BF21: 569 | BG21: 569 | BH21: 600 | BI21: 600 | BJ21: 600 | BK21: 600 | BL21: 600 | BM21: 600 | BN21: 600 | BO21: 600 | BP21: 621 | BQ21: 621 | BR21: 621 | BS21: 621 | BT21: 600 | BU21: 600 | BV21: 600 | BW21: 600 | BX21: 600 | BY21: 600 | BZ21: 600 | CA21: 600 | CB21: 600 | CC21: 600 | CD21: 621 | CE21: 621 | CF21: 621 | CG21: 647 | CH21: 647 | CI21: 621 | CJ21: 621 | CK21: 647 | CL21: 647 | CM21: 647
A22: 6125 | B22: 3.5 | D22: 7 | E22: 692 | F22: 692 | G22: 692 | H22: 692 | I22: 692 | J22: 692 | K22: 692 | L22: 692 | M22: 692 | N22: 692 | O22: 692 | P22: 692 | Q22: 692 | R22: 692 | S22: 692 | T22: 692 | U22: 692 | V22: 692 | W22: 692 | X22: 692 | Y22: 692 | Z22: 692 | AA22: 692 | AB22: 692 | AC22: 692 | AD22: 692 | AE22: 692 | AF22: 692 | AG22: 692 | AH22: 692 | AI22: 692 | AJ22: 692 | AK22: 692 | AL22: 692 | AM22: 692 | AN22: 692 | AO22: 692 | AP22: 614 | AQ22: 614 | AR22: 614 | AS22: 614 | AT22: 614 | AU22: 614 | AV22: 614 | AW22: 614 | AX22: 614 | AZ22: 582 | BA22: 582 | BB22: 582 | BC22: 582 | BD22: 582 | BE22: 582 | BF22: 582 | BG22: 582 | BH22: 614 | BI22: 614 | BJ22: 614 | BK22: 614 | BL22: 614 | BM22: 614 | BN22: 614 | BO22: 614 | BP22: 636 | BQ22: 636 | BR22: 636 | BS22: 636 | BT22: 614 | BU22: 614 | BV22: 614 | BW22: 614 | BX22: 614 | BY22: 614 | BZ22: 614 | CA22: 614 | CB22: 614 | CC22: 614 | CD22: 636 | CE22: 636 | CF22: 636 | CG22: 663 | CH22: 663 | CI22: 636 | CJ22: 636 | CK22: 663 | CL22: 663 | CM22: 663
A23: 6300 | B23: 3.6 | C23: 9 | E23: 710 | F23: 710 | G23: 710 | H23: 710 | I23: 710 | J23: 710 | K23: 710 | L23: 710 | M23: 710 | N23: 710 | O23: 710 | P23: 710 | Q23: 710 | R23: 710 | S23: 710 | T23: 710 | U23: 710 | V23: 710 | W23: 710 | X23: 710 | Y23: 710 | Z23: 710 | AA23: 710 | AB23: 710 | AC23: 710 | AD23: 710 | AE23: 710 | AF23: 710 | AG23: 710 | AH23: 710 | AI23: 710 | AJ23: 710 | AK23: 710 | AL23: 710 | AM23: 710 | AN23: 710 | AO23: 710 | AP23: 655 | AQ23: 655 | AR23: 655 | AS23: 655 | AT23: 655 | AU23: 655 | AV23: 655 | AW23: 655 | AX23: 655 | AZ23: 621 | BA23: 621 | BB23: 621 | BC23: 621 | BD23: 621 | BE23: 621 | BF23: 621 | BG23: 621 | BH23: 655 | BI23: 655 | BJ23: 655 | BK23: 655 | BL23: 655 | BM23: 655 | BN23: 655 | BO23: 655 | BP23: 678 | BQ23: 678 | BR23: 678 | BS23: 678 | BT23: 655 | BU23: 655 | BV23: 655 | BW23: 655 | BX23: 655 | BY23: 655 | BZ23: 655 | CA23: 655 | CB23: 655 | CC23: 655 | CD23: 678 | CE23: 678 | CF23: 678 | CG23: 707 | CH23: 707 | CI23: 678 | CJ23: 678 | CK23: 707 | CL23: 707 | CM23: 707
A24: 7000 | B24: 4 | C24: 10 | D24: 8 | E24: 763 | F24: 763 | G24: 763 | H24: 763 | I24: 763 | J24: 763 | K24: 763 | L24: 763 | M24: 763 | N24: 763 | O24: 763 | P24: 763 | Q24: 763 | R24: 763 | S24: 763 | T24: 763 | U24: 763 | V24: 763 | W24: 763 | X24: 763 | Y24: 763 | Z24: 763 | AA24: 763 | AB24: 763 | AC24: 763 | AD24: 763 | AE24: 763 | AF24: 763 | AG24: 763 | AH24: 763 | AI24: 763 | AJ24: 763 | AK24: 763 | AL24: 763 | AM24: 763 | AN24: 763 | AO24: 763 | AP24: 690 | AQ24: 690 | AR24: 690 | AS24: 690 | AT24: 690 | AU24: 690 | AV24: 690 | AW24: 690 | AX24: 690 | AZ24: 654 | BA24: 654 | BB24: 654 | BC24: 654 | BD24: 654 | BE24: 654 | BF24: 654 | BG24: 654 | BH24: 690 | BI24: 690 | BJ24: 690 | BK24: 690 | BL24: 690 | BM24: 690 | BN24: 690 | BO24: 690 | BP24: 714 | BQ24: 714 | BR24: 714 | BS24: 714 | BT24: 690 | BU24: 690 | BV24: 690 | BW24: 690 | BX24: 690 | BY24: 690 | BZ24: 690 | CA24: 690 | CB24: 690 | CC24: 690 | CD24: 714 | CE24: 714 | CF24: 714 | CG24: 744 | CH24: 744 | CI24: 714 | CJ24: 714 | CK24: 744 | CL24: 744 | CM24: 744
A26: Transittijden:
A28: Dag van lading = Dag 0 | C28: Vertrek | G28: Transittijd in werkdagen | T28: Transittijd in werkdagen | AG28: Transittijd in werkdagen | AT28: Transittijd in werkdagen | BG28: Transittijd in werkdagen | BT28: Transittijd in werkdagen
A29: Groupage 1-5 pallets | C29: ma,di,wo,do,vrij | E29: 3/4 | F29: 3/4 | G29: 3/4 | H29: 3/4 | I29: 3/4 | J29: 3/4 | K29: 3/4 | L29: 3/4 | M29: 3/4 | N29: 3/4 | O29: 3/4 | P29: 3/4 | Q29: 3/4 | R29: 3/4 | S29: 3/4 | T29: 3/4 | U29: 3/4 | V29: 3/4 | W29: 3/4 | X29: 3/4 | Y29: 3/4 | Z29: 3/4 | AA29: 3/4 | AB29: 3/4 | AC29: 3/4 | AD29: 3/4 | AE29: 3/4 | AF29: 3/4 | AG29: 3/4 | AH29: 3/4 | AI29: 3/4 | AJ29: 3/4 | AK29: 3/4 | AL29: 3/4 | AM29: 3/4 | AN29: 3/4 | AO29: 3/4 | AP29: 3/4 | AQ29: 3/4 | AR29: 3/4 | AS29: 3/4 | AT29: 3/4 | AU29: 3/4 | AV29: 3/4 | AW29: 3/4 | AX29: 3/4 | AY29: 3/4 | AZ29: 3/4 | BA29: 3/4 | BB29: 3/4 | BC29: 3/4 | BD29: 3/4 | BE29: 3/4 | BF29: 3/4 | BG29: 3/4 | BH29: 3/4 | BI29: 3/4 | BJ29: 3/4 | BK29: 3/4 | BL29: 3/4 | BM29: 3/4 | BN29: 3/4 | BO29: 3/4 | BP29: 3/4 | BQ29: 3/4 | BR29: 3/4 | BS29: 3/4 | BT29: 3/4 | BU29: 3/4 | BV29: 3/4 | BW29: 3/4 | BX29: 3/4 | BY29: 3/4 | BZ29: 3/4 | CA29: 3/4 | CB29: 3/4 | CC29: 3/4 | CD29: 3/4 | CE29: 3/4 | CF29: 3/4 | CG29: 3/4 | CH29: 3/4 | CI29: 3/4 | CJ29: 3/4 | CK29: 3/4 | CL29: 3/4 | CM29: 3/4
A30: Deelpartijen > 5 pallets | C30: ma,di,wo,do,vrij | E30: 3 | F30: 3 | G30: 3 | H30: 3 | I30: 3 | J30: 3 | K30: 3 | L30: 3 | M30: 3 | N30: 3 | O30: 3 | P30: 3 | Q30: 3 | R30: 3 | S30: 3 | T30: 3 | U30: 3 | V30: 3 | W30: 3 | X30: 3 | Y30: 3 | Z30: 3 | AA30: 3 | AB30: 3 | AC30: 3 | AD30: 3 | AE30: 3 | AF30: 3 | AG30: 3 | AH30: 3 | AI30: 3 | AJ30: 3 | AK30: 3 | AL30: 3 | AM30: 3 | AN30: 3 | AO30: 3 | AP30: 3 | AQ30: 3 | AR30: 3 | AS30: 3 | AT30: 3 | AU30: 3 | AV30: 3 | AW30: 3 | AX30: 3 | AY30: 3 | AZ30: 3 | BA30: 3 | BB30: 3 | BC30: 3 | BD30: 3 | BE30: 3 | BF30: 3 | BG30: 3 | BH30: 3 | BI30: 3 | BJ30: 3 | BK30: 3 | BL30: 3 | BM30: 3 | BN30: 3 | BO30: 3 | BP30: 3 | BQ30: 3 | BR30: 3 | BS30: 3 | BT30: 3 | BU30: 3 | BV30: 3 | BW30: 3 | BX30: 3 | BY30: 3 | BZ30: 3 | CA30: 3 | CB30: 3 | CC30: 3 | CD30: 3 | CE30: 3 | CF30: 3 | CG30: 3 | CH30: 3 | CI30: 3 | CJ30: 3 | CK30: 3 | CL30: 3 | CM30: 3
A31: Compleet ladingen | C31: ma,di,wo,do,vrij | E31: 2 | F31: 1 | G31: 2 | H31: 2 | I31: 2 | J31: 2 | K31: 2 | L31: 1 | M31: 2 | N31: 1 | O31: 2 | P31: 2 | Q31: 2 | R31: 1 | S31: 2 | T31: 2 | U31: 2 | V31: 2 | W31: 2 | X31: 2 | Y31: 2 | Z31: 2 | AA31: 2 | AB31: 2 | AC31: 2 | AD31: 1 | AE31: 2 | AF31: 2 | AG31: 2 | AH31: 2 | AI31: 2 | AJ31: 2 | AK31: 2 | AL31: 2 | AM31: 2 | AN31: 2 | AO31: 2 | AP31: 2 | AQ31: 2 | AR31: 2 | AS31: 2 | AT31: 2 | AU31: 2 | AV31: 2 | AW31: 2 | AX31: 1 | AY31: 1 | AZ31: 2 | BA31: 1 | BB31: 1 | BC31: 2 | BD31: 1 | BE31: 2 | BF31: 1 | BG31: 1 | BH31: 1 | BI31: 1 | BJ31: 2 | BK31: 2 | BL31: 2 | BM31: 2 | BN31: 1 | BO31: 1 | BP31: 2 | BQ31: 1 | BR31: 2 | BS31: 2 | BT31: 2 | BU31: 1 | BV31: 1 | BW31: 1 | BX31: 2 | BY31: 2 | BZ31: 1 | CA31: 2 | CB31: 2 | CC31: 2 | CD31: 2 | CE31: 2 | CF31: 2 | CG31: 1 | CH31: 2 | CI31: 1 | CJ31: 1 | CK31: 1 | CL31: 1 | CM31: 1
A33: Condities:
A34: * Tarief is niet geldig voor de eilanden

Sheet EE
A3: =Voorblad!A5 -> Team Freight Forwarding Logistics
A4: Export Estland
A6: kg | B6: ldm | C6: euplt | D6: blkplt | E6: 10 | F6: 20 | G6: 21 | H6: 30 | I6: 31 | J6: 40 | K6: 41 | L6: 42 | M6: 43 | N6: 44 | O6: 45 | P6: 46 | Q6: 48 | R6: 49 | S6: 50 | T6: 51 | U6: 60 | V6: 61 | W6: 62 | X6: 63 | Y6: 64 | Z6: 65 | AA6: 66 | AB6: 67 | AC6: 68 | AD6: 69 | AE6: 70 | AF6: 71 | AG6: 72 | AH6: 73 | AI6: 74 | AJ6: 75 | AK6: 76 | AL6: 78 | AM6: 79 | AN6: 80 | AO6: 85 | AP6: 86 | AQ6: 87 | AR6: 88 | AS6: 90 | AT6: 91
A7: 300 | B7: 0.2 | C7: 0.5 | E7: 144 | F7: 171 | G7: 171 | H7: 171 | I7: 171 | J7: 171 | K7: 171 | L7: 171 | M7: 171 | N7: 165 | O7: 165 | P7: 165 | Q7: 171 | R7: 171 | S7: 171 | T7: 171 | U7: 171 | V7: 171 | W7: 171 | X7: 171 | Y7: 171 | Z7: 171 | AA7: 171 | AB7: 171 | AC7: 171 | AD7: 171 | AE7: 171 | AF7: 171 | AG7: 165 | AH7: 165 | AI7: 157 | AJ7: 157 | AK7: 157 | AL7: 165 | AM7: 165 | AN7: 171 | AO7: 171 | AP7: 171 | AQ7: 171 | AR7: 171 | AS7: 171 | AT7: 165
A8: 700 | B8: 0.4 | C8: 1 | E8: 182 | F8: 219 | G8: 219 | H8: 219 | I8: 219 | J8: 219 | K8: 219 | L8: 219 | M8: 219 | N8: 209 | O8: 209 | P8: 209 | Q8: 219 | R8: 219 | S8: 219 | T8: 219 | U8: 219 | V8: 219 | W8: 219 | X8: 219 | Y8: 219 | Z8: 219 | AA8: 219 | AB8: 219 | AC8: 219 | AD8: 219 | AE8: 219 | AF8: 219 | AG8: 209 | AH8: 209 | AI8: 200 | AJ8: 200 | AK8: 200 | AL8: 209 | AM8: 209 | AN8: 219 | AO8: 219 | AP8: 219 | AQ8: 219 | AR8: 219 | AS8: 209 | AT8: 209
A9: 875 | B9: 0.5 | D9: 1 | E9: 200 | F9: 240 | G9: 240 | H9: 240 | I9: 240 | J9: 240 | K9: 240 | L9: 240 | M9: 240 | N9: 230 | O9: 230 | P9: 230 | Q9: 240 | R9: 240 | S9: 240 | T9: 240 | U9: 240 | V9: 240 | W9: 240 | X9: 240 | Y9: 240 | Z9: 240 | AA9: 240 | AB9: 240 | AC9: 240 | AD9: 240 | AE9: 240 | AF9: 240 | AG9: 230 | AH9: 230 | AI9: 221 | AJ9: 221 | AK9: 221 | AL9: 230 | AM9: 230 | AN9: 240 | AO9: 240 | AP9: 240 | AQ9: 240 | AR9: 240 | AS9: 230 | AT9: 230
A10: 1050 | B10: 0.6 | E10: 213 | F10: 255 | G10: 255 | H10: 255 | I10: 255 | J10: 255 | K10: 255 | L10: 255 | M10: 255 | N10: 245 | O10: 245 | P10: 245 | Q10: 255 | R10: 255 | S10: 255 | T10: 255 | U10: 255 | V10: 255 | W10: 255 | X10: 255 | Y10: 255 | Z10: 255 | AA10: 255 | AB10: 255 | AC10: 255 | AD10: 255 | AE10: 255 | AF10: 255 | AG10: 245 | AH10: 245 | AI10: 235 | AJ10: 235 | AK10: 235 | AL10: 245 | AM10: 245 | AN10: 255 | AO10: 255 | AP10: 255 | AQ10: 255 | AR10: 255 | AS10: 245 | AT10: 245
A11: 1400 | B11: 0.8 | C11: 2 | E11: 274 | F11: 329 | G11: 329 | H11: 329 | I11: 329 | J11: 329 | K11: 329 | L11: 329 | M11: 329 | N11: 315 | O11: 315 | P11: 315 | Q11: 329 | R11: 329 | S11: 329 | T11: 329 | U11: 329 | V11: 329 | W11: 329 | X11: 329 | Y11: 329 | Z11: 329 | AA11: 329 | AB11: 329 | AC11: 329 | AD11: 329 | AE11: 329 | AF11: 329 | AG11: 315 | AH11: 315 | AI11: 300 | AJ11: 300 | AK11: 300 | AL11: 315 | AM11: 315 | AN11: 329 | AO11: 329 | AP11: 329 | AQ11: 329 | AR11: 329 | AS11: 315 | AT11: 315
A12: 1750 | B12: 1 | D12: 2 | E12: 327 | F12: 392 | G12: 392 | H12: 392 | I12: 392 | J12: 392 | K12: 392 | L12: 392 | M12: 392 | N12: 376 | O12: 376 | P12: 376 | Q12: 392 | R12: 392 | S12: 392 | T12: 392 | U12: 392 | V12: 392 | W12: 392 | X12: 392 | Y12: 392 | Z12: 392 | AA12: 392 | AB12: 392 | AC12: 392 | AD12: 392 | AE12: 392 | AF12: 392 | AG12: 376 | AH12: 376 | AI12: 360 | AJ12: 360 | AK12: 360 | AL12: 376 | AM12: 376 | AN12: 392 | AO12: 392 | AP12: 392 | AQ12: 392 | AR12: 392 | AS12: 376 | AT12: 376
A13: 2100 | B13: 1.2 | C13: 3 | E13: 379 | F13: 454 | G13: 454 | H13: 454 | I13: 454 | J13: 454 | K13: 454 | L13: 454 | M13: 454 | N13: 436 | O13: 436 | P13: 436 | Q13: 454 | R13: 454 | S13: 454 | T13: 454 | U13: 454 | V13: 454 | W13: 454 | X13: 454 | Y13: 454 | Z13: 454 | AA13: 454 | AB13: 454 | AC13: 454 | AD13: 454 | AE13: 454 | AF13: 454 | AG13: 436 | AH13: 436 | AI13: 416 | AJ13: 416 | AK13: 416 | AL13: 436 | AM13: 436 | AN13: 454 | AO13: 454 | AP13: 454 | AQ13: 454 | AR13: 454 | AS13: 436 | AT13: 436
A14: 2625 | B14: 1.5 | D14: 3 | E14: 437 | F14: 524 | G14: 524 | H14: 524 | I14: 524 | J14: 524 | K14: 524 | L14: 524 | M14: 524 | N14: 502 | O14: 502 | P14: 502 | Q14: 524 | R14: 524 | S14: 524 | T14: 524 | U14: 524 | V14: 524 | W14: 524 | X14: 524 | Y14: 524 | Z14: 524 | AA14: 524 | AB14: 524 | AC14: 524 | AD14: 524 | AE14: 524 | AF14: 524 | AG14: 502 | AH14: 502 | AI14: 481 | AJ14: 481 | AK14: 481 | AL14: 502 | AM14: 502 | AN14: 524 | AO14: 524 | AP14: 524 | AQ14: 524 | AR14: 524 | AS14: 502 | AT14: 502
A15: 2800 | B15: 1.6 | C15: 4 | E15: 476 | F15: 571 | G15: 571 | H15: 571 | I15: 571 | J15: 571 | K15: 571 | L15: 571 | M15: 571 | N15: 546 | O15: 546 | P15: 546 | Q15: 571 | R15: 571 | S15: 571 | T15: 571 | U15: 571 | V15: 571 | W15: 571 | X15: 571 | Y15: 571 | Z15: 571 | AA15: 571 | AB15: 571 | AC15: 571 | AD15: 571 | AE15: 571 | AF15: 571 | AG15: 546 | AH15: 546 | AI15: 523 | AJ15: 523 | AK15: 523 | AL15: 546 | AM15: 546 | AN15: 571 | AO15: 571 | AP15: 571 | AQ15: 571 | AR15: 571 | AS15: 546 | AT15: 546
A16: 3500 | B16: 2 | C16: 5 | D16: 4 | E16: 557 | F16: 669 | G16: 669 | H16: 669 | I16: 669 | J16: 669 | K16: 669 | L16: 669 | M16: 669 | N16: 641 | O16: 641 | P16: 641 | Q16: 669 | R16: 669 | S16: 669 | T16: 669 | U16: 669 | V16: 669 | W16: 669 | X16: 669 | Y16: 669 | Z16: 669 | AA16: 669 | AB16: 669 | AC16: 669 | AD16: 669 | AE16: 669 | AF16: 669 | AG16: 641 | AH16: 641 | AI16: 614 | AJ16: 614 | AK16: 614 | AL16: 641 | AM16: 641 | AN16: 669 | AO16: 669 | AP16: 669 | AQ16: 669 | AR16: 669 | AS16: 641 | AT16: 641
A17: 4200 | B17: 2.4 | C17: 6 | E17: 594 | F17: 706 | G17: 706 | H17: 705 | I17: 705 | J17: 705 | K17: 704 | L17: 704 | M17: 705 | N17: 677 | O17: 677 | P17: 676 | Q17: 703 | R17: 703 | S17: 702 | T17: 702 | U17: 702 | V17: 701 | W17: 702 | X17: 701 | Y17: 702 | Z17: 701 | AA17: 701 | AB17: 700 | AC17: 700 | AD17: 700 | AE17: 702 | AF17: 701 | AG17: 673 | AH17: 675 | AI17: 649 | AJ17: 648 | AK17: 648 | AL17: 673 | AM17: 675 | AN17: 700 | AO17: 700 | AP17: 699 | AQ17: 701 | AR17: 701 | AS17: 673 | AT17: 675
A18: 4375 | B18: 2.5 | D18: 5 | E18: 631 | F18: 742 | G18: 742 | H18: 740 | I18: 740 | J18: 740 | K18: 738 | L18: 738 | M18: 740 | N18: 712 | O18: 712 | P18: 710 | Q18: 736 | R18: 736 | S18: 734 | T18: 734 | U18: 734 | V18: 732 | W18: 734 | X18: 732 | Y18: 734 | Z18: 732 | AA18: 732 | AB18: 729 | AC18: 729 | AD18: 729 | AE18: 734 | AF18: 732 | AG18: 706 | AH18: 708 | AI18: 684 | AJ18: 682 | AK18: 682 | AL18: 706 | AM18: 708 | AN18: 729 | AO18: 729 | AP18: 727 | AQ18: 732 | AR18: 732 | AS18: 706 | AT18: 708
A19: 4900 | B19: 2.8 | C19: 7 | E19: 667 | F19: 779 | G19: 779 | H19: 776 | I19: 776 | J19: 776 | K19: 772 | L19: 772 | M19: 776 | N19: 748 | O19: 748 | P19: 745 | Q19: 769 | R19: 769 | S19: 765 | T19: 765 | U19: 765 | V19: 762 | W19: 765 | X19: 762 | Y19: 765 | Z19: 762 | AA19: 762 | AB19: 759 | AC19: 759 | AD19: 759 | AE19: 765 | AF19: 762 | AG19: 738 | AH19: 741 | AI19: 719 | AJ19: 716 | AK19: 716 | AL19: 738 | AM19: 741 | AN19: 759 | AO19: 759 | AP19: 756 | AQ19: 762 | AR19: 762 | AS19: 738 | AT19: 741
A20: 5250 | B20: 3 | D20: 6 | E20: 704 | F20: 815 | G20: 815 | H20: 810 | I20: 810 | J20: 810 | K20: 806 | L20: 806 | M20: 810 | N20: 783 | O20: 783 | P20: 779 | Q20: 802 | R20: 802 | S20: 798 | T20: 798 | U20: 798 | V20: 794 | W20: 798 | X20: 794 | Y20: 798 | Z20: 794 | AA20: 794 | AB20: 789 | AC20: 789 | AD20: 789 | AE20: 798 | AF20: 794 | AG20: 770 | AH20: 775 | AI20: 755 | AJ20: 751 | AK20: 751 | AL20: 770 | AM20: 775 | AN20: 789 | AO20: 789 | AP20: 785 | AQ20: 794 | AR20: 794 | AS20: 770 | AT20: 775
A21: 5600 | B21: 3.2 | C21: 8 | E21: 740 | F21: 851 | G21: 851 | H21: 846 | I21: 846 | J21: 846 | K21: 841 | L21: 841 | M21: 846 | N21: 819 | O21: 819 | P21: 812 | Q21: 835 | R21: 835 | S21: 830 | T21: 830 | U21: 830 | V21: 825 | W21: 830 | X21: 825 | Y21: 830 | Z21: 825 | AA21: 825 | AB21: 820 | AC21: 820 | AD21: 820 | AE21: 830 | AF21: 825 | AG21: 802 | AH21: 807 | AI21: 791 | AJ21: 785 | AK21: 785 | AL21: 802 | AM21: 807 | AN21: 820 | AO21: 820 | AP21: 814 | AQ21: 825 | AR21: 825 | AS21: 802 | AT21: 807
A22: 6125 | B22: 3.5 | D22: 7 | E22: 777 | F22: 888 | G22: 888 | H22: 881 | I22: 881 | J22: 881 | K22: 875 | L22: 875 | M22: 881 | N22: 853 | O22: 853 | P22: 847 | Q22: 869 | R22: 869 | S22: 863 | T22: 863 | U22: 863 | V22: 855 | W22: 863 | X22: 855 | Y22: 863 | Z22: 855 | AA22: 855 | AB22: 849 | AC22: 849 | AD22: 849 | AE22: 863 | AF22: 855 | AG22: 834 | AH22: 841 | AI22: 826 | AJ22: 820 | AK22: 820 | AL22: 834 | AM22: 841 | AN22: 849 | AO22: 849 | AP22: 843 | AQ22: 855 | AR22: 855 | AS22: 834 | AT22: 841
A23: 6300 | B23: 3.6 | C23: 9 | E23: 812 | F23: 924 | G23: 924 | H23: 917 | I23: 917 | J23: 917 | K23: 910 | L23: 910 | M23: 917 | N23: 889 | O23: 889 | P23: 881 | Q23: 902 | R23: 902 | S23: 894 | T23: 894 | U23: 894 | V23: 887 | W23: 894 | X23: 887 | Y23: 894 | Z23: 887 | AA23: 887 | AB23: 879 | AC23: 879 | AD23: 879 | AE23: 894 | AF23: 887 | AG23: 867 | AH23: 874 | AI23: 862 | AJ23: 853 | AK23: 853 | AL23: 867 | AM23: 874 | AN23: 879 | AO23: 879 | AP23: 872 | AQ23: 887 | AR23: 887 | AS23: 867 | AT23: 874
A24: 7000 | B24: 4 | C24: 10 | D24: 8 | E24: 849 | F24: 961 | G24: 961 | H24: 952 | I24: 952 | J24: 952 | K24: 943 | L24: 943 | M24: 952 | N24: 924 | O24: 924 | P24: 916 | Q24: 935 | R24: 935 | S24: 926 | T24: 926 | U24: 926 | V24: 918 | W24: 926 | X24: 918 | Y24: 926 | Z24: 918 | AA24: 918 | AB24: 910 | AC24: 910 | AD24: 910 | AE24: 926 | AF24: 918 | AG24: 898 | AH24: 908 | AI24: 896 | AJ24: 888 | AK24: 888 | AL24: 898 | AM24: 908 | AN24: 910 | AO24: 910 | AP24: 900 | AQ24: 918 | AR24: 918 | AS24: 898 | AT24: 908
A26: Transittijden:
A28: Dag van lading = Dag 0 | C28: Vertrek | G28: Transittijd in werkdagen | R28: Transittijd in werkdagen | AC28: Transittijd in werkdagen | AN28: Transittijd in werkdagen
A29: Groupage 1-5 pallets | C29: di,do,vrij | E29: 4/5 | F29: 4/5 | G29: 4/5 | H29: 4/5 | I29: 4/5 | J29: 4/5 | K29: 4/5 | L29: 4/5 | M29: 4/5 | N29: 4/5 | O29: 4/5 | P29: 4/5 | Q29: 4/5 | R29: 4/5 | S29: 4/5 | T29: 4/5 | U29: 4/5 | V29: 4/5 | W29: 4/5 | X29: 4/5 | Y29: 4/5 | Z29: 4/5 | AA29: 4/5 | AB29: 4/5 | AC29: 4/5 | AD29: 4/5 | AE29: 4/5 | AF29: 4/5 | AG29: 4/5 | AH29: 4/5 | AI29: 4/5 | AJ29: 4/5 | AK29: 4/5 | AL29: 4/5 | AM29: 4/5 | AN29: 4/5 | AO29: 4/5 | AP29: 4/5 | AQ29: 4/5 | AR29: 4/5 | AS29: 4/5 | AT29: 4/5
A30: Deelpartijen > 5 pallets | C30: di,wo,do,vrij | E30: 4/5 | F30: 4/5 | G30: 4/5 | H30: 4/5 | I30: 4/5 | J30: 4/5 | K30: 4/5 | L30: 4/5 | M30: 4/5 | N30: 4/5 | O30: 4/5 | P30: 4/5 | Q30: 4/5 | R30: 4/5 | S30: 4/5 | T30: 4/5 | U30: 4/5 | V30: 4/5 | W30: 4/5 | X30: 4/5 | Y30: 4/5 | Z30: 4/5 | AA30: 4/5 | AB30: 4/5 | AC30: 4/5 | AD30: 4/5 | AE30: 4/5 | AF30: 4/5 | AG30: 4/5 | AH30: 4/5 | AI30: 4/5 | AJ30: 4/5 | AK30: 4/5 | AL30: 4/5 | AM30: 4/5 | AN30: 4/5 | AO30: 4/5 | AP30: 4/5 | AQ30: 4/5 | AR30: 4/5 | AS30: 4/5 | AT30: 4/5
A31: Compleet ladingen | C31: di,wo,do,vrij | E31: 2/3 | F31: 2/3 | G31: 2/3 | H31: 2/3 | I31: 2/3 | J31: 2/3 | K31: 2/3 | L31: 2/3 | M31: 2/3 | N31: 2/3 | O31: 2/3 | P31: 2/3 | Q31: 2/3 | R31: 2/3 | S31: 2/3 | T31: 2/3 | U31: 2/3 | V31: 2/3 | W31: 2/3 | X31: 2/3 | Y31: 2/3 | Z31: 2/3 | AA31: 2/3 | AB31: 2/3 | AC31: 2/3 | AD31: 2/3 | AE31: 2/3 | AF31: 2/3 | AG31: 2/3 | AH31: 2/3 | AI31: 2/3 | AJ31: 2/3 | AK31: 2/3 | AL31: 2/3 | AM31: 2/3 | AN31: 2/3 | AO31: 2/3 | AP31: 2/3 | AQ31: 2/3 | AR31: 2/3 | AS31: 2/3 | AT31: 2/3
A33: Condities:
A34: * Tarief is niet geldig voor de eilanden

Sheet ES
A3: =Voorblad!A5 -> Team Freight Forwarding Logistics
A4: Export Spanje
A6: kg | B6: ldm | C6: euplt | D6: blkplt | E6: 1 | F6: 2 | G6: 3 | H6: 4 | I6: 5 | J6: 6 | K6: 8 | L6: 9 | M6: 10 | N6: 11 | O6: 12 | P6: 13 | Q6: 14 | R6: 15 | S6: 16 | T6: 17 | U6: 18 | V6: 19 | W6: 20 | X6: 21 | Y6: 22 | Z6: 23 | AA6: 24 | AB6: 25 | AC6: 26 | AD6: 27 | AE6: 28 | AF6: 29 | AG6: 30 | AH6: 31 | AI6: 32 | AJ6: 33 | AK6: 34 | AL6: 36 | AM6: 37 | AN6: 39 | AO6: 40 | AP6: 41 | AQ6: 42 | AR6: 43 | AS6: 44 | AT6: 45 | AU6: 46 | AV6: 47 | AW6: 48 | AX6: 49 | AY6: 50
A7: 300 | B7: 0.2 | C7: 0.5 | E7: 111 | F7: 132 | G7: 134 | H7: 136 | I7: 122 | J7: 132 | K7: 128 | L7: 116 | M7: 132 | N7: 136 | O7: 134 | P7: 126 | Q7: 132 | R7: 126 | S7: 126 | T7: 128 | U7: 132 | V7: 122 | W7: 111 | X7: 136 | Y7: 122 | Z7: 132 | AA7: 122 | AB7: 122 | AC7: 116 | AD7: 126 | AE7: 122 | AF7: 136 | AG7: 132 | AH7: 116 | AI7: 126 | AJ7: 122 | AK7: 116 | AL7: 126 | AM7: 122 | AN7: 116 | AO7: 122 | AP7: 136 | AQ7: 122 | AR7: 128 | AS7: 122 | AT7: 126 | AU7: 128 | AV7: 116 | AW7: 111 | AX7: 122 | AY7: 116
A8: 700 | B8: 0.4 | C8: 1 | E8: 150 | F8: 178 | G8: 181 | H8: 184 | I8: 162 | J8: 178 | K8: 175 | L8: 157 | M8: 178 | N8: 184 | O8: 181 | P8: 171 | Q8: 178 | R8: 171 | S8: 171 | T8: 175 | U8: 178 | V8: 162 | W8: 150 | X8: 184 | Y8: 162 | Z8: 178 | AA8: 162 | AB8: 162 | AC8: 157 | AD8: 171 | AE8: 162 | AF8: 184 | AG8: 178 | AH8: 157 | AI8: 171 | AJ8: 162 | AK8: 157 | AL8: 171 | AM8: 162 | AN8: 157 | AO8: 162 | AP8: 184 | AQ8: 162 | AR8: 175 | AS8: 162 | AT8: 171 | AU8: 175 | AV8: 157 | AW8: 150 | AX8: 162 | AY8: 157
A9: 875 | B9: 0.5 | D9: 1 | E9: 164 | F9: 192 | G9: 196 | H9: 198 | I9: 177 | J9: 192 | K9: 189 | L9: 171 | M9: 192 | N9: 198 | O9: 196 | P9: 185 | Q9: 192 | R9: 185 | S9: 185 | T9: 189 | U9: 192 | V9: 177 | W9: 164 | X9: 198 | Y9: 177 | Z9: 192 | AA9: 177 | AB9: 177 | AC9: 171 | AD9: 185 | AE9: 177 | AF9: 198 | AG9: 192 | AH9: 171 | AI9: 185 | AJ9: 177 | AK9: 171 | AL9: 185 | AM9: 177 | AN9: 171 | AO9: 177 | AP9: 198 | AQ9: 177 | AR9: 189 | AS9: 177 | AT9: 185 | AU9: 189 | AV9: 171 | AW9: 164 | AX9: 177 | AY9: 171
A10: 1050 | B10: 0.6 | E10: 196 | F10: 234 | G10: 239 | H10: 242 | I10: 214 | J10: 234 | K10: 224 | L10: 205 | M10: 234 | N10: 242 | O10: 239 | P10: 224 | Q10: 234 | R10: 224 | S10: 224 | T10: 224 | U10: 234 | V10: 214 | W10: 196 | X10: 242 | Y10: 214 | Z10: 234 | AA10: 214 | AB10: 214 | AC10: 205 | AD10: 224 | AE10: 214 | AF10: 242 | AG10: 234 | AH10: 205 | AI10: 224 | AJ10: 214 | AK10: 205 | AL10: 224 | AM10: 214 | AN10: 205 | AO10: 214 | AP10: 242 | AQ10: 214 | AR10: 229 | AS10: 214 | AT10: 224 | AU10: 229 | AV10: 205 | AW10: 196 | AX10: 214 | AY10: 205
A11: 1400 | B11: 0.8 | C11: 2 | E11: 258 | F11: 315 | G11: 322 | H11: 328 | I11: 285 | J11: 315 | K11: 291 | L11: 273 | M11: 315 | N11: 328 | O11: 322 | P11: 299 | Q11: 315 | R11: 299 | S11: 299 | T11: 291 | U11: 315 | V11: 285 | W11: 258 | X11: 328 | Y11: 285 | Z11: 315 | AA11: 285 | AB11: 285 | AC11: 273 | AD11: 299 | AE11: 285 | AF11: 328 | AG11: 315 | AH11: 273 | AI11: 299 | AJ11: 285 | AK11: 273 | AL11: 299 | AM11: 285 | AN11: 273 | AO11: 285 | AP11: 328 | AQ11: 285 | AR11: 308 | AS11: 285 | AT11: 299 | AU11: 308 | AV11: 273 | AW11: 258 | AX11: 285 | AY11: 273
A12: 1750 | B12: 1 | D12: 2 | E12: 283 | F12: 336 | G12: 346 | H12: 350 | I12: 309 | J12: 336 | K12: 331 | L12: 295 | M12: 336 | N12: 350 | O12: 346 | P12: 322 | Q12: 336 | R12: 322 | S12: 322 | T12: 331 | U12: 336 | V12: 309 | W12: 283 | X12: 350 | Y12: 309 | Z12: 336 | AA12: 309 | AB12: 309 | AC12: 295 | AD12: 322 | AE12: 309 | AF12: 350 | AG12: 336 | AH12: 295 | AI12: 322 | AJ12: 309 | AK12: 295 | AL12: 322 | AM12: 309 | AN12: 295 | AO12: 309 | AP12: 350 | AQ12: 309 | AR12: 331 | AS12: 309 | AT12: 322 | AU12: 331 | AV12: 295 | AW12: 283 | AX12: 309 | AY12: 295
A13: 2100 | B13: 1.2 | C13: 3 | E13: 366 | F13: 449 | G13: 459 | H13: 468 | I13: 405 | J13: 449 | K13: 407 | L13: 388 | M13: 449 | N13: 468 | O13: 459 | P13: 427 | Q13: 449 | R13: 427 | S13: 427 | T13: 407 | U13: 449 | V13: 405 | W13: 366 | X13: 468 | Y13: 405 | Z13: 449 | AA13: 405 | AB13: 405 | AC13: 388 | AD13: 427 | AE13: 405 | AF13: 468 | AG13: 449 | AH13: 388 | AI13: 427 | AJ13: 405 | AK13: 388 | AL13: 427 | AM13: 405 | AN13: 388 | AO13: 405 | AP13: 468 | AQ13: 405 | AR13: 437 | AS13: 405 | AT13: 427 | AU13: 437 | AV13: 388 | AW13: 366 | AX13: 405 | AY13: 388
A14: 2625 | B14: 1.5 | D14: 3 | E14: 401 | F14: 482 | G14: 495 | H14: 500 | I14: 439 | J14: 482 | K14: 455 | L14: 421 | M14: 482 | N14: 500 | O14: 495 | P14: 459 | Q14: 482 | R14: 459 | S14: 459 | T14: 455 | U14: 482 | V14: 439 | W14: 401 | X14: 500 | Y14: 439 | Z14: 482 | AA14: 439 | AB14: 439 | AC14: 421 | AD14: 459 | AE14: 439 | AF14: 500 | AG14: 482 | AH14: 421 | AI14: 459 | AJ14: 439 | AK14: 421 | AL14: 459 | AM14: 439 | AN14: 421 | AO14: 439 | AP14: 500 | AQ14: 439 | AR14: 472 | AS14: 439 | AT14: 459 | AU14: 472 | AV14: 421 | AW14: 401 | AX14: 439 | AY14: 421
A15: 2800 | B15: 1.6 | C15: 4 | E15: 458 | F15: 566 | G15: 579 | H15: 590 | I15: 509 | J15: 566 | K15: 459 | L15: 487 | M15: 566 | N15: 590 | O15: 579 | P15: 538 | Q15: 566 | R15: 538 | S15: 538 | T15: 459 | U15: 566 | V15: 509 | W15: 458 | X15: 590 | Y15: 509 | Z15: 566 | AA15: 509 | AB15: 509 | AC15: 487 | AD15: 538 | AE15: 509 | AF15: 590 | AG15: 566 | AH15: 487 | AI15: 538 | AJ15: 509 | AK15: 487 | AL15: 538 | AM15: 509 | AN15: 487 | AO15: 509 | AP15: 590 | AQ15: 509 | AR15: 551 | AS15: 509 | AT15: 538 | AU15: 551 | AV15: 487 | AW15: 458 | AX15: 509 | AY15: 487
A16: 3500 | B16: 2 | C16: 5 | D16: 4 | E16: 530 | F16: 650 | G16: 667 | H16: 677 | I16: 588 | J16: 650 | K16: 518 | L16: 563 | M16: 650 | N16: 677 | O16: 667 | P16: 618 | Q16: 650 | R16: 618 | S16: 618 | T16: 518 | U16: 650 | V16: 588 | W16: 530 | X16: 677 | Y16: 588 | Z16: 650 | AA16: 588 | AB16: 588 | AC16: 563 | AD16: 618 | AE16: 588 | AF16: 677 | AG16: 650 | AH16: 563 | AI16: 618 | AJ16: 588 | AK16: 563 | AL16: 618 | AM16: 588 | AN16: 563 | AO16: 588 | AP16: 677 | AQ16: 588 | AR16: 636 | AS16: 588 | AT16: 618 | AU16: 636 | AV16: 563 | AW16: 530 | AX16: 588 | AY16: 563
A17: 4200 | B17: 2.4 | C17: 6 | E17: 556 | F17: 678 | G17: 704 | H17: 794 | I17: 661 | J17: 794 | K17: 611 | L17: 590 | M17: 794 | N17: 802 | O17: 698 | P17: 725 | Q17: 794 | R17: 794 | S17: 661 | T17: 611 | U17: 794 | V17: 661 | W17: 554 | X17: 802 | Y17: 615 | Z17: 794 | AA17: 678 | AB17: 615 | AC17: 590 | AD17: 725 | AE17: 633 | AF17: 794 | AG17: 725 | AH17: 589 | AI17: 751 | AJ17: 678 | AK17: 661 | AL17: 751 | AM17: 678 | AN17: 661 | AO17: 661 | AP17: 802 | AQ17: 661 | AR17: 663 | AS17: 661 | AT17: 661 | AU17: 686 | AV17: 661 | AW17: 574 | AX17: 678 | AY17: 590
A18: 4375 | B18: 2.5 | D18: 5 | E18: 568 | F18: 696 | G18: 722 | H18: 817 | I18: 681 | J18: 817 | K18: 618 | L18: 603 | M18: 817 | N18: 851 | O18: 708 | P18: 743 | Q18: 817 | R18: 817 | S18: 681 | T18: 618 | U18: 817 | V18: 681 | W18: 565 | X18: 851 | Y18: 624 | Z18: 817 | AA18: 696 | AB18: 624 | AC18: 603 | AD18: 743 | AE18: 643 | AF18: 817 | AG18: 743 | AH18: 600 | AI18: 817 | AJ18: 696 | AK18: 681 | AL18: 817 | AM18: 696 | AN18: 681 | AO18: 681 | AP18: 851 | AQ18: 681 | AR18: 669 | AS18: 681 | AT18: 681 | AU18: 701 | AV18: 681 | AW18: 588 | AX18: 696 | AY18: 603
A19: 4900 | B19: 2.8 | C19: 7 | E19: 579 | F19: 739 | G19: 739 | H19: 868 | I19: 718 | J19: 868 | K19: 660 | L19: 616 | M19: 868 | N19: 908 | O19: 718 | P19: 794 | Q19: 868 | R19: 868 | S19: 718 | T19: 660 | U19: 868 | V19: 718 | W19: 574 | X19: 908 | Y19: 635 | Z19: 868 | AA19: 739 | AB19: 635 | AC19: 616 | AD19: 794 | AE19: 661 | AF19: 868 | AG19: 794 | AH19: 611 | AI19: 868 | AJ19: 739 | AK19: 718 | AL19: 868 | AM19: 739 | AN19: 718 | AO19: 718 | AP19: 908 | AQ19: 718 | AR19: 678 | AS19: 718 | AT19: 718 | AU19: 718 | AV19: 718 | AW19: 602 | AX19: 739 | AY19: 616
A20: 5250 | B20: 3 | D20: 6 | E20: 613 | F20: 772 | G20: 772 | H20: 904 | I20: 752 | J20: 904 | K20: 692 | L20: 627 | M20: 904 | N20: 949 | O20: 752 | P20: 831 | Q20: 904 | R20: 904 | S20: 752 | T20: 692 | U20: 904 | V20: 752 | W20: 609 | X20: 949 | Y20: 645 | Z20: 904 | AA20: 772 | AB20: 645 | AC20: 627 | AD20: 831 | AE20: 689 | AF20: 904 | AG20: 831 | AH20: 622 | AI20: 904 | AJ20: 772 | AK20: 752 | AL20: 904 | AM20: 772 | AN20: 752 | AO20: 752 | AP20: 949 | AQ20: 752 | AR20: 685 | AS20: 752 | AT20: 752 | AU20: 752 | AV20: 752 | AW20: 627 | AX20: 772 | AY20: 627
A21: 5600 | B21: 3.2 | C21: 8 | E21: 633 | F21: 800 | G21: 800 | H21: 939 | I21: 778 | J21: 939 | K21: 706 | L21: 656 | M21: 939 | N21: 988 | O21: 778 | P21: 865 | Q21: 939 | R21: 939 | S21: 778 | T21: 706 | U21: 939 | V21: 778 | W21: 627 | X21: 988 | Y21: 656 | Z21: 939 | AA21: 800 | AB21: 656 | AC21: 656 | AD21: 865 | AE21: 721 | AF21: 939 | AG21: 865 | AH21: 633 | AI21: 939 | AJ21: 800 | AK21: 778 | AL21: 939 | AM21: 800 | AN21: 778 | AO21: 778 | AP21: 988 | AQ21: 778 | AR21: 693 | AS21: 778 | AT21: 778 | AU21: 778 | AV21: 778 | AW21: 656 | AX21: 800 | AY21: 656
A22: 6125 | B22: 3.5 | D22: 7 | E22: 673 | F22: 848 | G22: 848 | H22: 993 | I22: 825 | J22: 993 | K22: 715 | L22: 694 | M22: 993 | N22: 1049 | O22: 825 | P22: 919 | Q22: 993 | R22: 993 | S22: 825 | T22: 715 | U22: 993 | V22: 825 | W22: 670 | X22: 1049 | Y22: 694 | Z22: 993 | AA22: 848 | AB22: 694 | AC22: 694 | AD22: 919 | AE22: 766 | AF22: 993 | AG22: 919 | AH22: 673 | AI22: 993 | AJ22: 848 | AK22: 825 | AL22: 993 | AM22: 848 | AN22: 825 | AO22: 825 | AP22: 1049 | AQ22: 825 | AR22: 701 | AS22: 825 | AT22: 825 | AU22: 825 | AV22: 825 | AW22: 694 | AX22: 848 | AY22: 694
A23: 6300 | B23: 3.6 | C23: 9 | E23: 685 | F23: 862 | G23: 862 | H23: 1009 | I23: 836 | J23: 1009 | K23: 726 | L23: 708 | M23: 1009 | N23: 1066 | O23: 836 | P23: 936 | Q23: 1009 | R23: 1009 | S23: 836 | T23: 726 | U23: 1009 | V23: 836 | W23: 682 | X23: 1066 | Y23: 708 | Z23: 1009 | AA23: 862 | AB23: 708 | AC23: 708 | AD23: 936 | AE23: 783 | AF23: 1009 | AG23: 936 | AH23: 685 | AI23: 1009 | AJ23: 862 | AK23: 836 | AL23: 1009 | AM23: 862 | AN23: 836 | AO23: 836 | AP23: 1066 | AQ23: 836 | AR23: 708 | AS23: 836 | AT23: 836 | AU23: 836 | AV23: 836 | AW23: 708 | AX23: 862 | AY23: 708
A24: 7000 | B24: 4 | C24: 10 | D24: 8 | E24: 738 | F24: 922 | G24: 922 | H24: 1081 | I24: 896 | J24: 1081 | K24: 736 | L24: 762 | M24: 1081 | N24: 1145 | O24: 896 | P24: 1006 | Q24: 1081 | R24: 1081 | S24: 896 | T24: 736 | U24: 1081 | V24: 896 | W24: 736 | X24: 1145 | Y24: 762 | Z24: 1081 | AA24: 922 | AB24: 762 | AC24: 762 | AD24: 1006 | AE24: 845 | AF24: 1081 | AG24: 1006 | AH24: 738 | AI24: 1081 | AJ24: 922 | AK24: 896 | AL24: 1081 | AM24: 922 | AN24: 896 | AO24: 896 | AP24: 1145 | AQ24: 896 | AR24: 762 | AS24: 896 | AT24: 896 | AU24: 896 | AV24: 896 | AW24: 762 | AX24: 922 | AY24: 762
A26: Transittijden:
A28: Dag van lading = Dag 0 | C28: Vertrek | G28: Transittijd in werkdagen | T28: Transittijd in werkdagen | AG28: Transittijd in werkdagen | AT28: Transittijd in werkdagen
A29: Groupage 1-5 pallets | C29: ma,di,wo,do,vrij | E29: 3/4 | F29: 4/5 | G29: 4/5 | H29: 4/5 | I29: 4/5 | J29: 4/5 | K29: 3/4 | L29: 4/5 | M29: 4/5 | N29: 4/5 | O29: 4/5 | P29: 4/5 | Q29: 4/5 | R29: 4/5 | S29: 4/5 | T29: 4/5 | U29: 4/5 | V29: 4/5 | W29: 3/4 | X29: 4/5 | Y29: 4/5 | Z29: 4/5 | AA29: 4/5 | AB29: 4/5 | AC29: 4/5 | AD29: 4/5 | AE29: 3/4 | AF29: 4/5 | AG29: 4/5 | AH29: 3/4 | AI29: 4/5 | AJ29: 4/5 | AK29: 4/5 | AL29: 4/5 | AM29: 4/5 | AN29: 4/5 | AO29: 4/5 | AP29: 4/5 | AQ29: 4/5 | AR29: 4/5 | AS29: 4/5 | AT29: 4/5 | AU29: 4/5 | AV29: 4/5 | AW29: 3/4 | AX29: 4/5 | AY29: 4/5
A30: Deelpartijen > 5 pallets | C30: ma,di,wo,do,vrij | E30: 2/3 | F30: 4 | G30: 4 | H30: 4 | I30: 3/4 | J30: 4 | K30: 2/3 | L30: 3/4 | M30: 4 | N30: 4 | O30: 3/4 | P30: 4 | Q30: 4 | R30: 4 | S30: 4 | T30: 3/4 | U30: 4 | V30: 3/4 | W30: 2/3 | X30: 4 | Y30: 3/4 | Z30: 4 | AA30: 3/4 | AB30: 3/4 | AC30: 3/4 | AD30: 4 | AE30: 2/3 | AF30: 4 | AG30: 4 | AH30: 2/3 | AI30: 4 | AJ30: 3/4 | AK30: 3/4 | AL30: 4 | AM30: 4 | AN30: 3/4 | AO30: 3/4 | AP30: 4 | AQ30: 3/4 | AR30: 3/4 | AS30: 3/4 | AT30: 4 | AU30: 4 | AV30: 3/4 | AW30: 2/3 | AX30: 3/4 | AY30: 3/4
A31: Compleet ladingen | C31: ma,di,wo,do,vrij | E31: 2 | F31: 3 | G31: 3 | H31: 3 | I31: 3 | J31: 3 | K31: 2 | L31: 3 | M31: 3 | N31: 3 | O31: 3 | P31: 3 | Q31: 3 | R31: 3 | S31: 3 | T31: 3 | U31: 3 | V31: 3 | W31: 2 | X31: 3 | Y31: 3 | Z31: 3 | AA31: 3 | AB31: 3 | AC31: 3 | AD31: 3 | AE31: 2 | AF31: 3 | AG31: 3 | AH31: 2 | AI31: 3 | AJ31: 3 | AK31: 3 | AL31: 3 | AM31: 3 | AN31: 3 | AO31: 3 | AP31: 3 | AQ31: 3 | AR31: 3 | AS31: 3 | AT31: 3 | AU31: 3 | AV31: 3 | AW31: 2 | AX31: 3 | AY31: 3
A33: Condities:
A34: * Leveringen 1 t/m 5 pallets met klepauto is inclusief, mits schriftelijk bevestigd. Vanaf 6 pallets kleplevering op aanvraag
A35: * Losadres moet bereikbaar zijn met een internationale trailer bij zendingen vanaf 6 pallets. Vanaf 6 pallets met mo-wagen (7 mtr) op aanvraag

Sheet FI
A3: =Voorblad!A5 -> Team Freight Forwarding Logistics
A4: Export Finland
A6: kg | B6: ldm | C6: euplt | D6: blkplt | E6: 00 | F6: 01 | G6: 02 | H6: 03 | I6: 04 | J6: 05 | K6: 06 | L6: 07 | M6: 08 | N6: 09 | O6: 10 | P6: 11 | Q6: 12 | R6: 13 | S6: 14 | T6: 15 | U6: 16 | V6: 17 | W6: 18 | X6: 19 | Y6: 20 | Z6: 21 | AA6: 23 | AB6: 24 | AC6: 25 | AD6: 26 | AE6: 27 | AF6: 28 | AG6: 29 | AH6: 30 | AI6: 31 | AJ6: 32 | AK6: 33 | AL6: 34 | AM6: 35 | AN6: 36 | AO6: 37 | AP6: 38 | AQ6: 39 | AR6: 40 | AS6: 41 | AT6: 42 | AU6: 43 | AV6: 44 | AW6: 45 | AX6: 46 | AY6: 47 | AZ6: 48 | BA6: 49 | BB6: 50 | BC6: 51 | BD6: 52 | BE6: 53 | BF6: 54 | BG6: 55 | BH6: 56 | BI6: 57 | BJ6: 58 | BK6: 59 | BL6: 60 | BM6: 61 | BN6: 62 | BO6: 63 | BP6: 64 | BQ6: 65 | BR6: 66 | BS6: 67 | BT6: 68 | BU6: 69 | BV6: 70 | BW6: 71 | BX6: 72 | BY6: 73 | BZ6: 74 | CA6: 75 | CB6: 76 | CC6: 77 | CD6: 78 | CE6: 79 | CF6: 80 | CG6: 81 | CH6: 82 | CI6: 83 | CJ6: 84 | CK6: 85 | CL6: 86 | CM6: 87 | CN6: 88 | CO6: 89 | CP6: 90 | CQ6: 91 | CR6: 92 | CS6: 93 | CT6: 94 | CU6: 95 | CV6: 96 | CW6: 97 | CX6: 98 | CY6: 99
A7: 300 | B7: 0.2 | C7: 0.5 | E7: 161 | F7: 161 | G7: 161 | H7: 161 | I7: 161 | J7: 161 | K7: 161 | L7: 161 | M7: 161 | N7: 161 | O7: 172 | P7: 172 | Q7: 172 | R7: 172 | S7: 183 | T7: 172 | U7: 172 | V7: 183 | W7: 183 | X7: 183 | Y7: 183 | Z7: 183 | AA7: 183 | AB7: 183 | AC7: 183 | AD7: 194 | AE7: 194 | AF7: 194 | AG7: 194 | AH7: 183 | AI7: 183 | AJ7: 183 | AK7: 194 | AL7: 194 | AM7: 194 | AN7: 194 | AO7: 194 | AP7: 194 | AQ7: 194 | AR7: 194 | AS7: 194 | AT7: 194 | AU7: 204 | AV7: 204 | AW7: 183 | AX7: 183 | AY7: 183 | AZ7: 183 | BA7: 183 | BB7: 194 | BC7: 194 | BD7: 194 | BE7: 194 | BF7: 194 | BG7: 194 | BH7: 194 | BI7: 204 | BJ7: 204 | BK7: 204 | BL7: 204 | BM7: 204 | BN7: 204 | BO7: 204 | BP7: 204 | BQ7: 204 | BR7: 204 | BS7: 204 | BT7: 204 | BU7: 204 | BV7: 204 | BW7: 204 | BX7: 204 | BY7: 222 | BZ7: 222 | CA7: 222 | CB7: 222 | CC7: 222 | CD7: 222 | CE7: 222 | CF7: 222 | CG7: 222 | CH7: 222 | CI7: 222 | CJ7: 222 | CK7: 222 | CL7: 222 | CM7: 222 | CN7: 222 | CO7: 222 | CP7: 222 | CQ7: 222 | CR7: 222 | CS7: 222 | CT7: 222 | CU7: 222 | CV7: 222 | CW7: 222 | CX7: 222 | CY7: 222
A8: 700 | B8: 0.4 | C8: 1 | E8: 223 | F8: 223 | G8: 223 | H8: 223 | I8: 223 | J8: 223 | K8: 223 | L8: 223 | M8: 223 | N8: 223 | O8: 228 | P8: 228 | Q8: 228 | R8: 228 | S8: 244 | T8: 228 | U8: 228 | V8: 244 | W8: 244 | X8: 244 | Y8: 244 | Z8: 244 | AA8: 244 | AB8: 244 | AC8: 244 | AD8: 249 | AE8: 249 | AF8: 249 | AG8: 249 | AH8: 244 | AI8: 244 | AJ8: 244 | AK8: 249 | AL8: 249 | AM8: 249 | AN8: 249 | AO8: 249 | AP8: 249 | AQ8: 249 | AR8: 249 | AS8: 249 | AT8: 249 | AU8: 283 | AV8: 283 | AW8: 244 | AX8: 244 | AY8: 244 | AZ8: 244 | BA8: 244 | BB8: 249 | BC8: 249 | BD8: 249 | BE8: 249 | BF8: 249 | BG8: 249 | BH8: 249 | BI8: 283 | BJ8: 283 | BK8: 283 | BL8: 283 | BM8: 283 | BN8: 283 | BO8: 283 | BP8: 283 | BQ8: 283 | BR8: 283 | BS8: 283 | BT8: 283 | BU8: 283 | BV8: 283 | BW8: 283 | BX8: 283 | BY8: 293 | BZ8: 293 | CA8: 293 | CB8: 293 | CC8: 293 | CD8: 293 | CE8: 293 | CF8: 293 | CG8: 293 | CH8: 293 | CI8: 293 | CJ8: 293 | CK8: 293 | CL8: 293 | CM8: 293 | CN8: 293 | CO8: 293 | CP8: 293 | CQ8: 293 | CR8: 293 | CS8: 293 | CT8: 293 | CU8: 293 | CV8: 293 | CW8: 293 | CX8: 293 | CY8: 293
A9: 875 | B9: 0.5 | D9: 1 | E9: 242 | F9: 242 | G9: 242 | H9: 242 | I9: 242 | J9: 242 | K9: 242 | L9: 242 | M9: 242 | N9: 242 | O9: 251 | P9: 251 | Q9: 251 | R9: 251 | S9: 267 | T9: 251 | U9: 251 | V9: 267 | W9: 267 | X9: 267 | Y9: 267 | Z9: 267 | AA9: 267 | AB9: 267 | AC9: 267 | AD9: 277 | AE9: 277 | AF9: 277 | AG9: 277 | AH9: 267 | AI9: 267 | AJ9: 267 | AK9: 277 | AL9: 277 | AM9: 277 | AN9: 277 | AO9: 277 | AP9: 277 | AQ9: 277 | AR9: 277 | AS9: 277 | AT9: 277 | AU9: 310 | AV9: 310 | AW9: 267 | AX9: 267 | AY9: 267 | AZ9: 267 | BA9: 267 | BB9: 277 | BC9: 277 | BD9: 277 | BE9: 277 | BF9: 277 | BG9: 277 | BH9: 277 | BI9: 310 | BJ9: 310 | BK9: 310 | BL9: 310 | BM9: 310 | BN9: 310 | BO9: 310 | BP9: 310 | BQ9: 310 | BR9: 310 | BS9: 310 | BT9: 310 | BU9: 310 | BV9: 310 | BW9: 310 | BX9: 310 | BY9: 321 | BZ9: 321 | CA9: 321 | CB9: 321 | CC9: 321 | CD9: 321 | CE9: 321 | CF9: 321 | CG9: 321 | CH9: 321 | CI9: 321 | CJ9: 321 | CK9: 321 | CL9: 321 | CM9: 321 | CN9: 321 | CO9: 321 | CP9: 321 | CQ9: 321 | CR9: 321 | CS9: 321 | CT9: 321 | CU9: 321 | CV9: 321 | CW9: 321 | CX9: 321 | CY9: 321
A10: 1050 | B10: 0.6 | E10: 275 | F10: 275 | G10: 275 | H10: 275 | I10: 275 | J10: 275 | K10: 275 | L10: 275 | M10: 275 | N10: 275 | O10: 297 | P10: 297 | Q10: 297 | R10: 297 | S10: 309 | T10: 297 | U10: 297 | V10: 309 | W10: 309 | X10: 309 | Y10: 309 | Z10: 309 | AA10: 309 | AB10: 309 | AC10: 309 | AD10: 335 | AE10: 335 | AF10: 335 | AG10: 335 | AH10: 309 | AI10: 309 | AJ10: 309 | AK10: 335 | AL10: 335 | AM10: 335 | AN10: 335 | AO10: 335 | AP10: 335 | AQ10: 335 | AR10: 335 | AS10: 335 | AT10: 335 | AU10: 363 | AV10: 363 | AW10: 309 | AX10: 309 | AY10: 309 | AZ10: 309 | BA10: 309 | BB10: 335 | BC10: 335 | BD10: 335 | BE10: 335 | BF10: 335 | BG10: 335 | BH10: 335 | BI10: 363 | BJ10: 363 | BK10: 363 | BL10: 363 | BM10: 363 | BN10: 363 | BO10: 363 | BP10: 363 | BQ10: 363 | BR10: 363 | BS10: 363 | BT10: 363 | BU10: 363 | BV10: 363 | BW10: 363 | BX10: 363 | BY10: 380 | BZ10: 380 | CA10: 380 | CB10: 380 | CC10: 380 | CD10: 380 | CE10: 380 | CF10: 380 | CG10: 380 | CH10: 380 | CI10: 380 | CJ10: 380 | CK10: 380 | CL10: 380 | CM10: 380 | CN10: 380 | CO10: 380 | CP10: 380 | CQ10: 380 | CR10: 380 | CS10: 380 | CT10: 380 | CU10: 380 | CV10: 380 | CW10: 380 | CX10: 380 | CY10: 380
A11: 1400 | B11: 0.8 | C11: 2 | E11: 337 | F11: 337 | G11: 337 | H11: 337 | I11: 337 | J11: 337 | K11: 337 | L11: 337 | M11: 337 | N11: 337 | O11: 360 | P11: 360 | Q11: 360 | R11: 360 | S11: 370 | T11: 360 | U11: 360 | V11: 370 | W11: 370 | X11: 370 | Y11: 370 | Z11: 370 | AA11: 370 | AB11: 370 | AC11: 370 | AD11: 398 | AE11: 398 | AF11: 398 | AG11: 398 | AH11: 370 | AI11: 370 | AJ11: 370 | AK11: 398 | AL11: 398 | AM11: 398 | AN11: 398 | AO11: 398 | AP11: 398 | AQ11: 398 | AR11: 398 | AS11: 398 | AT11: 398 | AU11: 425 | AV11: 425 | AW11: 370 | AX11: 370 | AY11: 370 | AZ11: 370 | BA11: 370 | BB11: 398 | BC11: 398 | BD11: 398 | BE11: 398 | BF11: 398 | BG11: 398 | BH11: 398 | BI11: 425 | BJ11: 425 | BK11: 425 | BL11: 425 | BM11: 425 | BN11: 425 | BO11: 425 | BP11: 425 | BQ11: 425 | BR11: 425 | BS11: 425 | BT11: 425 | BU11: 425 | BV11: 425 | BW11: 425 | BX11: 425 | BY11: 443 | BZ11: 443 | CA11: 443 | CB11: 443 | CC11: 443 | CD11: 443 | CE11: 443 | CF11: 443 | CG11: 443 | CH11: 443 | CI11: 443 | CJ11: 443 | CK11: 443 | CL11: 443 | CM11: 443 | CN11: 443 | CO11: 443 | CP11: 443 | CQ11: 443 | CR11: 443 | CS11: 443 | CT11: 443 | CU11: 443 | CV11: 443 | CW11: 443 | CX11: 443 | CY11: 443
A12: 1750 | B12: 1 | D12: 2 | E12: 374 | F12: 374 | G12: 374 | H12: 374 | I12: 374 | J12: 374 | K12: 374 | L12: 374 | M12: 374 | N12: 374 | O12: 404 | P12: 404 | Q12: 404 | R12: 404 | S12: 417 | T12: 404 | U12: 404 | V12: 417 | W12: 417 | X12: 417 | Y12: 417 | Z12: 417 | AA12: 417 | AB12: 417 | AC12: 417 | AD12: 448 | AE12: 448 | AF12: 448 | AG12: 448 | AH12: 417 | AI12: 417 | AJ12: 417 | AK12: 448 | AL12: 448 | AM12: 448 | AN12: 448 | AO12: 448 | AP12: 448 | AQ12: 448 | AR12: 448 | AS12: 448 | AT12: 448 | AU12: 478 | AV12: 478 | AW12: 417 | AX12: 417 | AY12: 417 | AZ12: 417 | BA12: 417 | BB12: 448 | BC12: 448 | BD12: 448 | BE12: 448 | BF12: 448 | BG12: 448 | BH12: 448 | BI12: 478 | BJ12: 478 | BK12: 478 | BL12: 478 | BM12: 478 | BN12: 478 | BO12: 478 | BP12: 478 | BQ12: 478 | BR12: 478 | BS12: 478 | BT12: 478 | BU12: 478 | BV12: 478 | BW12: 478 | BX12: 478 | BY12: 504 | BZ12: 504 | CA12: 504 | CB12: 504 | CC12: 504 | CD12: 504 | CE12: 504 | CF12: 504 | CG12: 504 | CH12: 504 | CI12: 504 | CJ12: 504 | CK12: 504 | CL12: 504 | CM12: 504 | CN12: 504 | CO12: 504 | CP12: 504 | CQ12: 504 | CR12: 504 | CS12: 504 | CT12: 504 | CU12: 504 | CV12: 504 | CW12: 504 | CX12: 504 | CY12: 504
A13: 2100 | B13: 1.2 | C13: 3 | E13: 438 | F13: 438 | G13: 438 | H13: 438 | I13: 438 | J13: 438 | K13: 438 | L13: 438 | M13: 438 | N13: 438 | O13: 477 | P13: 477 | Q13: 477 | R13: 477 | S13: 493 | T13: 477 | U13: 477 | V13: 493 | W13: 493 | X13: 493 | Y13: 493 | Z13: 493 | AA13: 493 | AB13: 493 | AC13: 493 | AD13: 526 | AE13: 526 | AF13: 526 | AG13: 526 | AH13: 493 | AI13: 493 | AJ13: 493 | AK13: 526 | AL13: 526 | AM13: 526 | AN13: 526 | AO13: 526 | AP13: 526 | AQ13: 526 | AR13: 526 | AS13: 526 | AT13: 526 | AU13: 557 | AV13: 557 | AW13: 493 | AX13: 493 | AY13: 493 | AZ13: 493 | BA13: 493 | BB13: 526 | BC13: 526 | BD13: 526 | BE13: 526 | BF13: 526 | BG13: 526 | BH13: 526 | BI13: 557 | BJ13: 557 | BK13: 557 | BL13: 557 | BM13: 557 | BN13: 557 | BO13: 557 | BP13: 557 | BQ13: 557 | BR13: 557 | BS13: 557 | BT13: 557 | BU13: 557 | BV13: 557 | BW13: 557 | BX13: 557 | BY13: 593 | BZ13: 593 | CA13: 593 | CB13: 593 | CC13: 593 | CD13: 593 | CE13: 593 | CF13: 593 | CG13: 593 | CH13: 593 | CI13: 593 | CJ13: 593 | CK13: 593 | CL13: 593 | CM13: 593 | CN13: 593 | CO13: 593 | CP13: 593 | CQ13: 593 | CR13: 593 | CS13: 593 | CT13: 593 | CU13: 593 | CV13: 593 | CW13: 593 | CX13: 593 | CY13: 593
A14: 2625 | B14: 1.5 | D14: 3 | E14: 518 | F14: 518 | G14: 518 | H14: 518 | I14: 518 | J14: 518 | K14: 518 | L14: 518 | M14: 518 | N14: 518 | O14: 551 | P14: 551 | Q14: 551 | R14: 551 | S14: 568 | T14: 551 | U14: 551 | V14: 568 | W14: 568 | X14: 568 | Y14: 568 | Z14: 568 | AA14: 568 | AB14: 568 | AC14: 568 | AD14: 600 | AE14: 600 | AF14: 600 | AG14: 600 | AH14: 568 | AI14: 568 | AJ14: 568 | AK14: 600 | AL14: 600 | AM14: 600 | AN14: 600 | AO14: 600 | AP14: 600 | AQ14: 600 | AR14: 600 | AS14: 600 | AT14: 600 | AU14: 638 | AV14: 638 | AW14: 568 | AX14: 568 | AY14: 568 | AZ14: 568 | BA14: 568 | BB14: 600 | BC14: 600 | BD14: 600 | BE14: 600 | BF14: 600 | BG14: 600 | BH14: 600 | BI14: 638 | BJ14: 638 | BK14: 638 | BL14: 638 | BM14: 638 | BN14: 638 | BO14: 638 | BP14: 638 | BQ14: 638 | BR14: 638 | BS14: 638 | BT14: 638 | BU14: 638 | BV14: 638 | BW14: 638 | BX14: 638 | BY14: 694 | BZ14: 694 | CA14: 694 | CB14: 694 | CC14: 694 | CD14: 694 | CE14: 694 | CF14: 694 | CG14: 694 | CH14: 694 | CI14: 694 | CJ14: 694 | CK14: 694 | CL14: 694 | CM14: 694 | CN14: 694 | CO14: 694 | CP14: 694 | CQ14: 694 | CR14: 694 | CS14: 694 | CT14: 694 | CU14: 694 | CV14: 694 | CW14: 694 | CX14: 694 | CY14: 694
A15: 2800 | B15: 1.6 | C15: 4 | E15: 571 | F15: 571 | G15: 571 | H15: 571 | I15: 571 | J15: 571 | K15: 571 | L15: 571 | M15: 571 | N15: 571 | O15: 605 | P15: 605 | Q15: 605 | R15: 605 | S15: 620 | T15: 605 | U15: 605 | V15: 620 | W15: 620 | X15: 620 | Y15: 620 | Z15: 620 | AA15: 620 | AB15: 620 | AC15: 620 | AD15: 654 | AE15: 654 | AF15: 654 | AG15: 654 | AH15: 620 | AI15: 620 | AJ15: 620 | AK15: 654 | AL15: 654 | AM15: 654 | AN15: 654 | AO15: 654 | AP15: 654 | AQ15: 654 | AR15: 654 | AS15: 654 | AT15: 654 | AU15: 692 | AV15: 692 | AW15: 620 | AX15: 620 | AY15: 620 | AZ15: 620 | BA15: 620 | BB15: 654 | BC15: 654 | BD15: 654 | BE15: 654 | BF15: 654 | BG15: 654 | BH15: 654 | BI15: 692 | BJ15: 692 | BK15: 692 | BL15: 692 | BM15: 692 | BN15: 692 | BO15: 692 | BP15: 692 | BQ15: 692 | BR15: 692 | BS15: 692 | BT15: 692 | BU15: 692 | BV15: 692 | BW15: 692 | BX15: 692 | BY15: 754 | BZ15: 754 | CA15: 754 | CB15: 754 | CC15: 754 | CD15: 754 | CE15: 754 | CF15: 754 | CG15: 754 | CH15: 754 | CI15: 754 | CJ15: 754 | CK15: 754 | CL15: 754 | CM15: 754 | CN15: 754 | CO15: 754 | CP15: 754 | CQ15: 754 | CR15: 754 | CS15: 754 | CT15: 754 | CU15: 754 | CV15: 754 | CW15: 754 | CX15: 754 | CY15: 754
A16: 3500 | B16: 2 | C16: 5 | D16: 4 | E16: 671 | F16: 671 | G16: 671 | H16: 671 | I16: 671 | J16: 671 | K16: 671 | L16: 671 | M16: 671 | N16: 671 | O16: 694 | P16: 694 | Q16: 694 | R16: 694 | S16: 738 | T16: 694 | U16: 694 | V16: 738 | W16: 738 | X16: 738 | Y16: 738 | Z16: 738 | AA16: 738 | AB16: 738 | AC16: 738 | AD16: 759 | AE16: 759 | AF16: 759 | AG16: 759 | AH16: 738 | AI16: 738 | AJ16: 738 | AK16: 759 | AL16: 759 | AM16: 759 | AN16: 759 | AO16: 759 | AP16: 759 | AQ16: 759 | AR16: 759 | AS16: 759 | AT16: 759 | AU16: 803 | AV16: 803 | AW16: 738 | AX16: 738 | AY16: 738 | AZ16: 738 | BA16: 738 | BB16: 759 | BC16: 759 | BD16: 759 | BE16: 759 | BF16: 759 | BG16: 759 | BH16: 759 | BI16: 803 | BJ16: 803 | BK16: 803 | BL16: 803 | BM16: 803 | BN16: 803 | BO16: 803 | BP16: 803 | BQ16: 803 | BR16: 803 | BS16: 803 | BT16: 803 | BU16: 803 | BV16: 803 | BW16: 803 | BX16: 803 | BY16: 893 | BZ16: 893 | CA16: 893 | CB16: 893 | CC16: 893 | CD16: 893 | CE16: 893 | CF16: 893 | CG16: 893 | CH16: 893 | CI16: 893 | CJ16: 893 | CK16: 893 | CL16: 893 | CM16: 893 | CN16: 893 | CO16: 893 | CP16: 893 | CQ16: 893 | CR16: 893 | CS16: 893 | CT16: 893 | CU16: 893 | CV16: 893 | CW16: 893 | CX16: 893 | CY16: 893
A17: 4200 | B17: 2.4 | C17: 6 | E17: 743 | F17: 743 | G17: 743 | H17: 743 | I17: 743 | J17: 743 | K17: 743 | L17: 743 | M17: 743 | N17: 743 | O17: 776 | P17: 776 | Q17: 776 | R17: 776 | S17: 818 | T17: 776 | U17: 776 | V17: 818 | W17: 818 | X17: 818 | Y17: 818 | Z17: 818 | AA17: 818 | AB17: 818 | AC17: 818 | AD17: 827 | AE17: 827 | AF17: 827 | AG17: 827 | AH17: 818 | AI17: 818 | AJ17: 818 | AK17: 827 | AL17: 827 | AM17: 827 | AN17: 827 | AO17: 827 | AP17: 827 | AQ17: 827 | AR17: 827 | AS17: 827 | AT17: 827 | AU17: 890 | AV17: 890 | AW17: 818 | AX17: 818 | AY17: 818 | AZ17: 818 | BA17: 818 | BB17: 827 | BC17: 827 | BD17: 827 | BE17: 827 | BF17: 827 | BG17: 827 | BH17: 827 | BI17: 890 | BJ17: 890 | BK17: 890 | BL17: 890 | BM17: 890 | BN17: 890 | BO17: 890 | BP17: 890 | BQ17: 890 | BR17: 890 | BS17: 890 | BT17: 890 | BU17: 890 | BV17: 890 | BW17: 890 | BX17: 890 | BY17: 993 | BZ17: 993 | CA17: 993 | CB17: 993 | CC17: 993 | CD17: 993 | CE17: 993 | CF17: 993 | CG17: 993 | CH17: 993 | CI17: 993 | CJ17: 993 | CK17: 993 | CL17: 993 | CM17: 993 | CN17: 993 | CO17: 993 | CP17: 993 | CQ17: 993 | CR17: 993 | CS17: 993 | CT17: 993 | CU17: 993 | CV17: 993 | CW17: 993 | CX17: 993 | CY17: 993
A18: 4375 | B18: 2.5 | D18: 5 | E18: 769 | F18: 769 | G18: 769 | H18: 769 | I18: 769 | J18: 769 | K18: 769 | L18: 769 | M18: 769 | N18: 769 | O18: 798 | P18: 798 | Q18: 798 | R18: 798 | S18: 840 | T18: 798 | U18: 798 | V18: 840 | W18: 840 | X18: 840 | Y18: 840 | Z18: 840 | AA18: 840 | AB18: 840 | AC18: 840 | AD18: 853 | AE18: 853 | AF18: 853 | AG18: 853 | AH18: 840 | AI18: 840 | AJ18: 840 | AK18: 853 | AL18: 853 | AM18: 853 | AN18: 853 | AO18: 853 | AP18: 853 | AQ18: 853 | AR18: 853 | AS18: 853 | AT18: 853 | AU18: 913 | AV18: 913 | AW18: 840 | AX18: 840 | AY18: 840 | AZ18: 840 | BA18: 840 | BB18: 853 | BC18: 853 | BD18: 853 | BE18: 853 | BF18: 853 | BG18: 853 | BH18: 853 | BI18: 913 | BJ18: 913 | BK18: 913 | BL18: 913 | BM18: 913 | BN18: 913 | BO18: 913 | BP18: 913 | BQ18: 913 | BR18: 913 | BS18: 913 | BT18: 913 | BU18: 913 | BV18: 913 | BW18: 913 | BX18: 913 | BY18: 1025 | BZ18: 1025 | CA18: 1025 | CB18: 1025 | CC18: 1025 | CD18: 1025 | CE18: 1025 | CF18: 1025 | CG18: 1025 | CH18: 1025 | CI18: 1025 | CJ18: 1025 | CK18: 1025 | CL18: 1025 | CM18: 1025 | CN18: 1025 | CO18: 1025 | CP18: 1025 | CQ18: 1025 | CR18: 1025 | CS18: 1025 | CT18: 1025 | CU18: 1025 | CV18: 1025 | CW18: 1025 | CX18: 1025 | CY18: 1025
A19: 4900 | B19: 2.8 | C19: 7 | E19: 792 | F19: 792 | G19: 792 | H19: 792 | I19: 792 | J19: 792 | K19: 792 | L19: 792 | M19: 792 | N19: 792 | O19: 812 | P19: 812 | Q19: 812 | R19: 812 | S19: 854 | T19: 812 | U19: 812 | V19: 854 | W19: 854 | X19: 854 | Y19: 854 | Z19: 854 | AA19: 854 | AB19: 854 | AC19: 854 | AD19: 880 | AE19: 880 | AF19: 880 | AG19: 880 | AH19: 854 | AI19: 854 | AJ19: 854 | AK19: 880 | AL19: 880 | AM19: 880 | AN19: 880 | AO19: 880 | AP19: 880 | AQ19: 880 | AR19: 880 | AS19: 880 | AT19: 880 | AU19: 927 | AV19: 927 | AW19: 854 | AX19: 854 | AY19: 854 | AZ19: 854 | BA19: 854 | BB19: 880 | BC19: 880 | BD19: 880 | BE19: 880 | BF19: 880 | BG19: 880 | BH19: 880 | BI19: 927 | BJ19: 927 | BK19: 927 | BL19: 927 | BM19: 927 | BN19: 927 | BO19: 927 | BP19: 927 | BQ19: 927 | BR19: 927 | BS19: 927 | BT19: 927 | BU19: 927 | BV19: 927 | BW19: 927 | BX19: 927 | BY19: 1067 | BZ19: 1067 | CA19: 1067 | CB19: 1067 | CC19: 1067 | CD19: 1067 | CE19: 1067 | CF19: 1067 | CG19: 1067 | CH19: 1067 | CI19: 1067 | CJ19: 1067 | CK19: 1067 | CL19: 1067 | CM19: 1067 | CN19: 1067 | CO19: 1067 | CP19: 1067 | CQ19: 1067 | CR19: 1067 | CS19: 1067 | CT19: 1067 | CU19: 1067 | CV19: 1067 | CW19: 1067 | CX19: 1067 | CY19: 1067
A20: 5250 | B20: 3 | D20: 6 | E20: 832 | F20: 832 | G20: 832 | H20: 832 | I20: 832 | J20: 832 | K20: 832 | L20: 832 | M20: 832 | N20: 832 | O20: 864 | P20: 864 | Q20: 864 | R20: 864 | S20: 899 | T20: 864 | U20: 864 | V20: 899 | W20: 899 | X20: 899 | Y20: 899 | Z20: 899 | AA20: 899 | AB20: 899 | AC20: 899 | AD20: 923 | AE20: 923 | AF20: 923 | AG20: 923 | AH20: 899 | AI20: 899 | AJ20: 899 | AK20: 923 | AL20: 923 | AM20: 923 | AN20: 923 | AO20: 923 | AP20: 923 | AQ20: 923 | AR20: 923 | AS20: 923 | AT20: 923 | AU20: 979 | AV20: 979 | AW20: 899 | AX20: 899 | AY20: 899 | AZ20: 899 | BA20: 899 | BB20: 923 | BC20: 923 | BD20: 923 | BE20: 923 | BF20: 923 | BG20: 923 | BH20: 923 | BI20: 979 | BJ20: 979 | BK20: 979 | BL20: 979 | BM20: 979 | BN20: 979 | BO20: 979 | BP20: 979 | BQ20: 979 | BR20: 979 | BS20: 979 | BT20: 979 | BU20: 979 | BV20: 979 | BW20: 979 | BX20: 979 | BY20: 1132 | BZ20: 1132 | CA20: 1132 | CB20: 1132 | CC20: 1132 | CD20: 1132 | CE20: 1132 | CF20: 1132 | CG20: 1132 | CH20: 1132 | CI20: 1132 | CJ20: 1132 | CK20: 1132 | CL20: 1132 | CM20: 1132 | CN20: 1132 | CO20: 1132 | CP20: 1132 | CQ20: 1132 | CR20: 1132 | CS20: 1132 | CT20: 1132 | CU20: 1132 | CV20: 1132 | CW20: 1132 | CX20: 1132 | CY20: 1132
A21: 5600 | B21: 3.2 | C21: 8 | E21: 872 | F21: 872 | G21: 872 | H21: 872 | I21: 872 | J21: 872 | K21: 872 | L21: 872 | M21: 872 | N21: 872 | O21: 913 | P21: 913 | Q21: 913 | R21: 913 | S21: 946 | T21: 913 | U21: 913 | V21: 946 | W21: 946 | X21: 946 | Y21: 946 | Z21: 946 | AA21: 946 | AB21: 946 | AC21: 946 | AD21: 966 | AE21: 966 | AF21: 966 | AG21: 966 | AH21: 946 | AI21: 946 | AJ21: 946 | AK21: 966 | AL21: 966 | AM21: 966 | AN21: 966 | AO21: 966 | AP21: 966 | AQ21: 966 | AR21: 966 | AS21: 966 | AT21: 966 | AU21: 1029 | AV21: 1029 | AW21: 946 | AX21: 946 | AY21: 946 | AZ21: 946 | BA21: 946 | BB21: 966 | BC21: 966 | BD21: 966 | BE21: 966 | BF21: 966 | BG21: 966 | BH21: 966 | BI21: 1029 | BJ21: 1029 | BK21: 1029 | BL21: 1029 | BM21: 1029 | BN21: 1029 | BO21: 1029 | BP21: 1029 | BQ21: 1029 | BR21: 1029 | BS21: 1029 | BT21: 1029 | BU21: 1029 | BV21: 1029 | BW21: 1029 | BX21: 1029 | BY21: 1195 | BZ21: 1195 | CA21: 1195 | CB21: 1195 | CC21: 1195 | CD21: 1195 | CE21: 1195 | CF21: 1195 | CG21: 1195 | CH21: 1195 | CI21: 1195 | CJ21: 1195 | CK21: 1195 | CL21: 1195 | CM21: 1195 | CN21: 1195 | CO21: 1195 | CP21: 1195 | CQ21: 1195 | CR21: 1195 | CS21: 1195 | CT21: 1195 | CU21: 1195 | CV21: 1195 | CW21: 1195 | CX21: 1195 | CY21: 1195
A22: 6125 | B22: 3.5 | D22: 7 | E22: 948 | F22: 948 | G22: 948 | H22: 948 | I22: 948 | J22: 948 | K22: 948 | L22: 948 | M22: 948 | N22: 948 | O22: 973 | P22: 973 | Q22: 973 | R22: 973 | S22: 1029 | T22: 973 | U22: 973 | V22: 1029 | W22: 1029 | X22: 1029 | Y22: 1029 | Z22: 1029 | AA22: 1029 | AB22: 1029 | AC22: 1029 | AD22: 1051 | AE22: 1051 | AF22: 1051 | AG22: 1051 | AH22: 1029 | AI22: 1029 | AJ22: 1029 | AK22: 1051 | AL22: 1051 | AM22: 1051 | AN22: 1051 | AO22: 1051 | AP22: 1051 | AQ22: 1051 | AR22: 1051 | AS22: 1051 | AT22: 1051 | AU22: 1122 | AV22: 1122 | AW22: 1029 | AX22: 1029 | AY22: 1029 | AZ22: 1029 | BA22: 1029 | BB22: 1051 | BC22: 1051 | BD22: 1051 | BE22: 1051 | BF22: 1051 | BG22: 1051 | BH22: 1051 | BI22: 1122 | BJ22: 1122 | BK22: 1122 | BL22: 1122 | BM22: 1122 | BN22: 1122 | BO22: 1122 | BP22: 1122 | BQ22: 1122 | BR22: 1122 | BS22: 1122 | BT22: 1122 | BU22: 1122 | BV22: 1122 | BW22: 1122 | BX22: 1122 | BY22: 1292 | BZ22: 1292 | CA22: 1292 | CB22: 1292 | CC22: 1292 | CD22: 1292 | CE22: 1292 | CF22: 1292 | CG22: 1292 | CH22: 1292 | CI22: 1292 | CJ22: 1292 | CK22: 1292 | CL22: 1292 | CM22: 1292 | CN22: 1292 | CO22: 1292 | CP22: 1292 | CQ22: 1292 | CR22: 1292 | CS22: 1292 | CT22: 1292 | CU22: 1292 | CV22: 1292 | CW22: 1292 | CX22: 1292 | CY22: 1292
A23: 6300 | B23: 3.6 | C23: 9 | E23: 973 | F23: 973 | G23: 973 | H23: 973 | I23: 973 | J23: 973 | K23: 973 | L23: 973 | M23: 973 | N23: 973 | O23: 994 | P23: 994 | Q23: 994 | R23: 994 | S23: 1057 | T23: 994 | U23: 994 | V23: 1057 | W23: 1057 | X23: 1057 | Y23: 1057 | Z23: 1057 | AA23: 1057 | AB23: 1057 | AC23: 1057 | AD23: 1079 | AE23: 1079 | AF23: 1079 | AG23: 1079 | AH23: 1057 | AI23: 1057 | AJ23: 1057 | AK23: 1079 | AL23: 1079 | AM23: 1079 | AN23: 1079 | AO23: 1079 | AP23: 1079 | AQ23: 1079 | AR23: 1079 | AS23: 1079 | AT23: 1079 | AU23: 1151 | AV23: 1151 | AW23: 1057 | AX23: 1057 | AY23: 1057 | AZ23: 1057 | BA23: 1057 | BB23: 1079 | BC23: 1079 | BD23: 1079 | BE23: 1079 | BF23: 1079 | BG23: 1079 | BH23: 1079 | BI23: 1151 | BJ23: 1151 | BK23: 1151 | BL23: 1151 | BM23: 1151 | BN23: 1151 | BO23: 1151 | BP23: 1151 | BQ23: 1151 | BR23: 1151 | BS23: 1151 | BT23: 1151 | BU23: 1151 | BV23: 1151 | BW23: 1151 | BX23: 1151 | BY23: 1323 | BZ23: 1323 | CA23: 1323 | CB23: 1323 | CC23: 1323 | CD23: 1323 | CE23: 1323 | CF23: 1323 | CG23: 1323 | CH23: 1323 | CI23: 1323 | CJ23: 1323 | CK23: 1323 | CL23: 1323 | CM23: 1323 | CN23: 1323 | CO23: 1323 | CP23: 1323 | CQ23: 1323 | CR23: 1323 | CS23: 1323 | CT23: 1323 | CU23: 1323 | CV23: 1323 | CW23: 1323 | CX23: 1323 | CY23: 1323
A24: 7000 | B24: 4 | C24: 10 | D24: 8 | E24: 1085 | F24: 1085 | G24: 1085 | H24: 1085 | I24: 1085 | J24: 1085 | K24: 1085 | L24: 1085 | M24: 1085 | N24: 1085 | O24: 1106 | P24: 1106 | Q24: 1106 | R24: 1106 | S24: 1137 | T24: 1106 | U24: 1106 | V24: 1137 | W24: 1137 | X24: 1137 | Y24: 1137 | Z24: 1137 | AA24: 1137 | AB24: 1137 | AC24: 1137 | AD24: 1179 | AE24: 1179 | AF24: 1179 | AG24: 1179 | AH24: 1137 | AI24: 1137 | AJ24: 1137 | AK24: 1179 | AL24: 1179 | AM24: 1179 | AN24: 1179 | AO24: 1179 | AP24: 1179 | AQ24: 1179 | AR24: 1179 | AS24: 1179 | AT24: 1179 | AU24: 1242 | AV24: 1242 | AW24: 1137 | AX24: 1137 | AY24: 1137 | AZ24: 1137 | BA24: 1137 | BB24: 1179 | BC24: 1179 | BD24: 1179 | BE24: 1179 | BF24: 1179 | BG24: 1179 | BH24: 1179 | BI24: 1242 | BJ24: 1242 | BK24: 1242 | BL24: 1242 | BM24: 1242 | BN24: 1242 | BO24: 1242 | BP24: 1242 | BQ24: 1242 | BR24: 1242 | BS24: 1242 | BT24: 1242 | BU24: 1242 | BV24: 1242 | BW24: 1242 | BX24: 1242 | BY24: 1451 | BZ24: 1451 | CA24: 1451 | CB24: 1451 | CC24: 1451 | CD24: 1451 | CE24: 1451 | CF24: 1451 | CG24: 1451 | CH24: 1451 | CI24: 1451 | CJ24: 1451 | CK24: 1451 | CL24: 1451 | CM24: 1451 | CN24: 1451 | CO24: 1451 | CP24: 1451 | CQ24: 1451 | CR24: 1451 | CS24: 1451 | CT24: 1451 | CU24: 1451 | CV24: 1451 | CW24: 1451 | CX24: 1451 | CY24: 1451
A26: Transittijden:
A28: Dag van lading = Dag 0 | C28: Vertrek | G28: Transittijd in werkdagen | T28: Transittijd in werkdagen | AF28: Transittijd in werkdagen | AS28: Transittijd in werkdagen | BF28: Transittijd in werkdagen | BS28: Transittijd in werkdagen | BT28: Transittijd in werkdagen | BU28: Transittijd in werkdagen | CH28: Transittijd in werkdagen | CU28: Transittijd in werkdagen
A29: Groupage 1-5 pallets | C29: di,vrij | E29: 5 | F29: 5 | G29: 5 | H29: 5 | I29: 5 | J29: 5 | K29: 5 | L29: 5 | M29: 5 | N29: 5 | O29: 6 | P29: 6 | Q29: 6 | R29: 6 | S29: 6 | T29: 6 | U29: 6 | V29: 6 | W29: 6 | X29: 6 | Y29: 6 | Z29: 6 | AA29: 6 | AB29: 6 | AC29: 6 | AD29: 6 | AE29: 6 | AF29: 6 | AG29: 6 | AH29: 6 | AI29: 6 | AJ29: 6 | AK29: 6 | AL29: 6 | AM29: 6 | AN29: 6 | AO29: 6 | AP29: 6 | AQ29: 6 | AR29: 6 | AS29: 7 | AT29: 7 | AU29: 7 | AV29: 7 | AW29: 6 | AX29: 6 | AY29: 6 | AZ29: 6 | BA29: 6 | BB29: 6 | BC29: 6 | BD29: 6 | BE29: 6 | BF29: 6 | BG29: 6 | BH29: 6 | BI29: 7 | BJ29: 7 | BK29: 7 | BL29: 7 | BM29: 7 | BN29: 7 | BO29: 7 | BP29: 7 | BQ29: 7 | BR29: 7 | BS29: 7 | BT29: 7 | BU29: 7 | BV29: 7 | BW29: 7 | BX29: 7 | BY29: 7 | BZ29: 7 | CA29: 7 | CB29: 7 | CC29: 7 | CD29: 7 | CE29: 7 | CF29: 7 | CG29: 7 | CH29: 7 | CI29: 7 | CJ29: 7 | CK29: 7 | CL29: 7 | CM29: 7 | CN29: 7 | CO29: 7 | CP29: 7 | CQ29: 7 | CR29: 7 | CS29: 7 | CT29: 7 | CU29: 7 | CV29: 7 | CW29: 7 | CX29: OR | CY29: OR
A30: Deelpartijen > 5 pallets | C30: di,vrij | E30: 5 | F30: 5 | G30: 5 | H30: 5 | I30: 5 | J30: 5 | K30: 5 | L30: 5 | M30: 5 | N30: 5 | O30: 6 | P30: 6 | Q30: 6 | R30: 6 | S30: 6 | T30: 6 | U30: 6 | V30: 6 | W30: 6 | X30: 6 | Y30: 6 | Z30: 6 | AA30: 6 | AB30: 6 | AC30: 6 | AD30: 6 | AE30: 6 | AF30: 6 | AG30: 6 | AH30: 6 | AI30: 6 | AJ30: 6 | AK30: 6 | AL30: 6 | AM30: 6 | AN30: 6 | AO30: 6 | AP30: 6 | AQ30: 6 | AR30: 6 | AS30: 6/7 | AT30: 6/7 | AU30: 6/7 | AV30: 6/7 | AW30: 6 | AX30: 6 | AY30: 6 | AZ30: 6 | BA30: 6 | BB30: 6 | BC30: 6 | BD30: 6 | BE30: 6 | BF30: 6 | BG30: 6 | BH30: 6 | BI30: 6/7 | BJ30: 6/7 | BK30: 6/7 | BL30: 6/7 | BM30: 6/7 | BN30: 6/7 | BO30: 6/7 | BP30: 6/7 | BQ30: 6/7 | BR30: 6/7 | BS30: 6/7 | BT30: 6/7 | BU30: 6/7 | BV30: 6/7 | BW30: 6/7 | BX30: 6/7 | BY30: 6/7 | BZ30: 6/7 | CA30: 6/7 | CB30: 6/7 | CC30: 6/7 | CD30: 6/7 | CE30: 6/7 | CF30: 6/7 | CG30: 6/7 | CH30: 6/7 | CI30: 6/7 | CJ30: 6/7 | CK30: 6/7 | CL30: 6/7 | CM30: 6/7 | CN30: 6/7 | CO30: 6/7 | CP30: 6/7 | CQ30: 6/7 | CR30: 6/7 | CS30: 6/7 | CT30: 6/7 | CU30: 6/7 | CV30: 6/7 | CW30: 6/7 | CX30: OR | CY30: OR
A31: Compleet ladingen | C31: ma,di,wo,do,vrij | E31: 3/4 | F31: 3/4 | G31: 3/4 | H31: 3/4 | I31: 3/4 | J31: 3/4 | K31: 3/4 | L31: 3/4 | M31: 3/4 | N31: 3/4 | O31: 4/5 | P31: 4/5 | Q31: 4/5 | R31: 4/5 | S31: 4/5 | T31: 4/5 | U31: 4/5 | V31: 4/5 | W31: 4/5 | X31: 4/5 | Y31: 4/5 | Z31: 4/5 | AA31: 4/5 | AB31: 4/5 | AC31: 4/5 | AD31: 4/5 | AE31: 4/5 | AF31: 4/5 | AG31: 4/5 | AH31: 4/5 | AI31: 4/5 | AJ31: 4/5 | AK31: 4/5 | AL31: 4/5 | AM31: 4/5 | AN31: 4/5 | AO31: 4/5 | AP31: 4/5 | AQ31: 4/5 | AR31: 4/5 | AS31: 5/6 | AT31: 5/6 | AU31: 5/6 | AV31: 5/6 | AW31: 4/5 | AX31: 4/5 | AY31: 4/5 | AZ31: 4/5 | BA31: 4/5 | BB31: 4/5 | BC31: 4/5 | BD31: 4/5 | BE31: 4/5 | BF31: 4/5 | BG31: 4/5 | BH31: 4/5 | BI31: 5/6 | BJ31: 5/6 | BK31: 5/6 | BL31: 5/6 | BM31: 5/6 | BN31: 5/6 | BO31: 5/6 | BP31: 5/6 | BQ31: 5/6 | BR31: 5/6 | BS31: 5/6 | BT31: 5/6 | BU31: 5/6 | BV31: 5/6 | BW31: 5/6 | BX31: 5/6 | BY31: 5/6 | BZ31: 5/6 | CA31: 5/6 | CB31: 5/6 | CC31: 5/6 | CD31: 5/6 | CE31: 5/6 | CF31: 5/6 | CG31: 5/6 | CH31: 5/6 | CI31: 5/6 | CJ31: 5/6 | CK31: 5/6 | CL31: 5/6 | CM31: 5/6 | CN31: 5/6 | CO31: 5/6 | CP31: 5/6 | CQ31: 5/6 | CR31: 5/6 | CS31: 5/6 | CT31: 5/6 | CU31: 5/6 | CV31: 5/6 | CW31: 5/6 | CX31: OR | CY31: OR
A33: Condities:
A34: * Tarief is niet geldig voor de eilanden

Sheet FR
A3: =Voorblad!A5 -> Team Freight Forwarding Logistics
A4: Export Frankrijk
A6: kg | B6: ldm | C6: euplt | D6: blkplt | E6: 1 | F6: 2 | G6: 3 | H6: 4 | I6: 5 | J6: 6 | K6: 7 | L6: 8 | M6: 9 | N6: 10 | O6: 11 | P6: 12 | Q6: 13 | R6: 14 | S6: 15 | T6: 16 | U6: 17 | V6: 18 | W6: 19 | X6: 20 | Y6: 21 | Z6: 22 | AA6: 23 | AB6: 24 | AC6: 25 | AD6: 26 | AE6: 27 | AF6: 28 | AG6: 29 | AH6: 30 | AI6: 31 | AJ6: 32 | AK6: 33 | AL6: 34 | AM6: 35 | AN6: 36 | AO6: 37 | AP6: 38 | AQ6: 39 | AR6: 40 | AS6: 41 | AT6: 42 | AU6: 43 | AV6: 44 | AW6: 45 | AX6: 46 | AY6: 47 | AZ6: 48 | BA6: 49 | BB6: 50 | BC6: 51 | BD6: 52 | BE6: 53 | BF6: 54 | BG6: 55 | BH6: 56 | BI6: 57 | BJ6: 58 | BK6: 59 | BL6: 60 | BM6: 61 | BN6: 62 | BO6: 63 | BP6: 64 | BQ6: 65 | BR6: 66 | BS6: 67 | BT6: 68 | BU6: 69 | BV6: 70 | BW6: 71 | BX6: 72 | BY6: 73 | BZ6: 74 | CA6: 75 | CB6: 76 | CC6: 77 | CD6: 78 | CE6: 79 | CF6: 80 | CG6: 81 | CH6: 82 | CI6: 83 | CJ6: 84 | CK6: 85 | CL6: 86 | CM6: 87 | CN6: 88 | CO6: 89 | CP6: 90 | CQ6: 91 | CR6: 92 | CS6: 93 | CT6: 94 | CU6: 95
A7: 300 | B7: 0.2 | C7: 0.5 | E7: 96 | F7: 90 | G7: 96 | H7: 104 | I7: 104 | J7: 104 | K7: 100 | L7: 90 | M7: 100 | N7: 91 | O7: 100 | P7: 100 | Q7: 100 | R7: 91 | S7: 100 | T7: 96 | U7: 96 | V7: 91 | W7: 96 | X7: 142 | Y7: 96 | Z7: 96 | AA7: 96 | AB7: 100 | AC7: 96 | AD7: 100 | AE7: 91 | AF7: 91 | AG7: 100 | AH7: 100 | AI7: 100 | AJ7: 100 | AK7: 100 | AL7: 100 | AM7: 96 | AN7: 91 | AO7: 91 | AP7: 96 | AQ7: 96 | AR7: 100 | AS7: 91 | AT7: 96 | AU7: 96 | AV7: 96 | AW7: 91 | AX7: 100 | AY7: 100 | AZ7: 100 | BA7: 96 | BB7: 96 | BC7: 91 | BD7: 96 | BE7: 96 | BF7: 96 | BG7: 96 | BH7: 96 | BI7: 96 | BJ7: 91 | BK7: 75 | BL7: 81 | BM7: 91 | BN7: 75 | BO7: 96 | BP7: 104 | BQ7: 104 | BR7: 104 | BS7: 96 | BT7: 96 | BU7: 96 | BV7: 96 | BW7: 96 | BX7: 96 | BY7: 96 | BZ7: 96 | CA7: 204 | CB7: 91 | CC7: 81 | CD7: 81 | CE7: 96 | CF7: 90 | CG7: 100 | CH7: 100 | CI7: 104 | CJ7: 100 | CK7: 96 | CL7: 96 | CM7: 96 | CN7: 96 | CO7: 91 | CP7: 96 | CQ7: 81 | CR7: 81 | CS7: 81 | CT7: 81 | CU7: 81
A8: 700 | B8: 0.4 | C8: 1 | E8: 147 | F8: 135 | G8: 147 | H8: 160 | I8: 160 | J8: 160 | K8: 153 | L8: 136 | M8: 153 | N8: 138 | O8: 153 | P8: 153 | Q8: 153 | R8: 138 | S8: 153 | T8: 148 | U8: 148 | V8: 138 | W8: 148 | X8: 234 | Y8: 148 | Z8: 148 | AA8: 148 | AB8: 153 | AC8: 148 | AD8: 153 | AE8: 138 | AF8: 138 | AG8: 153 | AH8: 153 | AI8: 153 | AJ8: 153 | AK8: 153 | AL8: 153 | AM8: 148 | AN8: 138 | AO8: 138 | AP8: 148 | AQ8: 148 | AR8: 153 | AS8: 138 | AT8: 148 | AU8: 148 | AV8: 148 | AW8: 138 | AX8: 153 | AY8: 153 | AZ8: 153 | BA8: 148 | BB8: 148 | BC8: 138 | BD8: 148 | BE8: 148 | BF8: 148 | BG8: 148 | BH8: 148 | BI8: 148 | BJ8: 138 | BK8: 114 | BL8: 123 | BM8: 138 | BN8: 114 | BO8: 148 | BP8: 160 | BQ8: 160 | BR8: 160 | BS8: 148 | BT8: 148 | BU8: 148 | BV8: 148 | BW8: 148 | BX8: 148 | BY8: 148 | BZ8: 148 | CA8: 247 | CB8: 138 | CC8: 123 | CD8: 123 | CE8: 148 | CF8: 136 | CG8: 153 | CH8: 153 | CI8: 160 | CJ8: 153 | CK8: 148 | CL8: 148 | CM8: 148 | CN8: 148 | CO8: 138 | CP8: 148 | CQ8: 123 | CR8: 123 | CS8: 123 | CT8: 123 | CU8: 123
A9: 875 | B9: 0.5 | D9: 1 | E9: 164 | F9: 156 | G9: 164 | H9: 180 | I9: 180 | J9: 180 | K9: 172 | L9: 156 | M9: 172 | N9: 158 | O9: 172 | P9: 172 | Q9: 172 | R9: 158 | S9: 172 | T9: 164 | U9: 164 | V9: 158 | W9: 164 | X9: 277 | Y9: 164 | Z9: 164 | AA9: 164 | AB9: 172 | AC9: 164 | AD9: 172 | AE9: 158 | AF9: 158 | AG9: 172 | AH9: 172 | AI9: 172 | AJ9: 172 | AK9: 172 | AL9: 172 | AM9: 164 | AN9: 158 | AO9: 158 | AP9: 164 | AQ9: 164 | AR9: 172 | AS9: 158 | AT9: 164 | AU9: 164 | AV9: 164 | AW9: 158 | AX9: 172 | AY9: 172 | AZ9: 172 | BA9: 164 | BB9: 164 | BC9: 158 | BD9: 164 | BE9: 164 | BF9: 164 | BG9: 164 | BH9: 164 | BI9: 164 | BJ9: 158 | BK9: 125 | BL9: 135 | BM9: 158 | BN9: 125 | BO9: 164 | BP9: 180 | BQ9: 180 | BR9: 180 | BS9: 164 | BT9: 164 | BU9: 164 | BV9: 164 | BW9: 164 | BX9: 164 | BY9: 164 | BZ9: 164 | CA9: 260 | CB9: 158 | CC9: 135 | CD9: 135 | CE9: 164 | CF9: 156 | CG9: 172 | CH9: 172 | CI9: 180 | CJ9: 172 | CK9: 164 | CL9: 164 | CM9: 164 | CN9: 164 | CO9: 158 | CP9: 164 | CQ9: 135 | CR9: 135 | CS9: 135 | CT9: 135 | CU9: 135
A10: 1050 | B10: 0.6 | E10: 197 | F10: 188 | G10: 197 | H10: 215 | I10: 215 | J10: 215 | K10: 205 | L10: 188 | M10: 205 | N10: 190 | O10: 205 | P10: 205 | Q10: 205 | R10: 190 | S10: 205 | T10: 197 | U10: 197 | V10: 190 | W10: 197 | X10: 327 | Y10: 197 | Z10: 197 | AA10: 197 | AB10: 205 | AC10: 197 | AD10: 205 | AE10: 190 | AF10: 190 | AG10: 205 | AH10: 205 | AI10: 205 | AJ10: 205 | AK10: 205 | AL10: 205 | AM10: 197 | AN10: 190 | AO10: 190 | AP10: 197 | AQ10: 197 | AR10: 205 | AS10: 190 | AT10: 197 | AU10: 197 | AV10: 197 | AW10: 190 | AX10: 205 | AY10: 205 | AZ10: 205 | BA10: 197 | BB10: 197 | BC10: 190 | BD10: 197 | BE10: 197 | BF10: 197 | BG10: 197 | BH10: 197 | BI10: 197 | BJ10: 190 | BK10: 150 | BL10: 161 | BM10: 190 | BN10: 150 | BO10: 197 | BP10: 215 | BQ10: 215 | BR10: 215 | BS10: 197 | BT10: 197 | BU10: 197 | BV10: 197 | BW10: 197 | BX10: 197 | BY10: 197 | BZ10: 197 | CA10: 286 | CB10: 190 | CC10: 161 | CD10: 161 | CE10: 197 | CF10: 188 | CG10: 205 | CH10: 205 | CI10: 215 | CJ10: 205 | CK10: 197 | CL10: 197 | CM10: 197 | CN10: 197 | CO10: 190 | CP10: 197 | CQ10: 161 | CR10: 161 | CS10: 161 | CT10: 161 | CU10: 161
A11: 1400 | B11: 0.8 | C11: 2 | E11: 261 | F11: 247 | G11: 261 | H11: 284 | I11: 284 | J11: 284 | K11: 272 | L11: 247 | M11: 272 | N11: 251 | O11: 272 | P11: 272 | Q11: 272 | R11: 251 | S11: 272 | T11: 261 | U11: 261 | V11: 251 | W11: 261 | X11: 426 | Y11: 261 | Z11: 261 | AA11: 261 | AB11: 272 | AC11: 261 | AD11: 272 | AE11: 251 | AF11: 251 | AG11: 272 | AH11: 272 | AI11: 272 | AJ11: 272 | AK11: 272 | AL11: 272 | AM11: 261 | AN11: 251 | AO11: 251 | AP11: 261 | AQ11: 261 | AR11: 272 | AS11: 251 | AT11: 261 | AU11: 261 | AV11: 261 | AW11: 251 | AX11: 272 | AY11: 272 | AZ11: 272 | BA11: 261 | BB11: 261 | BC11: 251 | BD11: 261 | BE11: 261 | BF11: 261 | BG11: 261 | BH11: 261 | BI11: 261 | BJ11: 251 | BK11: 198 | BL11: 215 | BM11: 251 | BN11: 198 | BO11: 261 | BP11: 284 | BQ11: 284 | BR11: 284 | BS11: 261 | BT11: 261 | BU11: 261 | BV11: 261 | BW11: 261 | BX11: 261 | BY11: 261 | BZ11: 261 | CA11: 338 | CB11: 251 | CC11: 215 | CD11: 215 | CE11: 261 | CF11: 247 | CG11: 272 | CH11: 272 | CI11: 284 | CJ11: 272 | CK11: 261 | CL11: 261 | CM11: 261 | CN11: 261 | CO11: 251 | CP11: 261 | CQ11: 215 | CR11: 215 | CS11: 215 | CT11: 215 | CU11: 215
A12: 1750 | B12: 1 | D12: 2 | E12: 293 | F12: 266 | G12: 293 | H12: 322 | I12: 322 | J12: 322 | K12: 310 | L12: 266 | M12: 310 | N12: 269 | O12: 310 | P12: 310 | Q12: 310 | R12: 269 | S12: 310 | T12: 293 | U12: 293 | V12: 269 | W12: 293 | X12: 501 | Y12: 293 | Z12: 293 | AA12: 293 | AB12: 310 | AC12: 293 | AD12: 310 | AE12: 269 | AF12: 269 | AG12: 310 | AH12: 310 | AI12: 310 | AJ12: 310 | AK12: 310 | AL12: 310 | AM12: 293 | AN12: 269 | AO12: 269 | AP12: 293 | AQ12: 293 | AR12: 310 | AS12: 269 | AT12: 293 | AU12: 293 | AV12: 293 | AW12: 269 | AX12: 310 | AY12: 310 | AZ12: 310 | BA12: 293 | BB12: 293 | BC12: 269 | BD12: 293 | BE12: 293 | BF12: 293 | BG12: 293 | BH12: 293 | BI12: 293 | BJ12: 269 | BK12: 219 | BL12: 237 | BM12: 269 | BN12: 219 | BO12: 293 | BP12: 322 | BQ12: 322 | BR12: 322 | BS12: 293 | BT12: 293 | BU12: 293 | BV12: 293 | BW12: 293 | BX12: 293 | BY12: 293 | BZ12: 293 | CA12: 361 | CB12: 269 | CC12: 237 | CD12: 237 | CE12: 293 | CF12: 266 | CG12: 310 | CH12: 310 | CI12: 322 | CJ12: 310 | CK12: 293 | CL12: 293 | CM12: 293 | CN12: 293 | CO12: 269 | CP12: 293 | CQ12: 237 | CR12: 237 | CS12: 237 | CT12: 237 | CU12: 237
A13: 2100 | B13: 1.2 | C13: 3 | E13: 343 | F13: 312 | G13: 343 | H13: 376 | I13: 376 | J13: 376 | K13: 362 | L13: 312 | M13: 362 | N13: 317 | O13: 362 | P13: 362 | Q13: 362 | R13: 317 | S13: 362 | T13: 343 | U13: 343 | V13: 317 | W13: 343 | X13: 594 | Y13: 343 | Z13: 343 | AA13: 343 | AB13: 362 | AC13: 343 | AD13: 362 | AE13: 317 | AF13: 317 | AG13: 362 | AH13: 362 | AI13: 362 | AJ13: 362 | AK13: 362 | AL13: 362 | AM13: 343 | AN13: 317 | AO13: 317 | AP13: 343 | AQ13: 343 | AR13: 362 | AS13: 317 | AT13: 343 | AU13: 343 | AV13: 343 | AW13: 317 | AX13: 362 | AY13: 362 | AZ13: 362 | BA13: 343 | BB13: 343 | BC13: 317 | BD13: 343 | BE13: 343 | BF13: 343 | BG13: 343 | BH13: 343 | BI13: 343 | BJ13: 317 | BK13: 258 | BL13: 281 | BM13: 317 | BN13: 258 | BO13: 343 | BP13: 376 | BQ13: 376 | BR13: 376 | BS13: 343 | BT13: 343 | BU13: 343 | BV13: 343 | BW13: 343 | BX13: 343 | BY13: 343 | BZ13: 343 | CA13: 404 | CB13: 317 | CC13: 281 | CD13: 281 | CE13: 343 | CF13: 312 | CG13: 362 | CH13: 362 | CI13: 376 | CJ13: 362 | CK13: 343 | CL13: 343 | CM13: 343 | CN13: 343 | CO13: 317 | CP13: 343 | CQ13: 281 | CR13: 281 | CS13: 281 | CT13: 281 | CU13: 281
A14: 2625 | B14: 1.5 | D14: 3 | E14: 413 | F14: 373 | G14: 413 | H14: 456 | I14: 456 | J14: 456 | K14: 436 | L14: 373 | M14: 436 | N14: 378 | O14: 436 | P14: 436 | Q14: 436 | R14: 378 | S14: 436 | T14: 413 | U14: 413 | V14: 378 | W14: 413 | X14: 714 | Y14: 413 | Z14: 413 | AA14: 413 | AB14: 436 | AC14: 413 | AD14: 436 | AE14: 378 | AF14: 378 | AG14: 436 | AH14: 436 | AI14: 436 | AJ14: 436 | AK14: 436 | AL14: 436 | AM14: 413 | AN14: 378 | AO14: 378 | AP14: 413 | AQ14: 413 | AR14: 436 | AS14: 378 | AT14: 413 | AU14: 413 | AV14: 413 | AW14: 378 | AX14: 436 | AY14: 436 | AZ14: 436 | BA14: 413 | BB14: 413 | BC14: 378 | BD14: 413 | BE14: 413 | BF14: 413 | BG14: 413 | BH14: 413 | BI14: 413 | BJ14: 378 | BK14: 306 | BL14: 331 | BM14: 378 | BN14: 306 | BO14: 413 | BP14: 456 | BQ14: 456 | BR14: 456 | BS14: 413 | BT14: 413 | BU14: 413 | BV14: 413 | BW14: 413 | BX14: 413 | BY14: 413 | BZ14: 413 | CA14: 455 | CB14: 378 | CC14: 331 | CD14: 331 | CE14: 413 | CF14: 373 | CG14: 436 | CH14: 436 | CI14: 456 | CJ14: 436 | CK14: 413 | CL14: 413 | CM14: 413 | CN14: 413 | CO14: 378 | CP14: 413 | CQ14: 331 | CR14: 331 | CS14: 331 | CT14: 331 | CU14: 331
A15: 2800 | B15: 1.6 | C15: 4 | E15: 444 | F15: 402 | G15: 444 | H15: 487 | I15: 487 | J15: 487 | K15: 468 | L15: 402 | M15: 468 | N15: 409 | O15: 468 | P15: 468 | Q15: 468 | R15: 409 | S15: 468 | T15: 444 | U15: 444 | V15: 409 | W15: 444 | X15: 778 | Y15: 444 | Z15: 444 | AA15: 444 | AB15: 468 | AC15: 444 | AD15: 468 | AE15: 409 | AF15: 409 | AG15: 468 | AH15: 468 | AI15: 468 | AJ15: 468 | AK15: 468 | AL15: 468 | AM15: 444 | AN15: 409 | AO15: 409 | AP15: 444 | AQ15: 444 | AR15: 468 | AS15: 409 | AT15: 444 | AU15: 444 | AV15: 444 | AW15: 409 | AX15: 468 | AY15: 468 | AZ15: 468 | BA15: 444 | BB15: 444 | BC15: 409 | BD15: 444 | BE15: 444 | BF15: 444 | BG15: 444 | BH15: 444 | BI15: 444 | BJ15: 409 | BK15: 333 | BL15: 361 | BM15: 409 | BN15: 333 | BO15: 444 | BP15: 487 | BQ15: 487 | BR15: 487 | BS15: 444 | BT15: 444 | BU15: 444 | BV15: 444 | BW15: 444 | BX15: 444 | BY15: 444 | BZ15: 444 | CA15: 484 | CB15: 409 | CC15: 361 | CD15: 361 | CE15: 444 | CF15: 402 | CG15: 468 | CH15: 468 | CI15: 487 | CJ15: 468 | CK15: 444 | CL15: 444 | CM15: 444 | CN15: 444 | CO15: 409 | CP15: 444 | CQ15: 361 | CR15: 361 | CS15: 361 | CT15: 361 | CU15: 361
A16: 3500 | B16: 2 | C16: 5 | D16: 4 | E16: 489 | F16: 443 | G16: 489 | H16: 536 | I16: 536 | J16: 536 | K16: 514 | L16: 443 | M16: 514 | N16: 451 | O16: 514 | P16: 514 | Q16: 514 | R16: 451 | S16: 514 | T16: 489 | U16: 489 | V16: 451 | W16: 489 | X16: OR | Y16: 489 | Z16: 489 | AA16: 489 | AB16: 514 | AC16: 489 | AD16: 514 | AE16: 451 | AF16: 451 | AG16: 514 | AH16: 514 | AI16: 514 | AJ16: 514 | AK16: 514 | AL16: 514 | AM16: 489 | AN16: 451 | AO16: 451 | AP16: 489 | AQ16: 489 | AR16: 514 | AS16: 451 | AT16: 489 | AU16: 489 | AV16: 489 | AW16: 451 | AX16: 514 | AY16: 514 | AZ16: 514 | BA16: 489 | BB16: 489 | BC16: 451 | BD16: 489 | BE16: 489 | BF16: 489 | BG16: 489 | BH16: 489 | BI16: 489 | BJ16: 451 | BK16: 366 | BL16: 399 | BM16: 451 | BN16: 366 | BO16: 489 | BP16: 536 | BQ16: 536 | BR16: 536 | BS16: 489 | BT16: 489 | BU16: 489 | BV16: 489 | BW16: 489 | BX16: 489 | BY16: 489 | BZ16: 489 | CA16: OR | CB16: 451 | CC16: 399 | CD16: 399 | CE16: 489 | CF16: 443 | CG16: 514 | CH16: 514 | CI16: 536 | CJ16: 514 | CK16: 489 | CL16: 489 | CM16: 489 | CN16: 489 | CO16: 451 | CP16: 489 | CQ16: 399 | CR16: 399 | CS16: 399 | CT16: 399 | CU16: 399
A17: 4200 | B17: 2.4 | C17: 6 | E17: 539 | F17: 459 | G17: 539 | H17: 637 | I17: 627 | J17: 667 | K17: 579 | L17: 460 | M17: 637 | N17: 485 | O17: 627 | P17: 603 | Q17: 627 | R17: 483 | S17: 579 | T17: 574 | U17: 574 | V17: 489 | W17: 579 | X17: OR | Y17: 513 | Z17: 548 | AA17: 548 | AB17: 579 | AC17: 533 | AD17: 579 | AE17: 472 | AF17: 472 | AG17: 627 | AH17: 603 | AI17: 627 | AJ17: 627 | AK17: 579 | AL17: 603 | AM17: 518 | AN17: 489 | AO17: 489 | AP17: 579 | AQ17: 541 | AR17: 603 | AS17: 491 | AT17: 579 | AU17: 579 | AV17: 518 | AW17: 471 | AX17: 603 | AY17: 603 | AZ17: 603 | BA17: 518 | BB17: 513 | BC17: 472 | BD17: 507 | BE17: 512 | BF17: 508 | BG17: 508 | BH17: 569 | BI17: 505 | BJ17: 489 | BK17: 382 | BL17: 413 | BM17: 491 | BN17: 382 | BO17: 548 | BP17: 637 | BQ17: 637 | BR17: 637 | BS17: 509 | BT17: 503 | BU17: 548 | BV17: 504 | BW17: 518 | BX17: 512 | BY17: 579 | BZ17: 548 | CA17: OR | CB17: 472 | CC17: 433 | CD17: 429 | CE17: 518 | CF17: 459 | CG17: 627 | CH17: 627 | CI17: 627 | CJ17: 603 | CK17: 518 | CL17: 518 | CM17: 548 | CN17: 509 | CO17: 491 | CP17: 512 | CQ17: 433 | CR17: 429 | CS17: 422 | CT17: 429 | CU17: 429
A18: 4375 | B18: 2.5 | D18: 5 | E18: 572 | F18: 464 | G18: 572 | H18: 663 | I18: 656 | J18: 686 | K18: 603 | L18: 466 | M18: 663 | N18: 492 | O18: 656 | P18: 631 | Q18: 656 | R18: 489 | S18: 603 | T18: 592 | U18: 592 | V18: 496 | W18: 603 | X18: OR | Y18: 521 | Z18: 571 | AA18: 571 | AB18: 603 | AC18: 545 | AD18: 603 | AE18: 481 | AF18: 481 | AG18: 656 | AH18: 631 | AI18: 656 | AJ18: 656 | AK18: 603 | AL18: 631 | AM18: 539 | AN18: 496 | AO18: 496 | AP18: 603 | AQ18: 560 | AR18: 631 | AS18: 499 | AT18: 603 | AU18: 603 | AV18: 539 | AW18: 479 | AX18: 631 | AY18: 631 | AZ18: 631 | BA18: 539 | BB18: 521 | BC18: 481 | BD18: 514 | BE18: 521 | BF18: 515 | BG18: 515 | BH18: 627 | BI18: 509 | BJ18: 496 | BK18: 386 | BL18: 417 | BM18: 499 | BN18: 388 | BO18: 571 | BP18: 663 | BQ18: 663 | BR18: 663 | BS18: 517 | BT18: 507 | BU18: 571 | BV18: 509 | BW18: 539 | BX18: 521 | BY18: 603 | BZ18: 596 | CA18: OR | CB18: 482 | CC18: 441 | CD18: 432 | CE18: 539 | CF18: 464 | CG18: 656 | CH18: 656 | CI18: 656 | CJ18: 631 | CK18: 539 | CL18: 539 | CM18: 571 | CN18: 517 | CO18: 499 | CP18: 521 | CQ18: 441 | CR18: 432 | CS18: 427 | CT18: 432 | CU18: 432
A19: 4900 | B19: 2.8 | C19: 7 | E19: 605 | F19: 470 | G19: 605 | H19: 708 | I19: 703 | J19: 708 | K19: 646 | L19: 472 | M19: 708 | N19: 497 | O19: 703 | P19: 672 | Q19: 703 | R19: 493 | S19: 646 | T19: 611 | U19: 611 | V19: 503 | W19: 646 | X19: OR | Y19: 530 | Z19: 611 | AA19: 611 | AB19: 646 | AC19: 554 | AD19: 646 | AE19: 490 | AF19: 490 | AG19: 703 | AH19: 672 | AI19: 703 | AJ19: 703 | AK19: 646 | AL19: 672 | AM19: 576 | AN19: 503 | AO19: 503 | AP19: 646 | AQ19: 576 | AR19: 672 | AS19: 509 | AT19: 646 | AU19: 646 | AV19: 576 | AW19: 486 | AX19: 672 | AY19: 672 | AZ19: 672 | BA19: 576 | BB19: 530 | BC19: 490 | BD19: 519 | BE19: 530 | BF19: 522 | BG19: 522 | BH19: 686 | BI19: 513 | BJ19: 503 | BK19: 392 | BL19: 422 | BM19: 509 | BN19: 393 | BO19: 611 | BP19: 708 | BQ19: 708 | BR19: 708 | BS19: 524 | BT19: 514 | BU19: 611 | BV19: 517 | BW19: 576 | BX19: 530 | BY19: 646 | BZ19: 646 | CA19: OR | CB19: 492 | CC19: 450 | CD19: 435 | CE19: 576 | CF19: 470 | CG19: 703 | CH19: 703 | CI19: 703 | CJ19: 672 | CK19: 576 | CL19: 576 | CM19: 611 | CN19: 524 | CO19: 509 | CP19: 530 | CQ19: 450 | CR19: 435 | CS19: 432 | CT19: 435 | CU19: 435
A20: 5250 | B20: 3 | D20: 6 | E20: 634 | F20: 476 | G20: 634 | H20: 759 | I20: 751 | J20: 759 | K20: 691 | L20: 477 | M20: 759 | N20: 503 | O20: 751 | P20: 723 | Q20: 751 | R20: 497 | S20: 691 | T20: 655 | U20: 655 | V20: 539 | W20: 691 | X20: OR | Y20: 539 | Z20: 655 | AA20: 655 | AB20: 691 | AC20: 565 | AD20: 691 | AE20: 497 | AF20: 497 | AG20: 743 | AH20: 723 | AI20: 751 | AJ20: 751 | AK20: 691 | AL20: 723 | AM20: 618 | AN20: 539 | AO20: 539 | AP20: 691 | AQ20: 618 | AR20: 723 | AS20: 520 | AT20: 691 | AU20: 691 | AV20: 605 | AW20: 497 | AX20: 723 | AY20: 723 | AZ20: 723 | BA20: 605 | BB20: 539 | BC20: 497 | BD20: 524 | BE20: 539 | BF20: 528 | BG20: 528 | BH20: 719 | BI20: 515 | BJ20: 539 | BK20: 397 | BL20: 426 | BM20: 520 | BN20: 398 | BO20: 655 | BP20: 759 | BQ20: 759 | BR20: 759 | BS20: 532 | BT20: 521 | BU20: 655 | BV20: 523 | BW20: 618 | BX20: 539 | BY20: 691 | BZ20: 691 | CA20: OR | CB20: 501 | CC20: 456 | CD20: 439 | CE20: 618 | CF20: 475 | CG20: 751 | CH20: 751 | CI20: 751 | CJ20: 723 | CK20: 618 | CL20: 618 | CM20: 655 | CN20: 532 | CO20: 520 | CP20: 539 | CQ20: 456 | CR20: 439 | CS20: 437 | CT20: 439 | CU20: 439
